Workbook

Sheet Resultados da organização
A1: P.BORGES
B3: FINANCEIRO | M3: PACE | P3: OPERAÇÕES
E4: P.Borges | F4: Região | G4: PBvsRegião | H4: Tipologia | I4: PBvsTipo | J4: Nacional | K4: PBvsNac | M4: 20 | N4: 32 | S4: P.Borges | U4: Nacional/Objetivo | W4: Variação | X4: LY | Y4: YTD vs LY
B5: Crescimento de vendas | E5: 0.1184 | F5: 0.0635 | G5: =(E5-F5)*100 -> 5.49 | H5: 0.0475 | I5: =(E5-H5)*100 -> 7.09 | J5: 0.073 | K5: =(E5-J5)*100 -> 4.54 | P5: Tempos de Serviço | S5: 105 | U5: 95 | W5: =S5-U5 -> 10 | X5: 110 | Y5: =S5-X5 -> -5
B6: Crescimento de GC's | E6: 0.0411 | F6: 0.0231 | G6: =(E6-F6)*100 -> 1.8 | H6: 0.0053 | I6: =(E6-H6)*100 -> 3.58 | J6: 0.0263 | K6: =(E6-J6)*100 -> 1.48 | M6: 0.88 | N6: 0.94 | P6: Tempos Delivery | S6: =6.1*60 -> 366 | U6: =5.1*60 -> 306 | W6: =S6-U6 -> 60 | X6: =6.8*60 -> 408 | Y6: =S6-X6 -> -42
B7: Crescimento Delivery | E7: 0.1926 | F7: 0.1152 | G7: =(E7-F7)*100 -> 7.74 | H7: 0.0483 | I7: =(E7-H7)*100 -> 14.43 | J7: 0.1623 | K7: =(E7-J7)*100 -> 3.03 | P7: Fastinsight | S7: 0.974 | U7: 0.941 | W7: =(S7-U7)*100 -> 3.3 | X7: 0.951 | Y7: =(S7-X7)*100 -> 2.3
B8: Crescimento GC's Delivery | E8: 0.1055 | F8: 0.091 | G8: =(E8-F8)*100 -> 1.45 | H8: 0.0318 | I8: =(E8-H8)*100 -> 7.37 | J8: 0.1095 | K8: =(E8-J8)*100 -> -0.4 | P8: Turnover | U8: 0.6 | W8: =S8-U8 -> -0.6
B9: Peso Delivery | E9: 0.525 | F9: 0.289 | G9: =(E9-F9)*100 -> 23.6 | H9: 0.279 | I9: =(E9-H9)*100 -> 24.6 | J9: 0.181 | K9: =(E9-J9)*100 -> 34.4 | P9: Staffing | U9: 0.35 | W9: =S9-U9 -> -0.35
B10: Peso MOP | E10: 0.0036 | F10: 0.0072 | G10: =(E10-F10)*100 -> -0.36 | H10: 0.007 | I10: =(E10-H10)*100 -> -0.34 | J10: 0.0093 | K10: =(E10-J10)*100 -> -0.57 | P10: BSV | U10: 1 | W10: =S10-U10 -> -1
M11: Vendas YTD
B12: *Atualizado 1-8 | L12: 2024 | M12: 2525592 | N12: Variação
L13: 2025 | M13: 2824671 | N13: =M13-M12 -> 299079 | O13: =N13/M12 -> 0.11841936
F15: Janeiro | G15: Fevereiro | H15: Março | I15: Abril | J15: Maio | K15: Junho | L15: Julho | M15: Agosto | N15: Setembro | O15: Outubro | P15: Novembro | Q15: Dezembro | R15: YTD | S15: LY | T15: Variação
C16: Crescimento de vendas | R16: =E5 -> 0.1184 | T16: =R16-S16 -> 0.1184
C17: Crescimento de GC's | R17: =E6 -> 0.0411 | T17: =R17-S17 -> 0.0411
C18: Crescimento Delivery | R18: =E7 -> 0.1926 | T18: =R18-S18 -> 0.1926
C19: Crescimento GC's Delivery | R19: =E8 -> 0.1055 | T19: =R19-S19 -> 0.1055
C20: Peso Delivery | F20: =(Serviço!C71+Serviço!C82)/(Serviço!C81+Serviço!C70) -> 0.57534934 | G20: =(Serviço!D71+Serviço!D82)/(Serviço!D81+Serviço!D70) -> 0.48743466 | H20: =(Serviço!E71+Serviço!E82)/(Serviço!E81+Serviço!E70) -> 0.55094074 | I20: =(Serviço!F71+Serviço!F82)/(Serviço!F81+Serviço!F70) -> 0.48917944 | J20: =(Serviço!G71+Serviço!G82)/(Serviço!G81+Serviço!G70) -> 0.51277637 | K20: =(Serviço!H71+Serviço!H82)/(Serviço!H81+Serviço!H70) -> 0.51137935 | L20: =(Serviço!I71+Serviço!I82)/(Serviço!I81+Serviço!I70) -> 0.47767429 | M20: =(Serviço!J71+Serviço!J82)/(Serviço!J81+Serviço!J70) -> 0.45997226 | ... R20: =(Serviço!O71+Serviço!O82)/(Serviço!O81+Serviço!O70) -> 0.51384802 | T20: =R20-S20 -> 0.51384802
C21: Peso MOP | F21: 0.0039 | G21: 0.0033 | H21: 0.0034 | I21: 0.0038 | J21: 0.0038 | K21: =(Serviço!H88+Serviço!H77)/(Serviço!H70+Serviço!H81) -> 0.0039636347 | L21: =(Serviço!I88+Serviço!I77)/(Serviço!I70+Serviço!I81) -> 0.0040832965 | M21: =(Serviço!J88+Serviço!J77)/(Serviço!J70+Serviço!J81) -> 0.003587231 | N21: =(Serviço!K88+Serviço!K77)/(Serviço!K70+Serviço!K81) -> 0.0041365766 | O21: =(Serviço!L88+Serviço!L77)/(Serviço!L70+Serviço!L81) -> 0.0034680251 | P21: =(Serviço!M88+Serviço!M77)/(Serviço!M70+Serviço!M81) -> 0.0030682228 | Q21: =(Serviço!N88+Serviço!N77)/(Serviço!N70+Serviço!N81) -> 0.0044746874 | R21: =(Serviço!O88+Serviço!O77)/(Serviço!O70+Serviço!O81) -> 0.0038939401
C22: Tempos de Serviço | F22: =Serviço!O9 -> 110 | G22: =Serviço!P9 -> 110 | H22: =Serviço!Q9 -> 114 | I22: =Serviço!R9 -> 117 | J22: =Serviço!S9 -> 119 | K22: =Serviço!T9 -> 123 | L22: =Serviço!U9 -> 145 | M22: =Serviço!V9 -> 143 | ... R22: =Serviço!AA9 -> 111 | S22: 128 | T22: =R22-S22 -> -17
C23: Tempos de serviço Nacional | F23: 130 | G23: 136 | H23: 150 | I23: 156 | J23: 162 | T23: =R23-S23 -> 0
C24: Fastinsight | F24: 0.981 | G24: 0.98 | H24: 0.963 | I24: 0.974 | J24: 0.969 | T24: =R24-S24 -> 0
C25: Fastinsight Nacional | F25: 0.952 | G25: 0.947 | H25: 0.937 | I25: 0.935 | J25: 0.927 | T25: =R25-S25 -> 0
C26: Turnover | T26: =R26-S26 -> 0
C27: Staffing | T27: =R27-S27 -> 0
T28: =R28-S28 -> 0
F30: Janeiro | G30: Fevereiro | H30: Março | I30: Abril | J30: Maio | K30: Junho | L30: Julho | M30: Agosto | N30: Setembro | O30: Outubro | P30: Novembro | Q30: Dezembro | R30: YTD | S30: LY | T30: Variação
C31: Vendas PB | S31: 0.1669 | T31: =(R31-S31)*100 -> -16.69
C32: Vendas Região | S32: 0.1952 | T32: =(R32-S32)*100 -> -19.52
C33: PB vs Região | F33: =F31-F32 -> 0 | G33: =G31-G32 -> 0 | H33: =H31-H32 -> 0 | I33: =I31-I32 -> 0 | J33: =J31-J32 -> 0 | K33: =K31-K32 -> 0 | L33: =L31-L32 -> 0 | M33: =M31-M32 -> 0 | ... R33: =R31-R32 -> 0 | T33: =(R33-S33)*100 -> 0
C34: Vendas Tipologia (Free Stand) | S34: 0.1538 | T34: =(R34-S34)*100 -> -15.38
C35: PB vs Tipologia | F35: =F31-F34 -> 0 | G35: =G31-G34 -> 0 | H35: =H31-H34 -> 0 | I35: =I31-I34 -> 0 | J35: =J31-J34 -> 0 | K35: =K31-K34 -> 0 | L35: =L31-L34 -> 0 | M35: =M31-M34 -> 0 | ... R35: =R31-R34 -> 0 | T35: =(R35-S35)*100 -> 0
C36: Vendas Nacional | R36: 0.0852 | S36: 0.1952 | T36: =(R36-S36)*100 -> -11
C37: PB vs Nacional | F37: =F31-F36 -> 0 | G37: =G31-G36 -> 0 | H37: =H31-H36 -> 0 | I37: =I31-I36 -> 0 | J37: =J31-J36 -> 0 | K37: =K31-K36 -> 0 | L37: =L31-L36 -> 0 | M37: =M31-M36 -> 0 | ... R37: =R31-R36 -> -0.0852 | T37: =(R37-S37)*100 -> -8.52
C38: GC's PB | S38: 0.1074 | T38: =(R38-S38)*100 -> -10.74
C39: Gc's Região | S39: 0.1444 | T39: =(R39-S39)*100 -> -14.44
C40: Gc's Tipologia | S40: 0.0906 | T40: =(R40-S40)*100 -> -9.06
C41: Gc's Nacional | S41: 0.1444 | T41: =(R41-S41)*100 -> -14.44
C42: Delivery PB | F42: =F18 -> 0 | G42: =G18 -> 0 | H42: =H18 -> 0 | I42: =I18 -> 0 | J42: =J18 -> 0 | K42: =K18 -> 0 | L42: =L18 -> 0 | M42: =M18 -> 0 | ... R42: =R18 -> 0.1926 | S42: 0.1274 | T42: =(R42-S42)*100 -> 6.52
C43: Delivery Região | S43: 0.0976 | T43: =(R43-S43)*100 -> -9.76
C44: Delivery Nacional | S44: 0.1068 | T44: =(R44-S44)*100 -> -10.68
C45: Gc's Delivery PB | F45: =F19 -> 0 | G45: =G19 -> 0 | H45: =H19 -> 0 | I45: =I19 -> 0 | J45: =J19 -> 0 | K45: =K19 -> 0 | L45: =L19 -> 0 | M45: =M19 -> 0 | ... R45: =R19 -> 0.1055 | S45: 0.0516 | T45: =(R45-S45)*100 -> 5.39
C46: Gc's Delivery Região | S46: 0.0156 | T46: =(R46-S46)*100 -> -1.56
C47: Gc's Delivery Nacional | S47: 0.0267 | T47: =(R47-S47)*100 -> -2.67

Sheet Serviço
B2: TEMPOS DE SERVIÇO
B4: YTD | H4: DEZEMBRO
B5: AMADORA | C5: TEMPO | D5: VAR | E5: RANK | F5: Percentil | G5: OBJETIVO | H5: AMADORA | I5: TEMPO | J5: VAR | K5: RANK | L5: Percentil
B6: ALMOÇO | G6: 110 | H6: ALMOÇO | O6: Jan | P6: fev | Q6: mar | R6: Abr | S6: Mai | T6: Jun | U6: Jul | V6: Ago | W6: Set | X6: Out | Y6: Nov | Z6: Dez | AA6: YTD | AB6: LY
B7: JANTAR | H7: JANTAR | M7: R2P | N7: AMADORA | O7: 116 | P7: 115 | Q7: 122 | R7: 128 | S7: 132 | T7: 134 | U7: 151 | V7: 158 | W7: 133 | X7: 152 | Y7: 128 | AA7: 116 | AB7: 118
B8: DIA | C8: 133 | D8: -1 | E8: 17 | F8: =(E8/215) -> 0.079069767 | H8: DIA | I8: 123 | K8: 23 | L8: =(K8/215) -> 0.10697674 | N8: QUELUZ | O8: 100 | P8: 102 | Q8: 101 | R8: 101 | S8: 101 | T8: 107 | U8: 135 | V8: 113 | W8: 99 | X8: 104 | Y8: 122 | AA8: 103 | AB8: 100
B9: YTD | H9: DEZEMBRO | N9: P.BORGES | O9: 110 | P9: 110 | Q9: 114 | R9: 117 | S9: 119 | T9: 123 | U9: 145 | V9: 143 | W9: 125 | X9: 131 | Y9: 126 | AA9: 111 | AB9: 110
B10: QUELUZ | C10: TEMPO | D10: VAR | E10: RANK | F10: Percentil | G10: OBJETIVO | H10: QUELUZ | I10: TEMPO | J10: VAR | K10: RANK | L10: Percentil | M10: Delivery | N10: AMADORA | O10: 19.6 | P10: 19.3 | Q10: 19.7 | R10: 18.4 | S10: 16.7 | T10: 18.5 | U10: 18.6 | V10: 18.2 | W10: 17.7 | X10: 19.3
B11: ALMOÇO | G11: 110 | H11: ALMOÇO | N11: QUELUZ | O11: 18.6 | P11: 18.8 | Q11: 19.7 | R11: 18.8 | S11: 17.6 | T11: 19.2 | U11: 21.2 | V11: 18.9 | W11: 17.8 | X11: 19.3
B12: JANTAR | H12: JANTAR | N12: P.BORGES | O12: 19.1 | P12: 19.1 | Q12: 19.7 | R12: 18.5 | S12: 17.1 | T12: 18.2 | U12: 19.6 | V12: 18.5 | W12: 17.7 | X12: 19.3
B13: DIA | C13: 107 | D13: 1 | E13: 3 | F13: =(E13/215) -> 0.013953488 | H13: DIA | I13: 106 | K13: 9 | L13: =(K13/215) -> 0.041860465
B14: DELIVERY | H14: DELIVERY
B15: DELIVERY | C15: TEMPO | D15: VAR | E15: RANK | F15: Percentil | G15: NACIONAL | H15: DELIVERY | I15: TEMPO | J15: VAR | K15: RANK | L15: Percentil
B16: AMADORA | C16: 81 | D16: -1 | E16: 53 | F16: =(E16/215) -> 0.24651163 | G16: 170 | H16: AMADORA | I16: 65 | K16: 14 | L16: =(K16/215) -> 0.065116279
B17: QUELUZ | C17: 74 | D17: 2 | E17: 29 | F17: =(E17/215) -> 0.13488372 | H17: QUELUZ | I17: 79 | K17: 52 | L17: =(K17/215) -> 0.24186047
B19: QUALIDADE DO SERVIÇO
C21: FASTINSIGHT AMADORA | K21: FASTINSIGHT QUELUZ
C22: DEZEMBRO | G22: ANO | K22: DEZEMBRO | O22: ANO
C23: SG | D23: LIMPEZA | E23: SIMPATIA | F23: RAPIDEZ | G23: SG | I23: NPS | K23: SG | L23: LIMPEZA | M23: QUALIDADE | N23: RAPIDEZ | O23: SG | Q23: NPS
C24: 96.55 | D24: 97.78 | E24: 93.33 | F24: 93.33 | G24: 95.87 | I24: 96.79 | K24: 98.51 | L24: 100 | M24: 100 | N24: 100
C26: SG | D26: Jan | E26: Fev | F26: Mar | G26: Abr | H26: Mai | I26: Jun | J26: Jul | K26: Ago | L26: Set | M26: Out | N26: Nov | O26: Dez | P26: YTD | Q26: LY | R26: OBJETIVO | S26: NACIONAL
C27: Amadora | D27: 94.96 | E27: 96.5 | F27: 95.74 | G27: 97.03 | H27: 96.13 | I27: 95.16 | J27: 95.87 | K27: 96.43 | L27: 95.47 | M27: 96.4 | N27: 95.39 | O27: 93.3 | P27: 95.34 | Q27: 94.76 | R27: 95 | S27: 90.65
C28: Queluz | D28: 96.86 | E28: 97.68 | F28: 96.41 | G28: 96.66 | H28: 97.46 | I28: 98.35 | J28: 97.19 | K28: 97.45 | L28: 98.28 | M28: 96.63 | N28: 96.63 | O28: 100 | P28: 97.24 | Q28: 95.6 | R28: 95
C30: RÁCIO DE RECLAMAÇÕES
C31: GC's Amadora | E31: 275602 | F31: Amadora | G31: SALA | H31: DELIVERY | I31: TOTAL | J31: Queluz | K31: SALA | L31: DELIVERY | M31: TOTAL | N31: LY | O31: AMADORA | P31: QUELUZ | Q31: PBORGES
C32: GC's Queluz | E32: 173866 | F32: QUALIDADE | I32: =SUM(G32:H32) -> 0 | J32: QUALIDADE | M32: =SUM(K32:L32) -> 0 | N32: SALA | O32: 2 | P32: 3 | Q32: =O32+P32 -> 5
C33: P.Borges | E33: =((SUM(I32:I34)+SUM(M32:M34))/(E31+E32))*100000 -> 0.22248525 | F33: SERVIÇO | I33: =SUM(G33:H33) -> 0 | J33: SERVIÇO | L33: 1 | M33: =SUM(K33:L33) -> 1 | N33: DELIVERY | O33: 2 | P33: 6 | Q33: =O33+P33 -> 8
F34: LIMPEZA | I34: =SUM(G34:H34) -> 0 | J34: LIMPEZA | M34: =SUM(K34:L34) -> 0 | N34: GC'S | O34: 298405 | P34: 191877 | Q34: =O34+P34 -> 490282
F35: RÁCIO | G35: =(SUM(G32:G34)/E31)*100000 -> 0 | H35: =(SUM(H32:H34)/E31)*100000 -> 0 | I35: =(SUM(I32:I34)/E31)*100000 -> 0 | J35: RÁCIO | K35: =(SUM(K32:K34)/E32)*100000 -> 0 | L35: =(SUM(L32:L34)/E32)*100000 -> 0.57515558 | M35: =(SUM(M32:M34)/E32)*100000 -> 0.57515558 | N35: RÁCIO | O35: 1.34 | P35: 4.69 | Q35: 2.65
D37: Reclamações | E37: Jan | F37: Fev | G37: Mar | H37: Abr | I37: Mai | J37: Jun | K37: Jul | L37: Ago | M37: Set | N37: Out | O37: Nov | P37: Dez | Q37: OBJETIVO | S37: NACIONAL
D38: Amadora | E38: 0 | F38: 0 | G38: 0 | H38: 0 | I38: 0 | J38: 0 | K38: 0 | L38: 0 | M38: 0 | Q38: 2 | R38: 4 | S38: LR 1,26
D39: Queluz | E39: 0 | F39: 0 | G39: 0 | H39: 0 | I39: 0 | J39: 1 | K39: 0 | L39: 0 | M39: 0 | Q39: 2 | R39: 3 | S39: CC 0,91
E42: COMUNICAÇÃO DIGITAL
E43: Amadora | F43: VAR | G43: Ava. Total | H43: Ava. Mês | I43: Queluz | J43: Queluz | K43: VAR | L43: Ava. Total | M43: Ava. Mês | N43: LY | O43: Amadora | P43: QUELUZ
E44: 4.2 | F44: 0 | G44: 3459 | H44: 105 | J44: 4.3 | K44: 0 | L44: 3094 | M44: 33 | O44: 4.1 | P44: 4.2
E45: 4.2 | G45: 4004 | H45: 39 | J45: 4.3 | L45: 3605 | M45: 35 | O45: 4.2 | P45: 4.3
D46: UBER | E46: 4.2 | J46: 4.3 | N46: UBER | O46: 4.5 | P46: 4.5
D48: Google | E48: Jan | F48: Fev | G48: Mar | H48: Abr | I48: Mai | J48: Jun | K48: Jul | L48: Ago | M48: Set | N48: Out | O48: Nov | P48: Dez | Q48: OBJETIVO
D49: Amadora | E49: 4.2 | F49: 4.2 | G49: 4.2 | H49: 4.2 | I49: 4.3 | J49: 4.2 | K49: 4.2 | L49: 4.2 | M49: 4.2 | N49: 4.2 | Q49: 4.2
D50: Queluz | E50: 4.3 | F50: 4.3 | G50: 4.3 | H50: 4.3 | I50: 4.3 | J50: 4.3 | K50: 4.3 | L50: 4.3 | M50: 4.3 | N50: 4.3 | Q50: 4.3
D52: Mlovers | E52: Jan | F52: Fev | G52: Mar | H52: Abr | I52: Mai | J52: Jun | K52: Jul | L52: Ago | M52: Set | N52: Out | O52: Nov | P52: Dez | Q52: OBJETIVO
D53: Amadora | E53: 0.113 | F53: 0.13 | G53: 0.149 | H53: 0.128 | I53: 0.135 | J53: 0.113 | K53: 10.49 | L53: 7.82 | M53: 11.33 | N53: 12.89 | O53: 11.67 | P53: 11.65 | Q53: 0.14
D54: Queluz | E54: 0.145 | F54: 0.169 | G54: 0.184 | H54: 0.172 | I54: 0.164 | J54: 0.15 | K54: 13.7 | L54: 11.23 | M54: 13.37 | N54: 15.4 | O54: 15.01 | P54: 15.8 | Q54: 0.18
B56: 20/32 | C56: Jan | D56: Fev | E56: Mar | F56: Abr | G56: Mai | H56: Jun | I56: Jul | J56: Ago | K56: Set | L56: Out | M56: Nov | N56: Dez | O56: YTD | P56: LY | Q56: OBJETIVO | R56: NACIONAL
B57: ESTRELAS | C57: 4.1 | D57: 4 | E57: 4.1 | F57: 4.3 | G57: 4.3 | H57: 4.3 | I57: 4.1 | J57: 4.1 | K57: 4.2 | L57: 4.2 | M57: 4.3 | O57: 4.2 | P57: 4.2 | Q57: 4.5
B58: TEMPOS | C58: 5.8 | D58: 5 | E58: 4.7 | F58: 5.3 | G58: 4.5 | H58: 4.8 | I58: 5.2 | J58: 5.7 | K58: 5.4 | L58: 6.9 | M58: 5.3 | O58: 5.7 | P58: 6.1 | Q58: 6.5 | R58: 5.4
B59: INEXATIDÃO | C59: 0.029 | D59: 0.018 | E59: 0.018 | F59: 0.018 | G59: 0.021 | H59: 0.023 | I59: 0.022 | J59: 0.025 | K59: 0.021 | L59: 0.03 | M59: 0.018 | O59: 0.026 | P59: 0.0305 | Q59: 0.015
B60: AVA. PRODUTO | E60: 0.79 | F60: 0.8 | G60: 0.8 | H60: 0.81 | I60: 0.81 | J60: 0.79 | K60: 0.78 | Q60: 0.9
B61: TEMPO TOTAL | C61: 19.6 | D61: 19.2 | E61: 19.3 | F61: 19.5 | G61: 16.4 | H61: 17.5 | I61: 18.5 | J61: 18.6 | K61: 17.5 | L61: 19.7 | M61: 18.9 | O61: 18.6 | P61: 19.9 | Q61: 21 | R61: 20.7
B62: ESTRELAS | C62: 4.1 | D62: 3.9 | E62: 4 | F62: 4.3 | G62: 4.2 | H62: 4.3 | I62: 3.9 | J62: 4.1 | K62: 4.2 | L62: 4.1 | M62: 4 | O62: 4.1 | P62: 4.2 | Q62: 4.5
B63: TEMPOS | C63: 5 | D63: 5 | E63: 5.2 | F63: 5.3 | G63: 5.2 | H63: 5.6 | I63: 6.5 | J63: 6 | K63: 5.6 | L63: 5.3 | M63: 5.9 | O63: 5.9 | P63: 5.9 | Q63: 6.5
B64: INEXATIDÃO | C64: 0.025 | D64: 0.017 | E64: 0.014 | F64: 0.017 | G64: 0.019 | H64: 0.02 | I64: 0.029 | J64: 0.0205 | K64: 0.017 | L64: 0.018 | M64: 0.023 | O64: 0.023 | P64: 0.0261 | Q64: 0.015
B65: AVA. PRODUTO | E65: 0.73 | F65: 0.73 | G65: 0.75 | H65: 0.77 | I65: 0.78 | J65: 0.75 | K65: 0.77 | L65: 0.76 | Q65: 0.9
B66: TEMPO TOTAL | C66: 17.8 | D66: 18.7 | E66: 19.3 | F66: 19 | G66: 17.4 | H66: 19.2 | I66: 21.2 | J66: 19.1 | K66: 17.5 | L66: 19.8 | M66: 20.4 | O66: 19 | P66: 19.6 | Q66: 21
B68: VENDAS POR PLATAFORMA
B69: Amadora | C69: Jan | D69: Fev | E69: Mar | F69: Abr | G69: Mai | H69: Jun | I69: Jul | J69: Ago | K69: Set | L69: Out | M69: Nov | N69: Dez | O69: YTD | P69: LY | Q69: OBJETIVO
B70: TOTAIS | C70: 288945 | D70: 254163 | E70: 280532 | F70: 247258 | G70: 251597 | H70: 252397 | I70: 268928 | J70: 286413 | K70: 246748 | L70: 236241 | M70: 236196 | N70: 82979 | O70: =SUM(C70:N70) -> 2932397 | P70: 3244120 | Q70: =P70*(1+Q106) -> 3568532
B71: DELIVERY | C71: 172283 | D71: 128204 | E71: 157457 | F71: 121125 | G71: 131076 | H71: 128943 | I71: 126406 | J71: 124607 | K71: 127604 | L71: 122774 | M71: 129060 | N71: 45288 | O71: =SUM(C71:N71) -> 1514827 | P71: 1765626 | Q71: =P71*(1+Q107) -> 1818594.8
B72: % DELIVERY | C72: =C71/C70 -> 0.59624842 | D72: =D71/D70 -> 0.50441646 | E72: =E71/E70 -> 0.56128 | F72: =F71/F70 -> 0.48987293 | G72: =G71/G70 -> 0.52097601 | H72: =H71/H70 -> 0.51087374 | I72: =I71/I70 -> 0.47003659 | J72: =J71/J70 -> 0.43506056 | ... Q72: =Q71/Q70 -> 0.50961986
B73: SALA | C73: =C70-C71 -> 116662 | D73: =D70-D71 -> 125959 | E73: =E70-E71 -> 123075 | F73: =F70-F71 -> 126133 | G73: =G70-G71 -> 120521 | H73: =H70-H71 -> 123454 | I73: =I70-I71 -> 142522 | J73: =J70-J71 -> 161806 | ... N73: =N70-N71 -> 37691 | O73: =SUM(C73:N73) -> 1417570 | P73: =P70-P71 -> 1478494 | Q73: =Q70-Q71-Q77 -> 1739796.3
B74: % SALA | C74: =C73/C$70 -> 0.40375158 | D74: =D73/D$70 -> 0.49558354 | E74: =E73/E$70 -> 0.43872 | F74: =F73/F$70 -> 0.51012707 | G74: =G73/G$70 -> 0.47902399 | H74: =H73/H$70 -> 0.48912626 | I74: =I73/I$70 -> 0.52996341 | J74: =J73/J$70 -> 0.56493944 | ... O74: =O73/O$70 -> 0.48341681
B75: TAKE-AWAY | O75: =+SUM(C74:N74) -> 5.782207
B76: % TAKE-AWAY | C76: =C73/C70 -> 0.40375158 | D76: =D73/D70 -> 0.49558354 | E76: =E73/E70 -> 0.43872 | F76: =F73/F70 -> 0.51012707 | G76: =G73/G70 -> 0.47902399 | H76: =H73/H70 -> 0.48912626 | L76: =L73/L$70 -> 0.4803019 | M76: =M73/M$70 -> 0.45358939 | N76: =N73/N$70 -> 0.45422336 | P76: =P73/P70 -> 0.45574578
B77: MOP | C77: 1090 | D77: 631 | E77: 1021 | F77: 711 | G77: 976 | H77: 841 | I77: 970 | J77: 633 | K77: 751 | L77: 783 | M77: 661 | N77: 216 | O77: =SUM(C77:N77) -> 9284 | P77: 9219 | Q77: =P77*1.1 -> 10140.9
B78: % MOP | C78: =C77/C$70 -> 0.0037723442 | D78: =D77/D$70 -> 0.0024826588 | E78: =E77/E$70 -> 0.0036395135 | F78: =F77/F$70 -> 0.0028755389 | G78: =G77/G$70 -> 0.0038792195 | H78: =H77/H$70 -> 0.0033320523 | I78: =I77/I$70 -> 0.0036069134 | J78: =J77/J$70 -> 0.0022100952 | ... P78: =P77/P$70 -> 0.0028417568 | Q78: =Q77/Q70 -> 0.0028417568
B80: Queluz | C80: Jan | D80: Fev | E80: Mar | F80: Abr | G80: Mai | H80: Jun | I80: Jul | J80: Ago | K80: Set | L80: Out | M80: Nov | N80: Dez | O80: YTD | P80: LY | Q80: OBJETIVO
B81: TOTAIS | C81: 157396 | D81: 143160 | E81: 153168 | F81: 142879 | G81: 161979 | H81: 159094 | I81: 165280 | J81: 168534 | K81: 155517 | L81: 161680 | M81: 162732 | N81: 57366 | O81: =SUM(C81:N81) -> 1788785 | P81: 1812293 | Q81: =P81*(1+Q116) -> 1993522.3
B82: DELIVERY | C82: 84519 | D82: 65465 | E82: 81486 | F82: 69722 | G82: 80996 | H82: 81485 | I82: 81004 | J82: 84656 | K82: 80057 | L82: 83675 | M82: 87136 | N82: 30942 | O82: =SUM(C82:N82) -> 911143 | P82: 905089 | Q82: =P82*(1+Q117) -> 941292.56
B83: % DELIVERY | C83: =C82/C81 -> 0.53698315 | D83: =D82/D81 -> 0.45728555 | E83: =E82/E81 -> 0.53200407 | F83: =F82/F81 -> 0.48797934 | G83: =G82/G81 -> 0.50004013 | H83: =H82/H81 -> 0.51218148 | I83: =I82/I81 -> 0.49010165 | J83: =J82/J81 -> 0.50230814 | ... Q83: =Q82/Q81 -> 0.47217559
B84: SALA | C84: =C81-C82 -> 72877 | D84: =D81-D82 -> 77695 | E84: =E81-E82 -> 71682 | F84: =F81-F82 -> 73157 | G84: =G81-G82 -> 80983 | H84: =H81-H82 -> 77609 | I84: =I81-I82 -> 84276 | J84: =J81-J82 -> 83878 | ... N84: =N81-N82 -> 26424 | O84: =SUM(C84:N84) -> 877642 | P84: =P81-P82 -> 907204 | Q84: =Q81-Q82-Q88 -> 1041776.4
B85: % SALA | C85: =C84/C$81 -> 0.46301685 | D85: =D84/D$81 -> 0.54271445 | E85: =E84/E$81 -> 0.46799593 | F85: =F84/F$81 -> 0.51202066 | G85: =G84/G$81 -> 0.49995987 | H85: =H84/H$81 -> 0.48781852 | I85: =I84/I$81 -> 0.50989835 | J85: =J84/J$81 -> 0.49769186 | ... O85: =O84/O$81 -> 0.49063582
B86: TAKE-AWAY | O86: =+SUM(C85:N85) -> 5.8739663
B87: % TAKE-AWAY | C87: =C84/C81 -> 0.46301685 | D87: =D84/D81 -> 0.54271445 | E87: =E84/E81 -> 0.46799593 | F87: =F84/F81 -> 0.51202066 | G87: =G84/G81 -> 0.49995987 | H87: =H84/H81 -> 0.48781852 | I87: =I84/I81 -> 0.50989835 | J87: =J84/J81 -> 0.49769186 | ... P87: =P84/P81 -> 0.50058351
B88: MOP | C88: 1048 | D88: 458 | E88: 640 | F88: 834 | G88: 1043 | H88: 790 | I88: 803 | J88: 999 | K88: 913 | L88: 597 | M88: 563 | N88: 412 | O88: =SUM(C88:N88) -> 9100 | P88: 9503 | Q88: =P88*1.1 -> 10453.3
B89: % MOP | C89: =C88/C$81 -> 0.0066583649 | D89: =D88/D$81 -> 0.0031992177 | E89: =E88/E$81 -> 0.0041784185 | F89: =F88/F$81 -> 0.0058371069 | G89: =G88/G$81 -> 0.0064391063 | H89: =H88/H$81 -> 0.0049656178 | I89: =I88/I$81 -> 0.0048584221 | J89: =J88/J$81 -> 0.0059275873 | ... P89: =P88/P$81 -> 0.0052436333 | Q89: =Q88/Q81 -> 0.0052436333
B104: EVOLUÇÃO RELATIVA DE VENDAS
B105: 20/32 | C105: JANEIRO | D105: FEVEREIRO | E105: MARÇO | F105: ABRIL | G105: MAIO | H105: JUNHO | I105: JULHO | J105: AGOSTO | K105: SETEMBRO | L105: OUTUBRO | M105: NOVEMBRO | N105: DEZEMBRO | O105: ANO | P105: LY | Q105: OBJETIVO
B106: 20 vs 2024 | C106: 0.2134 | D106: 0.2094 | E106: 0.1435 | F106: -0.0822 | G106: -0.113 | H106: -0.087 | I106: -0.1377 | J106: -0.0697 | K106: -0.0817 | L106: -0.1251 | M106: -0.1651 | N106: -0.1236 | O106: 0.2236 | Q106: 0.1
B107: DELIVERY | C107: 0.3223 | D107: 0.3505 | E107: 0.1877 | F107: -0.1228 | G107: -0.1644 | H107: -0.1559 | I107: -0.1822 | J107: -0.1936 | K107: -0.1366 | L107: -0.2074 | M107: -0.211 | N107: -0.1668 | O107: 0.3335 | Q107: 0.03
B108: 20 vs 2019
B109: 32 vs 2024 | C109: 0.0819 | D109: 0.1379 | E109: 0.0313 | F109: 0.0593 | G109: 0.0629 | H109: 0.0767 | I109: 0.0584 | J109: 0.0861 | K109: 0.1032 | L109: 0.0527 | M109: -0.0279 | N109: 0.0033 | O109: 0.1091 | Q109: 0.06
B110: DELIVERY | C110: 0.1486 | D110: 0.2264 | E110: 0.0447 | F110: 0.1154 | G110: 0.0624 | H110: 0.088 | I110: 0.111 | J110: 0.1123 | K110: 0.1835 | L110: 0.061 | M110: -0.0111 | N110: 0.0584 | O110: 0.1648 | Q110: 0
B111: 32 vs 2023
B112: Nacional vs 2019 | Q112: 45061
B114: EVOLUÇÃO RELATIVA DAS GC'S
B115: 20/32 | C115: JANEIRO | D115: FEVEREIRO | E115: MARÇO | F115: ABRIL | G115: MAIO | H115: JUNHO | I115: JULHO | J115: AGOSTO | K115: SETEMBRO | L115: OUTUBRO | M115: NOVEMBRO | N115: DEZEMBRO | O115: ANO | P115: LY | Q115: OBJETIVO
B116: TOTAIS vs 2024 | C116: 0.1271 | D116: 0.1266 | E116: 0.0657 | F116: -0.1341 | G116: -0.1299 | H116: 0.0932 | I116: -0.1199 | J116: -0.0982 | K116: -0.1151 | L116: -0.1484 | M116: -0.2089 | N116: -0.2031 | O116: 0.1379 | Q116: 0.1
B117: DELIVERY | C117: 0.2841 | D117: 0.3171 | E117: 0.1418 | F117: -0.1762 | G117: -0.2244 | H117: -0.196 | I117: -0.235 | J117: -0.2403 | K117: -0.1809 | L117: 0.2477 | M117: -0.2665 | N117: -0.2505 | O117: 0.2984 | Q117: 0.04
B118: 20 vs 2019
B119: TOTAIS vs 2024 | C119: 0.0111 | D119: 0.0587 | E119: -0.0005 | F119: -0.0136 | G119: -0.0076 | H119: 0.0401 | I119: -0.0489 | J119: -0.0104 | K119: 0.0023 | L119: -0.0349 | M119: -0.1324 | N119: -0.1274 | O119: 0.0433 | Q119: 0.1
B120: DELIVERY | C120: 0.1127 | D120: 0.1775 | E120: -0.0172 | F120: 5.6 | G120: 0.0624 | H120: 0.0609 | I120: 0.0457 | J120: 0.0818 | K120: 0.1626 | L120: -0.0027 | M120: -0.0906 | N120: -0.0366 | O120: 0.1307 | Q120: 0.04
B121: 32 vs 2019
B122: Nacional vs 2019
C127: 20/32 | D127: JANEIRO | E127: FEVEREIRO | F127: MARÇO | G127: ABRIL | H127: MAIO | I127: JUNHO | J127: JULHO | K127: AGOSTO | L127: SETEMBRO | M127: OUTUBRO | N127: NOVEMBRO | O127: DEZEMBRO | P127: ANO
C128: Tempo serviço | D128: =IF(O7<$G6,"OK","NOK") -> NOK | E128: =IF(P7<$G6,"OK","NOK") -> NOK | F128: =IF(Q7<$G6,"OK","NOK") -> NOK | G128: =IF(R7<$G6,"OK","NOK") -> NOK | H128: =IF(S7<$G6,"OK","NOK") -> NOK | I128: =IF(T7<$G6,"OK","NOK") -> NOK | J128: =IF(U7<$G6,"OK","NOK") -> NOK | K128: =IF(V7<$G6,"OK","NOK") -> NOK | ... O128: =IF(Z7<$G6,"OK","NOK") -> OK | P128: =+COUNTIF(D127:O127,"OK") -> 0
C129: Fastinsight | D129: =IF(D27>$R27,"OK","NOK") -> OK | E129: =IF(E27>$R27,"OK","NOK") -> OK | F129: =IF(F27>$R27,"OK","NOK") -> OK | G129: =IF(G27>$R27,"OK","NOK") -> OK | H129: =IF(H27>$R27,"OK","NOK") -> OK | I129: =IF(I27>$R27,"OK","NOK") -> OK | J129: =IF(J27>$R27,"OK","NOK") -> OK | K129: =IF(K27>$R27,"OK","NOK") -> OK | ... O129: =IF(O27>$R27,"OK","NOK") -> NOK | P129: =+COUNTIF(D128:O128,"OK") -> 1
C130: Reclamações | D130: =IF(E38<$Q38,"OK","NOK") -> OK | E130: =IF(F38<$Q38,"OK","NOK") -> OK | F130: =IF(G38<$Q38,"OK","NOK") -> OK | G130: =IF(H38<$Q38,"OK","NOK") -> OK | H130: =IF(I38<$Q38,"OK","NOK") -> OK | I130: =IF(J38<$Q38,"OK","NOK") -> OK | J130: =IF(K38<$Q38,"OK","NOK") -> OK | K130: =IF(L38<$Q38,"OK","NOK") -> OK | ... O130: =IF(P38<$Q38,"OK","NOK") -> OK | P130: =+COUNTIF(D129:O129,"OK") -> 11
C131: Google | D131: =IF(E49>=$Q49,"OK","NOK") -> OK | E131: =IF(F49>=$Q49,"OK","NOK") -> OK | F131: =IF(G49>=$Q49,"OK","NOK") -> OK | G131: =IF(H49>=$Q49,"OK","NOK") -> OK | H131: =IF(I49>=$Q49,"OK","NOK") -> OK | I131: =IF(J49>=$Q49,"OK","NOK") -> OK | J131: =IF(K49>=$Q49,"OK","NOK") -> OK | K131: =IF(L49>=$Q49,"OK","NOK") -> OK | ... O131: =IF(P49>=$Q49,"OK","NOK") -> NOK | P131: =+COUNTIF(D130:O130,"OK") -> 12
C132: Rating UBER | D132: =IF(E53>=$Q53,"OK","NOK") -> NOK | E132: =IF(F53>=$Q53,"OK","NOK") -> NOK | F132: =IF(G53>=$Q53,"OK","NOK") -> OK | G132: =IF(H53>=$Q53,"OK","NOK") -> NOK | H132: =IF(I53>=$Q53,"OK","NOK") -> NOK | I132: =IF(J53>=$Q53,"OK","NOK") -> NOK | J132: =IF(K53>=$Q53,"OK","NOK") -> OK | K132: =IF(L53>=$Q53,"OK","NOK") -> OK | ... O132: =IF(P53>=$Q53,"OK","NOK") -> OK | P132: =+COUNTIF(D131:O131,"OK") -> 10
C133: Tempos UBER | D133: =IF(C58<$Q58,"OK","NOK") -> OK | E133: =IF(D58<$Q58,"OK","NOK") -> OK | F133: =IF(E58<$Q58,"OK","NOK") -> OK | G133: =IF(F58<$Q58,"OK","NOK") -> OK | H133: =IF(G58<$Q58,"OK","NOK") -> OK | I133: =IF(H58<$Q58,"OK","NOK") -> OK | J133: =IF(I58<$Q58,"OK","NOK") -> OK | K133: =IF(J58<$Q58,"OK","NOK") -> OK | ... O133: =IF(N58<$Q58,"OK","NOK") -> OK | P133: =+COUNTIF(D132:O132,"OK") -> 7
...

Sheet Serviço MTD
B2: TEMPOS DE SERVIÇO
B4: YTD | H4: JUNHO
B5: AMADORA | C5: TEMPO | D5: VAR | E5: RANK | F5: Percentil | G5: OBJETIVO | H5: AMADORA | I5: TEMPO | J5: VAR | K5: RANK | L5: Percentil
B6: ALMOÇO | G6: 100 | H6: ALMOÇO | N6: Jan | O6: fev | P6: mar | Q6: Abr | R6: Mai | S6: Jun | T6: Jul | U6: Ago | V6: Set | W6: Out | X6: Nov | Y6: Dez | Z6: YTD | AA6: LY
B7: JANTAR | H7: JANTAR | M7: AMADORA | N7: 105 | O7: 101 | P7: 103 | Q7: 113 | AA7: 141
B8: DIA | C8: 107 | D8: 1 | E8: 14 | F8: =(E8/188) -> 0.074468085 | H8: DIA | I8: 176 | K8: 128 | L8: =(K8/188) -> 0.68085106 | M8: QUELUZ | N8: 88 | O8: 92 | P8: 94 | Q8: 107 | AA8: 107
B9: YTD | H9: MAIO | M9: P.BORGES | N9: 98 | O9: 97 | P9: 99 | Q9: 111 | AA9: 128
B10: QUELUZ | C10: TEMPO | D10: VAR | E10: RANK | F10: Percentil | G10: OBJETIVO | H10: QUELUZ | I10: TEMPO | J10: VAR | K10: RANK | L10: Percentil
B11: ALMOÇO | G11: 95 | H11: ALMOÇO
B12: JANTAR | H12: JANTAR
B13: DIA | C13: 97 | D13: 2 | E13: 4 | F13: =(E13/188) -> 0.021276596 | H13: DIA | I13: 126 | K13: 40 | L13: =(K13/188) -> 0.21276596
B15: QUALIDADE DO SERVIÇO
C17: FASTINSIGHT AMADORA | K17: FASTINSIGHT QUELUZ
C18: JUNHO | G18: ANO | K18: JUNHO | O18: ANO
C19: SG | D19: VAR | E19: NPS | F19: VAR | G19: SG | I19: NPS | K19: SG | L19: VAR | M19: NPS | N19: VAR | O19: SG | Q19: NPS
C20: 100 | E20: 100 | G20: 93.51 | I20: 95.31 | K20: 77.78 | M20: 81.48 | O20: 94.1 | Q20: 95.1
C22: SG | D22: Jan | E22: Fev | F22: Mar | G22: Abr | H22: Mai | I22: Jun | J22: Jul | K22: Ago | L22: Set | M22: Out | N22: Nov | O22: Dez | P22: YTD | Q22: LY | R22: OBJETIVO
C23: Amadora | D23: 91.46 | E23: 95.35 | F23: 93.24 | G23: 96.28 | H23: 93.8 | P23: 94.69 | Q23: 93.74 | R23: 93
C24: Queluz | D24: 94.09 | E24: 93.02 | F24: 93.87 | G24: 93.08 | H24: 94.07 | P24: 93.57 | Q24: 93.64 | R24: 93
C26: RÁCIO DE RECLAMAÇÕES
C27: GC's Amadora | E27: 106752 | F27: Amadora | G27: SALA | H27: DELIVERY | I27: TOTAL | J27: Queluz | K27: SALA | L27: DELIVERY | M27: TOTAL | N27: LY | O27: AMADORA | P27: QUELUZ | Q27: PBORGES
C28: GC's Queluz | E28: 71929 | F28: QUALIDADE | I28: =SUM(G28:H28) -> 0 | J28: QUALIDADE | K28: 1 | L28: 1 | M28: =SUM(K28:L28) -> 2 | N28: SALA | O28: 3 | P28: 0 | Q28: 3
C29: P.Borges | E29: =((SUM(I28:I30)+SUM(M28:M30))/(E27+E28))*100000 -> 1.1193132 | F29: SERVIÇO | I29: =SUM(G29:H29) -> 0 | J29: SERVIÇO | M29: =SUM(K29:L29) -> 0 | N29: DELIVERY | O29: 3 | P29: 3 | Q29: 6
F30: LIMPEZA | I30: =SUM(G30:H30) -> 0 | J30: LIMPEZA | M30: =SUM(K30:L30) -> 0 | N30: GC'S | O30: 266146 | P30: 176576 | Q30: 442722
F31: RÁCIO | G31: =(SUM(G28:G30)/E27)*100000 -> 0 | H31: =(SUM(H28:H30)/E27)*100000 -> 0 | I31: =(SUM(I28:I30)/E27)*100000 -> 0 | J31: RÁCIO | K31: =(SUM(K28:K30)/E28)*100000 -> 1.3902598 | L31: =(SUM(L28:L30)/E28)*100000 -> 1.3902598 | M31: =(SUM(M28:M30)/E28)*100000 -> 2.7805197 | N31: RÁCIO | O31: 2.25 | P31: 1.7 | Q31: 2.03
D33: Reclamações | E33: Jan | F33: Fev | G33: Mar | H33: Abr | I33: Mai | J33: Jun | K33: Jul | L33: Ago | M33: Set | N33: Out | O33: Nov | P33: Dez | Q33: OBJETIVO
D34: Amadora | E34: 0 | F34: 0 | G34: 0 | H34: 0 | Q34: 1.37 | R34: 4
D35: Queluz | E35: 6.32 | F35: 3.72 | G35: 4.27 | H35: 3.25 | Q35: 1.07 | R35: 2
E38: COMUNICAÇÃO DIGITAL
E39: Amadora | F39: VAR | G39: Ava. Total | H39: Ava. Mês | I39: Queluz | J39: Queluz | K39: VAR | L39: Ava. Total | M39: Ava. Mês | N39: LY | O39: Amadora | P39: QUELUZ
E40: 4 | G40: 1740 | H40: 4 | J40: 4 | K40: 0.1 | L40: 1921 | M40: 16 | O40: 4 | P40: 3.9
O41: 3.1 | P41: 0
D42: UBER | E42: 4.6 | G42: 2850 | H42: 633 | J42: 4.5 | L42: 1749 | M42: 379 | N42: UBER | O42: 4.4 | P42: 4.5
D44: Google | E44: Jan | F44: Fev | G44: Mar | H44: Abr | I44: Mai | J44: Jun | K44: Jul | L44: Ago | M44: Set | N44: Out | O44: Nov | P44: Dez | Q44: OBJETIVO
D45: Amadora | E45: 4 | F45: 4 | G45: 4 | H45: 4 | Q45: 4.1
D46: Queluz | E46: 3.9 | F46: 3.9 | G46: 4 | H46: 4 | Q46: 4.1
D48: UBER | E48: Jan | F48: Fev | G48: Mar | H48: Abr | I48: Mai | J48: Jun | K48: Jul | L48: Ago | M48: Set | N48: Out | O48: Nov | P48: Dez | Q48: OBJETIVO
D49: Amadora | E49: 4.5 | F49: 4.6 | G49: 4.6 | H49: 4.6 | P49: 4.6 | Q49: 4.5
D50: Queluz | E50: 4.5 | F50: 4.5 | G50: 4.5 | H50: 4.6 | Q50: 4.5
B52: 20/32 | C52: Jan | D52: Fev | E52: Mar | F52: Abr | G52: Mai | H52: Jun | I52: Jul | J52: Ago | K52: Set | L52: Out | M52: Nov | N52: Dez | O52: YTD | P52: OBJETIVO
B53: ESTRELAS | C53: 4.5 | D53: 4.6 | E53: 4.6 | F53: 4.6 | G53: 4.6 | O53: 4.6 | P53: 4.5
B54: TEMPOS | C54: 7.7 | D54: 7.3 | E54: 6.9 | F54: 7.2 | G54: 6.9 | O54: 7.1 | P54: 9
B55: AVA. ESTAFETAS | C55: 0.65 | D55: 0.7 | E55: 0.8 | F55: 0.82 | G55: 0.84 | O55: 0.84 | P55: 0.7
B56: AVA. PRODUTO | C56: 0.93 | D56: 0.93 | E56: 0.94 | F56: 0.95 | G56: 0.95 | O56: 0.95 | P56: 0.9
B57: EXATIDÃO | C57: 1.8 | D57: 2 | E57: 2.9 | P57: 1.5
B58: ESTRELAS | C58: 4.5 | D58: 4.5 | E58: 4.5 | F58: 4.6 | G58: 4.5 | O58: 4.5 | P58: 4.5
B59: TEMPOS | C59: 6.1 | D59: 6.3 | E59: 6.3 | F59: 6.7 | G59: 7.7 | O59: 6.7 | P59: 7.5
B60: AVA. ESTAFETAS | C60: 0.68 | D60: 0.74 | E60: 0.75 | F60: 0.74 | G60: 0.81 | O60: 0.81 | P60: 0.7
B61: AVA. PRODUTO | C61: 0.9 | D61: 0.92 | E61: 0.92 | F61: 0.93 | G61: 0.94 | O61: 0.94 | P61: 0.9
B62: EXATIDÃO | C62: 2.6 | D62: 2.3 | E62: 2.5 | P62: 1.5
B64: VENDAS POR PLATAFORMA
B65: Amadora | C65: Jan | D65: Fev | E65: Mar | F65: Abr | G65: Mai | H65: Jun | I65: Jul | J65: Ago | K65: Set | L65: Out | M65: Nov | N65: Dez | O65: YTD | P65: LY | Q65: OBJETIVO
B66: TOTAIS | C66: 218877 | D66: 193009 | E66: 215546 | F66: 212341 | G66: 214759 | H66: 42541 | O66: =SUM(C66:N66) -> 1097073 | P66: 2268923 | Q66: =P66*(1+Q102) -> 2631950.7
B67: DELIVERY | C67: 113002 | D67: 97934 | E67: 107956 | F67: 102436 | G67: 106734 | H67: 20526 | O67: =SUM(C67:N67) -> 548588 | P67: 1152336 | Q67: =P67*(1+Q103) -> 1152336
B68: % DELIVERY | C68: =C67/C66 -> 0.51628083 | D68: =D67/D66 -> 0.50740639 | E68: =E67/E66 -> 0.50084901 | F68: =F67/F66 -> 0.48241272 | G68: =G67/G66 -> 0.49699431 | H68: =H67/H66 -> 0.48249924 | I68: =I67/I66 -> #DIV/0! | J68: =J67/J66 -> #DIV/0! | ... O68: =O67/O66 -> 0.50004694 | P68: 0.50787797 | Q68: =Q67/Q66 -> 0.43782583
B69: SALA | C69: =C66-C67-C73 -> 105257 | D69: =D66-D67-D73 -> 94478 | E69: =E66-E67-E73 -> 106870 | F69: =F66-F67-F73 -> 109145 | G69: =G66-G67 -> 108025 | H69: =H66-H67 -> 22015 | O69: =SUM(C69:N69) -> 545790 | P69: 1109929 | Q69: =Q66-Q67-Q73 -> 1472290.9
B70: % SALA | C70: =C69/C$66 -> 0.48089566 | D70: =D69/D$66 -> 0.48950049 | E70: =E69/E$66 -> 0.49581064 | F70: =F69/F$66 -> 0.51400813 | G70: =G69/G$66 -> 0.50300569 | H70: =H69/H$66 -> 0.51750076 | I70: =I69/I$66 -> #DIV/0! | J70: =J69/J$66 -> #DIV/0! | ... O70: =O69/O$66 -> 0.49749652 | P70: 0.4891876
B71: TAKE-AWAY | O71: =+SUM(C71:N71) -> 0 | P71: 0
B72: % TAKE-AWAY | L72: =L69/L$66 -> #DIV/0! | M72: =M69/M$66 -> #DIV/0! | N72: =N69/N$66 -> #DIV/0!
B73: MOP | C73: 618 | D73: 597 | E73: 720 | F73: 760 | G73: 585 | H73: 119 | O73: =SUM(C73:N73) -> 3399 | P73: 6658 | Q73: =P73*1.1 -> 7323.8
B74: % MOP | C74: =C73/C$66 -> 0.0028235036 | D74: =D73/D$66 -> 0.00309312 | E74: =E73/E$66 -> 0.0033403543 | F74: =F73/F$66 -> 0.0035791486 | G74: =G73/G$66 -> 0.0027239836 | H74: =H73/H$66 -> 0.0027973014 | I74: =I73/I$66 -> #DIV/0! | J74: =J73/J$66 -> #DIV/0! | ... O74: =O73/O$66 -> 0.0030982441 | P74: 0.0029344319 | Q74: =Q73/Q66 -> 0.0027826509
B76: Queluz | C76: Jan | D76: Fev | E76: Mar | F76: Abr | G76: Mai | H76: Jun | I76: Jul | J76: Ago | K76: Set | L76: Out | M76: Nov | N76: Dez | O76: YTD | P76: LY | Q76: OBJETIVO
B77: TOTAIS | C77: 138499 | D77: 126553 | E77: 142121 | F77: 144158 | G77: 146961 | H77: 28624 | O77: =SUM(C77:N77) -> 726916 | P77: 1501867 | Q77: =P77*(1+Q112) -> 1652053.7
B78: DELIVERY | C78: 71357 | D78: 63709 | E78: 69661 | F78: 70784 | G78: 69620 | H78: 13826 | O78: =SUM(C78:N78) -> 358957 | P78: 764674 | Q78: =P78*(1+Q113) -> 726440.3
B79: % DELIVERY | C79: =C78/C77 -> 0.51521672 | D79: =D78/D77 -> 0.50341754 | E79: =E78/E77 -> 0.49015276 | F79: =F78/F77 -> 0.4910168 | G79: =G78/G77 -> 0.47373113 | H79: =H78/H77 -> 0.48302124 | I79: =I78/I77 -> #DIV/0! | J79: =J78/J77 -> #DIV/0! | ... O79: =O78/O77 -> 0.49380809 | P79: 0.50914895 | Q79: =Q78/Q77 -> 0.43971954
B80: SALA | C80: =C77-C78-C84 -> 66406 | D80: =D77-D78-D84 -> 62055 | E80: =E77-E78-E84 -> 71361 | F80: =F77-F78-F84 -> 72431 | G80: =G77-G78 -> 77341 | H80: =H77-H78 -> 14798 | O80: =SUM(C80:N80) -> 364392 | P80: 696711 | Q80: =Q77-Q78-Q84 -> 918241.2
B81: % SALA | C81: =C80/C$77 -> 0.47946917 | D81: =D80/D$77 -> 0.49034792 | E81: =E80/E$77 -> 0.5021144 | F81: =F80/F$77 -> 0.50244177 | G81: =G80/G$77 -> 0.52626887 | H81: =H80/H$77 -> 0.51697876 | I81: =I80/I$77 -> #DIV/0! | J81: =J80/J$77 -> #DIV/0! | ... O81: =O80/O$77 -> 0.50128488 | P81: 0.4638966
B82: TAKE-AWAY | O82: =+SUM(C82:N82) -> 0 | P82: 0
B83: % TAKE-AWAY | L83: =L80/L$66 -> #DIV/0! | M83: =M80/M$66 -> #DIV/0! | N83: =N80/N$66 -> #DIV/0!
B84: MOP | C84: 736 | D84: 789 | E84: 1099 | F84: 943 | G84: 814 | H84: 230 | O84: =SUM(C84:N84) -> 4611 | P84: 6702 | Q84: =P84*1.1 -> 7372.2
B85: % MOP | C85: =C84/C$66 -> 0.0033626192 | D85: =D84/D$66 -> 0.0040878923 | E85: =E84/E$77 -> 0.0077328474 | F85: =F84/F$66 -> 0.0044409699 | G85: =G84/G$66 -> 0.0037902952 | H85: =H84/H$66 -> 0.005406549 | I85: =I84/I$66 -> #DIV/0! | J85: =J84/J$66 -> #DIV/0! | K85: =K84/K$66 -> #DIV/0! | L85: =L84/L$66 -> #DIV/0! | M85: =M84/M$66 -> #DIV/0! | ... O85: =O84/O$66 -> 0.004203002 | P85: 0.0029538243 | Q85: =Q84/Q77 -> 0.0044624457
B100: EVOLUÇÃO RELATIVA DE VENDAS
B101: 20/32 | C101: JANEIRO | D101: FEVEREIRO | E101: MARÇO | F101: ABRIL | G101: MAIO | H101: JUNHO | I101: JULHO | J101: AGOSTO | K101: SETEMBRO | L101: OUTUBRO | M101: NOVEMBRO | N101: DEZEMBRO | O101: ANO | P101: LY | Q101: OBJETIVO
B102: 20 vs 2022 | C102: 0.189 | D102: 0.2597 | E102: 0.2197 | F102: 0.2385 | G102: 0.2173 | H102: 0.3148 | O102: 0.2199 | P102: 0.1884 | Q102: 0.16
B103: DELIVERY | C103: -0.035 | D103: 0.0946 | E103: 0.1347 | F103: 0.2138 | G103: 0.2253 | H103: 0.2588 | O103: 0.1122 | P103: 0.1058 | Q103: 0
B104: 20 vs 2019 | C104: 0.624 | D104: 0.595 | E104: 0.473 | F104: 0.485 | G104: 0.432 | H104: 0.599 | O104: 0.506 | P104: 0.236
B105: 32 vs 2022 | C105: 0.168 | D105: 0.2719 | E105: 0.2448 | F105: 0.2299 | G105: 0.2332 | H105: 0.3915 | O105: 0.223 | P105: 0.0522 | Q105: 0.12
B106: DELIVERY | C106: 0.01 | D106: 0.1601 | E106: 0.2002 | F106: 0.175 | G106: 0.127 | H106: 0.3055 | O106: 0.1246 | P106: -0.1221 | Q106: 0
B107: 32 vs 2019 | C107: 0.458 | D107: 0.515 | E107: 0.429 | F107: 0.464 | G107: 0.336 | H107: 0.661 | O107: 0.425 | P107: 0.167
B108: Nacional vs 2019 | C108: 0.353 | D108: 0.319 | E108: 0.192 | F108: 0.27 | G108: 0.153 | H108: 0.267 | O108: 0.252 | P108: 0.105 | Q108: 45061
B110: EVOLUÇÃO RELATIVA DAS GC'S
B111: 20/32 | C111: JANEIRO | D111: FEVEREIRO | E111: MARÇO | F111: ABRIL | G111: MAIO | H111: JUNHO | I111: JULHO | J111: AGOSTO | K111: SETEMBRO | L111: OUTUBRO | M111: NOVEMBRO | N111: DEZEMBRO | O111: ANO | P111: LY | Q111: OBJETIVO
B112: TOTAIS vs 2022 | C112: 0.253 | D112: 0.2414 | E112: 0.1714 | F112: 0.2063 | G112: 0.1522 | H112: 0.1976 | O112: 0.2025 | P112: 0.0695 | Q112: 0.1
B113: DELIVERY | C113: -0.078 | D113: 0.0555 | E113: 0.0879 | F113: 0.2208 | G113: 0.1556 | H113: 0.0997 | O113: 0.0638 | P113: -0.1679 | Q113: -0.05
B114: 20 vs 2019 | C114: 0.115 | D114: 0.048 | E114: 0.007 | F114: 0.057 | G114: -0.022 | H114: 0.083 | O114: 0.033 | P114: -0.121
B115: TOTAIS | C115: 0.203 | D115: 0.2141 | E115: 0.1925 | F115: 0.1925 | G115: 0.1352 | H115: 0.2065 | O115: 0.1887 | P115: 0.1336 | Q115: 0.06
B116: DELIVERY | C116: -0.027 | D116: 0.0959 | E116: 0.1263 | F116: 0.0726 | G116: 0.0473 | H116: 0.163 | O116: 0.0567 | P116: -0.1626 | Q116: -0.05
B117: 32 vs 2019 | C117: -0.01 | D117: -0.002 | E117: -0.008 | F117: 0.059 | G117: -0.083 | H117: 0.1 | O117: -0.016 | P117: -0.153
B118: Nacional vs 2019 | C118: -0.028 | D118: -0.037 | E118: -0.076 | F118: -0.012 | G118: 0.09 | H118: -0.037 | O118: -0.052 | P118: -0.13
C123: 20/32 | D123: JANEIRO | E123: FEVEREIRO | F123: MARÇO | G123: ABRIL | H123: MAIO | I123: JUNHO | J123: JULHO | K123: AGOSTO | L123: SETEMBRO | M123: OUTUBRO | N123: NOVEMBRO | O123: DEZEMBRO | P123: ANO
C124: Tempo serviço | D124: =IF(N7<$G6,"OK","NOK") -> NOK | E124: =IF(O7<$G6,"OK","NOK") -> NOK | F124: =IF(P7<$G6,"OK","NOK") -> NOK | G124: =IF(Q7<$G6,"OK","NOK") -> NOK | H124: =IF(R7<$G6,"OK","NOK") -> OK | I124: =IF(S7<$G6,"OK","NOK") -> OK | J124: =IF(T7<$G6,"OK","NOK") -> OK | K124: =IF(U7<$G6,"OK","NOK") -> OK | ... O124: =IF(Y7<$G6,"OK","NOK") -> OK | P124: =+COUNTIF(D124:O124,"OK") -> 8
C125: Fastinsight | D125: =IF(D23>$R23,"OK","NOK") -> NOK | E125: =IF(E23>$R23,"OK","NOK") -> OK | F125: =IF(F23>$R23,"OK","NOK") -> OK | G125: =IF(G23>$R23,"OK","NOK") -> OK | H125: =IF(H23>$R23,"OK","NOK") -> OK | I125: =IF(I23>$R23,"OK","NOK") -> NOK | J125: =IF(J23>$R23,"OK","NOK") -> NOK | K125: =IF(K23>$R23,"OK","NOK") -> NOK | ... O125: =IF(O23>$R23,"OK","NOK") -> NOK | P125: =+COUNTIF(D125:O125,"OK") -> 4
C126: Reclamações | D126: =IF(E34<$Q34,"OK","NOK") -> OK | E126: =IF(F34<$Q34,"OK","NOK") -> OK | F126: =IF(G34<$Q34,"OK","NOK") -> OK | G126: =IF(H34<$Q34,"OK","NOK") -> OK | H126: =IF(I34<$Q34,"OK","NOK") -> OK | I126: =IF(J34<$Q34,"OK","NOK") -> OK | J126: =IF(K34<$Q34,"OK","NOK") -> OK | K126: =IF(L34<$Q34,"OK","NOK") -> OK | ... O126: =IF(P34<$Q34,"OK","NOK") -> OK | P126: =+COUNTIF(D126:O126,"OK") -> 12
C127: Google | D127: =IF(E45>=$Q45,"OK","NOK") -> NOK | E127: =IF(F45>=$Q45,"OK","NOK") -> NOK | F127: =IF(G45>=$Q45,"OK","NOK") -> NOK | G127: =IF(H45>=$Q45,"OK","NOK") -> NOK | H127: =IF(I45>=$Q45,"OK","NOK") -> NOK | I127: =IF(J45>=$Q45,"OK","NOK") -> NOK | J127: =IF(K45>=$Q45,"OK","NOK") -> NOK | K127: =IF(L45>=$Q45,"OK","NOK") -> NOK | ... O127: =IF(P45>=$Q45,"OK","NOK") -> NOK | P127: =+COUNTIF(D127:O127,"OK") -> 0
C128: Rating UBER | D128: =IF(E49>=$Q49,"OK","NOK") -> OK | E128: =IF(F49>=$Q49,"OK","NOK") -> OK | F128: =IF(G49>=$Q49,"OK","NOK") -> OK | G128: =IF(H49>=$Q49,"OK","NOK") -> OK | H128: =IF(I49>=$Q49,"OK","NOK") -> NOK | I128: =IF(J49>=$Q49,"OK","NOK") -> NOK | J128: =IF(K49>=$Q49,"OK","NOK") -> NOK | K128: =IF(L49>=$Q49,"OK","NOK") -> NOK | ... O128: =IF(P49>=$Q49,"OK","NOK") -> OK | P128: =+COUNTIF(D128:O128,"OK") -> 5
C129: Tempos UBER | D129: =IF(C54<$P54,"OK","NOK") -> OK | E129: =IF(D54<$P54,"OK","NOK") -> OK | F129: =IF(E54<$P54,"OK","NOK") -> OK | G129: =IF(F54<$P54,"OK","NOK") -> OK | H129: =IF(G54<$P54,"OK","NOK") -> OK | I129: =IF(H54<$P54,"OK","NOK") -> OK | J129: =IF(I54<$P54,"OK","NOK") -> OK | K129: =IF(J54<$P54,"OK","NOK") -> OK | ... O129: =IF(N54<$P54,"OK","NOK") -> OK | P129: =+COUNTIF(D129:O129,"OK") -> 12
C130: Rácio exatidão | D130: =IF(C57<=$P57,"OK","NOK") -> NOK | E130: =IF(D57<=$P57,"OK","NOK") -> NOK | F130: =IF(E57<=$P57,"OK","NOK") -> NOK | G130: =IF(F57<=$P57,"OK","NOK") -> OK | H130: =IF(G57<=$P57,"OK","NOK") -> OK | I130: =IF(H57<=$P57,"OK","NOK") -> OK | J130: =IF(I57<=$P57,"OK","NOK") -> OK | K130: =IF(J57<=$P57,"OK","NOK") -> OK | ... O130: =IF(N57<=$P57,"OK","NOK") -> OK | P130: =+COUNTIF(D130:O130,"OK") -> 9
C131: Vendas | D131: =IF(C102>$Q102,"OK","NOK") -> OK | E131: =IF(D102>$Q102,"OK","NOK") -> OK | F131: =IF(E102>$Q102,"OK","NOK") -> OK | G131: =IF(F102>$Q102,"OK","NOK") -> OK | H131: =IF(G102>$Q102,"OK","NOK") -> OK | I131: =IF(H102>$Q102,"OK","NOK") -> OK | J131: =IF(I102>$Q102,"OK","NOK") -> NOK | K131: =IF(J102>$Q102,"OK","NOK") -> NOK | ... O131: =IF(N102>$Q102,"OK","NOK") -> NOK | P131: =+COUNTIF(D131:O131,"OK") -> 6
C132: GC's | D132: =IF(C112>$Q112,"OK","NOK") -> OK | E132: =IF(D112>$Q112,"OK","NOK") -> OK | F132: =IF(E112>$Q112,"OK","NOK") -> OK | G132: =IF(F112>$Q112,"OK","NOK") -> OK | H132: =IF(G112>$Q112,"OK","NOK") -> OK | I132: =IF(H112>$Q112,"OK","NOK") -> OK | J132: =IF(I112>$Q112,"OK","NOK") -> NOK | K132: =IF(J112>$Q112,"OK","NOK") -> NOK | ... O132: =IF(N112>$Q112,"OK","NOK") -> NOK | P132: =+COUNTIF(D132:O132,"OK") -> 6
C133: Total | D133: =COUNTIF(D124:D132,"OK") -> 5 | E133: =COUNTIF(E124:E132,"OK") -> 6 | F133: =COUNTIF(F124:F132,"OK") -> 6 | G133: =COUNTIF(G124:G132,"OK") -> 7 | H133: =COUNTIF(H124:H132,"OK") -> 7 | I133: =COUNTIF(I124:I132,"OK") -> 6 | J133: =COUNTIF(J124:J132,"OK") -> 4 | K133: =COUNTIF(K124:K132,"OK") -> 4 | ... O133: =COUNTIF(O124:O132,"OK") -> 5 | P133: =SUM(P124:P132) -> 62
...

Sheet Pessoas
B2: M.O. MENSAL
B4: VALOR DA HORA 2022 | E4: JANEIRO | F4: FEVEREIRO | G4: MARÇO | H4: ABRIL | I4: MAIO | J4: JUNHO | K4: JULHO | L4: AGOSTO | M4: SETEMBRO | N4: OUTUBRO | O4: NOVEMBRO | P4: DEZEMBRO | Q4: ANO
B5: 7.65 | D5: 20- VENDAS | E5: =C34 -> 288945 | F5: =C35 -> 254163 | G5: =C38 -> 280532 | H5: =C41 -> 247258 | I5: =C44 -> 251597 | J5: =C47 -> 252397 | K5: =C50 -> 268928 | L5: =C53 -> 286413 | M5: =C56 -> 246748 | N5: =C59 -> 236241 | O5: =C62 -> 236196 | P5: =C65 -> 82979 | Q5: =C68 -> 2932397 | S5: OBJETIVO
D6: 32- VENDAS | E6: =N34 -> 157396 | F6: =N35 -> 143160 | G6: =N38 -> 153168 | H6: =N41 -> 142879 | I6: =N44 -> 161979 | J6: =N47 -> 159094 | K6: =N50 -> 165280 | L6: =N53 -> 168534 | M6: =N56 -> 155517 | N6: =N59 -> 161680 | O6: =N62 -> 162732 | P6: =N65 -> 57366 | Q6: =N68 -> 1788785 | S6: 0.1
D7: 20- HORAS | E7: =D34 -> 3848 | F7: =D35 -> 3436 | G7: =D38 -> 3871 | H7: =D41 -> 3722 | I7: =D44 -> 3362 | J7: =+D47 -> 0 | K7: =+D50 -> 0 | L7: =+D53 -> 0 | M7: =+D56 -> 0 | N7: =+D59 -> 0 | O7: =+D62 -> 0 | P7: =+D65 -> 0 | Q7: =+D68 -> 18239 | S7: 0.105
D8: 32- HORAS | E8: =O34 -> 2500 | F8: =O35 -> 2330 | G8: =O38 -> 2444 | H8: =O41 -> 2535 | I8: =O44 -> 2489 | J8: =O47 -> 0 | K8: =O50 -> 0 | L8: =O53 -> 0 | M8: =O56 -> 0 | N8: =O59 -> 0 | O8: =O62 -> 0 | P8: =O65 -> 0 | Q8: =O68 -> 12298
D9: 20- PRODUTIVIDADE | E9: =E5/E7 -> 75.089657 | F9: =F5/F7 -> 73.970605 | G9: =G5/G7 -> 72.470163 | H9: =H5/H7 -> 66.431488 | I9: =I5/I7 -> 74.835515 | J9: =J5/J7 -> #DIV/0! | K9: =K5/K7 -> #DIV/0! | L9: =L5/L7 -> #DIV/0! | ... Q9: =Q5/Q7 -> 160.77619
D10: 32-PRODUTIVIDADE | E10: =E6/E8 -> 62.9584 | F10: =F6/F8 -> 61.44206 | G10: =G6/G8 -> 62.671031 | H10: =H6/H8 -> 56.362525 | I10: =I6/I8 -> 65.077943 | J10: =J6/J8 -> #DIV/0! | K10: =K6/K8 -> #DIV/0! | L10: =L6/L8 -> #DIV/0! | ... Q10: =Q6/Q8 -> 145.45333
D11: 20- MO | E11: =F34 -> 0.1123 | F11: =F35 -> 0.1107 | G11: =F38 -> 0.1142 | H11: =F41 -> 0.1068 | I11: =F44 -> 0.1064 | J11: =F47 -> 0 | K11: =F50 -> 0 | L11: =F53 -> 0 | M11: =F56 -> 0 | N11: =F59 -> 0 | O11: =F62 -> 0 | P11: =F65 -> 0
D12: 32- MO | E12: =Q34 -> 0.1204 | F12: =Q35 -> 0.1254 | G12: =Q38 -> 0.1184 | H12: =Q41 -> 0.1302 | I12: =Q44 -> 0.1218 | J12: =Q47 -> 0 | K12: =Q50 -> 0 | L12: =Q53 -> 0 | M12: =Q56 -> 0 | N12: =Q59 -> 0 | O12: =Q62 -> 0 | P12: =Q65 -> 0
H18: 60
H19: 55
B30: EVOLUÇÃO MENSAL DE HORAS
B32: COMPARAÇÃO DE CUSTOS AMADORA | M32: COMPARAÇÃO DE CUSTOS QUELUZ
C33: VENDAS | D33: HORAS | E33: PRODUTIVIDADE | F33: MO | N33: VENDAS | O33: HORAS | P33: PRODUTIVIDADE | Q33: MO
B34: JANEIRO | C34: =Serviço!C70 -> 288945 | D34: 3848 | E34: =C34/D34 -> 75.089657 | F34: 0.1123 | M34: JANEIRO | N34: =Serviço!C81 -> 157396 | O34: 2500 | P34: =N34/O34 -> 62.9584 | Q34: 0.1204
B35: FEVEREIRO | C35: =Serviço!D70 -> 254163 | D35: 3436 | E35: =C35/D35 -> 73.970605 | F35: 0.1107 | M35: FEVEREIRO | N35: =Serviço!D81 -> 143160 | O35: 2330 | P35: =N35/O35 -> 61.44206 | Q35: 0.1254
B36: ⃤ ABSOLUTA | C36: =C35-C34 -> -34782 | D36: =D35-D34 -> -412 | E36: =E35-E34 -> -1.1190516 | F36: =(F35-F34)*100 -> -0.16 | M36: ⃤ ABSOLUTA PP | N36: =N35-N34 -> -14236 | O36: =O35-O34 -> -170 | P36: =P35-P34 -> -1.5163399 | Q36: =(Q35-Q34)*100 -> 0.5
B37: ⃤ RELATIVA | C37: =C36/C34 -> -0.12037585 | D37: =D36/D34 -> -0.10706861 | E37: =E36/E35 -> -0.015128328 | F37: =(F35-F34)/F34 -> -0.014247551 | M37: ⃤ RELATIVA | N37: =N36/N34 -> -0.090447025 | O37: =O36/O34 -> -0.068 | P37: =P36/P35 -> -0.024679184 | Q37: =(Q35-Q34)/Q34 -> 0.041528239
B38: MARÇO | C38: =Serviço!E70 -> 280532 | D38: 3871 | E38: =C38/D38 -> 72.470163 | F38: 0.1142 | M38: MARÇO | N38: =Serviço!E81 -> 153168 | O38: 2444 | P38: =N38/O38 -> 62.671031 | Q38: 0.1184
B39: ⃤ ABSOLUTA | C39: =C38-C35 -> 26369 | D39: =D38-D35 -> 435 | E39: =E38-E35 -> -1.5004426 | F39: =(F38-F35)*100 -> 0.35 | M39: ⃤ ABSOLUTA PP | N39: =N38-N35 -> 10008 | O39: =O38-O35 -> 114 | P39: =P38-P35 -> 1.228971 | Q39: =(Q38-Q35)*100 -> -0.7
B40: ⃤ RELATIVA | C40: =C39/C35 -> 0.10374838 | D40: =D39/D35 -> 0.1266007 | E40: =E39/E35 -> -0.020284309 | F40: =(F38-F35)/F35 -> 0.031616983 | M40: ⃤ RELATIVA | N40: =N39/N35 -> 0.069907795 | O40: =O39/O35 -> 0.048927039 | P40: =P39/P35 -> 0.020002113 | Q40: =(Q38-Q35)/Q35 -> -0.055821372
B41: ABRIL | C41: =Serviço!F70 -> 247258 | D41: 3722 | E41: =C41/D41 -> 66.431488 | F41: 0.1068 | M41: ABRIL | N41: =Serviço!F81 -> 142879 | O41: 2535 | P41: =N41/O41 -> 56.362525 | Q41: 0.1302
B42: ⃤ ABSOLUTA | C42: =C41-C38 -> -33274 | D42: =D41-D38 -> -149 | E42: =E41-E38 -> -6.0386743 | F42: =(F41-F38)*100 -> -0.74 | M42: ⃤ ABSOLUTA PP | N42: =N41-N38 -> -10289 | O42: =O41-O38 -> 91 | P42: =P41-P38 -> -6.3085064 | Q42: =(Q41-Q38)*100 -> 1.18
B43: ⃤ RELATIVA | C43: =C42/C38 -> -0.11861035 | D43: =D42/D38 -> -0.038491346 | E43: =E42/E38 -> -0.083326352 | F43: =(F41-F38)/F38 -> -0.064798599 | M43: ⃤ RELATIVA | N43: =N42/N38 -> -0.067174606 | O43: =O42/O38 -> 0.037234043 | P43: =P42/P38 -> -0.10066065 | Q43: =(Q41-Q38)/Q38 -> 0.099662162
B44: MAIO | C44: =Serviço!G70 -> 251597 | D44: 3362 | E44: =C44/D44 -> 74.835515 | F44: 0.1064 | M44: MAIO | N44: =Serviço!G81 -> 161979 | O44: 2489 | P44: =N44/O44 -> 65.077943 | Q44: 0.1218
B45: ⃤ ABSOLUTA | C45: =C44-C41 -> 4339 | D45: =D44-D41 -> -360 | E45: =E44-E41 -> 8.4040261 | F45: =(F44-F41)*100 -> -0.04 | M45: ⃤ ABSOLUTA PP | N45: =N44-N41 -> 19100 | O45: =O44-O41 -> -46 | P45: =P44-P41 -> 8.7154183 | Q45: =(Q44-Q41)*100 -> -0.84
B46: ⃤ RELATIVA | C46: =C45/C41 -> 0.017548472 | D46: =D45/D41 -> -0.096722192 | E46: =E45/E41 -> 0.12650667 | F46: =(F44-F41)/F41 -> -0.0037453184 | M46: ⃤ RELATIVA | N46: =N45/N41 -> 0.13367955 | O46: =O45/O41 -> -0.018145957 | P46: =P45/P41 -> 0.15463144 | Q46: =(Q44-Q41)/Q41 -> -0.064516129
B47: JUNHO | C47: =Serviço!H70 -> 252397 | E47: =C47/D47 -> #DIV/0! | M47: JUNHO | N47: =Serviço!H81 -> 159094 | P47: =N47/O47 -> #DIV/0!
B48: ⃤ ABSOLUTA | C48: =C47-C44 -> 800 | D48: =D47-D44 -> -3362 | E48: =E47-E44 -> #DIV/0! | F48: =(F47-F44)*100 -> -10.64 | M48: ⃤ ABSOLUTA PP | N48: =N47-N44 -> -2885 | O48: =O47-O44 -> -2489 | P48: =P47-P44 -> #DIV/0! | Q48: =(Q47-Q44)*100 -> -12.18
B49: ⃤ RELATIVA | C49: =C48/C44 -> 0.0031796882 | D49: =D48/D44 -> -1 | E49: =E48/E44 -> #DIV/0! | F49: =(F47-F44)/F44 -> -1 | M49: ⃤ RELATIVA | N49: =N48/N44 -> -0.017810951 | O49: =O48/O44 -> -1 | P49: =P48/P44 -> #DIV/0! | Q49: =(Q47-Q44)/Q44 -> -1
B50: JULHO | C50: =Serviço!I70 -> 268928 | E50: =C50/D50 -> #DIV/0! | M50: JULHO | N50: =Serviço!I81 -> 165280 | P50: =N50/O50 -> #DIV/0!
B51: ⃤ ABSOLUTA | C51: =C50-C47 -> 16531 | D51: =D50-D47 -> 0 | E51: =E50-E47 -> #DIV/0! | F51: =(F50-F47)*100 -> 0 | M51: ⃤ ABSOLUTA PP | N51: =N50-N34 -> 7884 | O51: =O50-O34 -> -2500 | P51: =P50-P47 -> #DIV/0! | Q51: =(Q50-Q47)*100 -> 0
B52: ⃤ RELATIVA | C52: =C51/C47 -> 0.065496024 | D52: =D51/D47 -> #DIV/0! | E52: =E51/E47 -> #DIV/0! | F52: =(F50-F47)/F47 -> #DIV/0! | M52: ⃤ RELATIVA | N52: =N51/N34 -> 0.050090218 | O52: =O51/O34 -> -1 | P52: =P51/P47 -> #DIV/0! | Q52: =(Q50-Q47)/Q47 -> #DIV/0!
B53: AGOSTO | C53: =Serviço!J70 -> 286413 | E53: =C53/D53 -> #DIV/0! | M53: AGOSTO | N53: =Serviço!J81 -> 168534 | P53: =N53/O53 -> #DIV/0!
B54: ⃤ ABSOLUTA | C54: =C53-C50 -> 17485 | D54: =D53-D50 -> 0 | E54: =E53-E50 -> #DIV/0! | F54: =(F53-F50)*100 -> 0 | M54: ⃤ ABSOLUTA PP | N54: =N53-N50 -> 3254 | O54: =O53-O50 -> 0 | P54: =P53-P50 -> #DIV/0! | Q54: =(Q53-Q50)*100 -> 0
B55: ⃤ RELATIVA | C55: =C54/C50 -> 0.065017402 | D55: =D54/D50 -> #DIV/0! | E55: =E54/E50 -> #DIV/0! | F55: =(F53-F50)/F50 -> #DIV/0! | M55: ⃤ RELATIVA | N55: =N54/N50 -> 0.019687803 | O55: =O54/O50 -> #DIV/0! | P55: =P54/P50 -> #DIV/0! | Q55: =(Q53-Q50)/Q50 -> #DIV/0!
B56: SETEMBRO | C56: =Serviço!K70 -> 246748 | E56: =C56/D56 -> #DIV/0! | M56: SETEMBRO | N56: =Serviço!K81 -> 155517 | P56: =N56/O56 -> #DIV/0!
B57: ⃤ ABSOLUTA | C57: =C56-C53 -> -39665 | D57: =D56-D53 -> 0 | E57: =E56-E53 -> #DIV/0! | F57: =(F56-F53)*100 -> 0 | M57: ⃤ ABSOLUTA PP | N57: =N56-N53 -> -13017 | O57: =O56-O53 -> 0 | P57: =P56-P53 -> #DIV/0! | Q57: =(Q56-Q53)*100 -> 0
B58: ⃤ RELATIVA | C58: =C57/C53 -> -0.13848883 | D58: =D57/D53 -> #DIV/0! | E58: =E57/E53 -> #DIV/0! | F58: =(F56-F53)/F53 -> #DIV/0! | M58: ⃤ RELATIVA | N58: =N57/N53 -> -0.077236641 | O58: =O57/O53 -> #DIV/0! | P58: =P57/P53 -> #DIV/0! | Q58: =(Q56-Q53)/Q53 -> #DIV/0!
B59: OUTUBRO | C59: =Serviço!L70 -> 236241 | E59: =C59/D59 -> #DIV/0! | M59: OUTUBRO | N59: =Serviço!L81 -> 161680 | P59: =N59/O59 -> #DIV/0!
B60: ⃤ ABSOLUTA | C60: =C59-C56 -> -10507 | D60: =D59-D56 -> 0 | E60: =E59-E56 -> #DIV/0! | F60: =(F59-F56)*100 -> 0 | M60: ⃤ ABSOLUTA PP | N60: =N59-N56 -> 6163 | O60: =O59-O56 -> 0 | P60: =P59-P56 -> #DIV/0! | Q60: =(Q59-Q56)*100 -> 0
B61: ⃤ RELATIVA | C61: =C60/C56 -> -0.042581905 | D61: =D60/D56 -> #DIV/0! | E61: =E60/E56 -> #DIV/0! | F61: =(F59-F56)/F56 -> #DIV/0! | M61: ⃤ RELATIVA | N61: =N60/N56 -> 0.039629108 | O61: =O60/O56 -> #DIV/0! | P61: =P60/P56 -> #DIV/0! | Q61: =(Q59-Q56)/Q56 -> #DIV/0!
B62: NOVEMBRO | C62: =Serviço!M70 -> 236196 | E62: =C62/D62 -> #DIV/0! | M62: NOVEMBRO | N62: =Serviço!M81 -> 162732 | P62: =N62/O62 -> #DIV/0!
B63: ⃤ ABSOLUTA | C63: =C62-C59 -> -45 | D63: =D62-D59 -> 0 | E63: =E62-E59 -> #DIV/0! | F63: =(F62-F59)*100 -> 0 | M63: ⃤ ABSOLUTA PP | N63: =N62-N59 -> 1052 | O63: =O62-O59 -> 0 | P63: =P62-P59 -> #DIV/0! | Q63: =(Q62-Q59)*100 -> 0
B64: ⃤ RELATIVA | C64: =C63/C59 -> -0.00019048345 | D64: =D63/D59 -> #DIV/0! | E64: =E63/E59 -> #DIV/0! | F64: =(F62-F59)/F59 -> #DIV/0! | M64: ⃤ RELATIVA | N64: =N63/N59 -> 0.0065066799 | O64: =O63/O59 -> #DIV/0! | P64: =P63/P59 -> #DIV/0! | Q64: =(Q62-Q59)/Q59 -> #DIV/0!
B65: DEZEMBRO | C65: =Serviço!N70 -> 82979 | E65: =C65/D65 -> #DIV/0! | M65: DEZEMBRO | N65: =Serviço!N81 -> 57366 | P65: =N65/O65 -> #DIV/0!
B66: ⃤ ABSOLUTA | C66: =C65-C59 -> -153262 | D66: =D65-D59 -> 0 | E66: =E65-E62 -> #DIV/0! | F66: =(F65-F62)*100 -> 0 | M66: ⃤ ABSOLUTA PP | N66: =N65-N59 -> -104314 | O66: =O65-O59 -> 0 | P66: =P65-P62 -> #DIV/0! | Q66: =(Q65-Q62)*100 -> 0
B67: ⃤ RELATIVA | C67: =C66/C59 -> -0.64875276 | D67: =D66/D59 -> #DIV/0! | E67: =E66/E62 -> #DIV/0! | F67: =(F65-F62)/F62 -> #DIV/0! | M67: ⃤ RELATIVA | N67: =N66/N59 -> -0.64518803 | O67: =O66/O59 -> #DIV/0! | P67: =P66/P62 -> #DIV/0! | Q67: =(Q65-Q62)/Q62 -> #DIV/0!
B68: TOTAL | C68: =SUM(C65+C62+C59+C56+C53+C50+C47+C44+C41+C38+C35+C34) -> 2932397 | D68: =SUM(D65+D62+D59+D56+D53+D50+D47+D44+D41+D38+D35+D34) -> 18239 | E68: =C68/D68 -> 160.77619 | M68: TOTAL | N68: =SUM(N65+N62+N59+N56+N53+N50+N47+N44+N41+N38+N35+N34) -> 1788785 | O68: =SUM(O65+O62+O59+O56+O53+O50+O47+O44+O41+O38+O35+O34) -> 12298 | P68: =N68/O68 -> 145.45333
B70: TURNOVER
C72: AMADORA | D72: QUELUZ
B73: JANEIRO | C73: 0 | D73: 0 | S73: OBJETIVO
B74: FEVEREIRO | C74: 0 | D74: 0 | S74: 0.85
B75: MARÇO | C75: 0.032 | D75: 0.1 | S75: 0.85
B76: ABRIL | C76: 0 | D76: 0.05
B77: MAIO | C77: 0.031 | D77: 0
B78: JUNHO
B79: JULHO
B80: AGOSTO
B81: SETEMBRO
B82: OUTUBRO
B83: NOVEMBRO
B84: DEZEMBRO
B85: ANO | C85: 0.063 | D85: 0.1
B86: LY | C86: 0.5 | D86: 0.842
B88: STAFFING
B90: STAFFING (abaixo do ideal) | E90: PLANIFICAÇÃO (ideal) | H90: STAFFING (abaixo do ideal) | K90: PLANIFICAÇÃO (ideal)
B91: 20- TOTAL | C91: 20- ALMOÇO | D91: 20- JANTAR | E91: 20- TOTAL | F91: 20- ALMOÇO | G91: 20- JANTAR | H91: 32- TOTAL | I91: 32- ALMOÇO | J91: 32- JANTAR | K91: 32- TOTAL | L91: 32- ALMOÇO | M91: 32- JANTAR
A92: JANEIRO | B92: 0.4 | C92: 0.23 | D92: 0.58 | E92: 0.45 | F92: 0.45 | G92: 0.45 | H92: 0.35 | I92: 0.32 | J92: 0.39 | K92: 0.27 | L92: 0.29 | M92: 0.26 | N92: OBJETIVO
A93: FEVEREIRO | B93: 0.34 | C93: 0.31 | D93: 0.38 | E93: 0.45 | F93: 0.34 | G93: 0.55 | H93: 0.33 | I93: 0.24 | J93: 0.41 | K93: 0.36 | L93: 0.55 | M93: 0.17 | N93: 0.35
A94: MARÇO | B94: 0.34 | C94: 0.23 | D94: 0.45 | E94: 0.4 | F94: 0.35 | G94: 0.45 | H94: 0.5 | I94: 0.37 | J94: 0.63 | K94: 0.33 | L94: 0.3 | M94: 0.37 | N94: 0.35
A95: ABRIL | B95: 0.5 | C95: 0.33 | D95: 0.67 | E95: 0.48 | F95: 0.57 | G95: 0.4 | H95: 0.38 | I95: 0.2 | J95: 0.57 | K95: 0.27 | L95: 0.23 | M95: 0.3
A96: MAIO | B96: 0.5 | C96: 0.35 | D96: 0.65 | E96: 0.45 | F96: 0.45 | G96: 0.45 | H96: 0.61 | I96: 0.65 | J96: 0.58 | K96: 0.4 | L96: 0.48 | M96: 0.32
A97: JUNHO
A98: JULHO
A99: AGOSTO
A100: SETEMBRO
A101: OUTUBRO
A102: NOVEMBRO
A103: DEZEMBRO
A104: ANO | B104: 0.43 | C104: 0.29 | D104: 0.57 | E104: 0.39 | F104: 0.36 | G104: 0.41 | H104: 0.56 | I104: 0.52 | J104: 0.61 | K104: 0.33 | L104: 0.38 | M104: 0.28
B107: HORAS EXTRA | O107: CEDÊNCIA DE HORAS
B109: MÊS | C109: AMADORA | D109: QUELUZ | E109: JUSTIFICAÇÃO | O109: MÊS | P109: AMADORA | Q109: QUELUZ | R109: JUSTIFICAÇÃO
B110: JANEIRO | O110: JANEIRO
B111: FEVEREIRO | O111: FEVEREIRO
B112: MARÇO | O112: MARÇO
B113: ABRIL | O113: ABRIL
B114: MAIO | C114: 108 | D114: 49 | O114: MAIO
B115: JUNHO | O115: JUNHO
B116: JULHO | O116: JULHO
B117: AGOSTO | O117: AGOSTO
B118: SETEMBRO | O118: SETEMBRO
B119: OUTUBRO | O119: OUTUBRO
B120: NOVEMBRO | O120: NOVEMBRO
B121: DEZEMBRO | O121: DEZEMBRO
B122: TOTAL | C122: =SUM(C110:C121) -> 108 | D122: =SUM(D110:D121) -> 49 | O122: TOTAL | P122: =SUM(P110:P121) -> 0 | Q122: =SUM(Q110:Q121) -> 0
B123: MÉDIA MENSAL | C123: =C122/COUNTIF(C110:C121,">0") -> 108 | D123: =D122/COUNTIF(D110:D121,">0") -> 49
B124: EXTRA POR 1000€ | C124: =C122/(C68/1000) -> 0.036829938 | D124: =D122/(N68/1000) -> 0.027392895
B125: EXTRA vs HORAS | C125: =C122/(D68) -> 0.0059213773 | D125: =D122/(O68) -> 0.0039843877
...

Sheet Produto
B2: CUSTO DE VENDAS
C3: JANEIRO | D3: FEVEREIRO | E3: MARÇO | F3: ABRIL | G3: MAIO | H3: JUNHO | I3: JULHO | J3: AGOSTO | K3: SETEMBRO | L3: OUTUBRO | M3: NOVEMBRO | N3: DEZEMBRO | O3: ANO | P3: LY
A4: OBJETIVO | B4: COMIDA (20) | C4: 0.2576 | D4: 0.26 | E4: 0.2613 | F4: 0.2613
B5: PAPEL (20) | C5: 0.0159 | D5: 0.0312 | E5: 0.0308 | F5: 0.031
A6: 0.007 | B6: REFEIÇÕES (20) | C6: 0.0082 | D6: 0.009 | E6: 0.0091 | F6: 0.008
A7: 0.005 | B7: PERDAS (20) | C7: 0.0052 | D7: 0.005 | E7: 0.005 | F7: 0.005
B8: PROMOS (20) | C8: 0.0017 | D8: 0.0024 | E8: 0.0027 | F8: 0.002
B9: C.VENDAS (20) | C9: 0.2903 | D9: 0.31 | E9: 0.2772 | F9: 0.3061
B10: COMIDA (32) | C10: 0.2494 | D10: 0.2671 | E10: 0.2723 | F10: 0.2547
B11: PAPEL (32) | C11: 0.03 | D11: 0.0314 | E11: 0.0339 | F11: 0.0338
A12: 0.008 | B12: REFEIÇÕES (32) | C12: 0.0105 | D12: 0.0095 | E12: 0.0089 | F12: 0.0098
A13: 0.005 | B13: PERDAS (32) | C13: 0.0071 | D13: 0.0074 | E13: 0.0069 | F13: 0.0086
B14: PROMOS (32) | C14: 0.0025 | D14: 0.0027 | E14: 0.0033 | F14: 0.0028
B15: C.VENDAS (32) | C15: 0.302 | D15: 0.3181 | E15: 0.3253 | F15: 0.3097
B31: DESVIOS
C32: PÃO REG | E32: CARNE REG | G32: CARNE ROYAL | I32: CHK OPT | K32: CHK NUGGETS | M32: BACON FATIAS | O32: COMPAL M/L | Q32: QUEIJO CHEDDAR | S32: QUEIJO EMMENTAL/WHITE
C33: 20 | D33: 32 | E33: 20 | F33: 32 | G33: 20 | H33: 32 | I33: 20 | J33: 32 | K33: 20 | L33: 32 | M33: 20 | N33: 32 | O33: 20 | P33: 32 | Q33: 20 | R33: 32 | S33: 20 | T33: 32
B34: JANEIRO | C34: -293 | D34: -62 | E34: -75 | F34: 16 | G34: -62 | H34: -20 | I34: 19 | J34: -9 | K34: -40 | L34: -9 | M34: 203 | N34: 70 | O34: -11 | P34: -16 | Q34: 280 | R34: -274 | S34: -21 | T34: -59
B35: FEVEREIRO | C35: -177 | D35: -77 | E35: 126 | F35: -95 | G35: 94 | H35: 10 | I35: 25 | J35: -16 | K35: -472 | L35: -334 | M35: -567 | N35: 254 | O35: -24 | P35: -17 | Q35: -509 | R35: -148 | S35: -130 | T35: -68
B36: ⃤ ABSOLUTA | C36: 116 | D36: -15 | E36: 201 | F36: -111 | G36: 156 | H36: 30 | I36: 6 | J36: -7 | K36: -432 | L36: -325 | M36: -770 | N36: 184 | O36: -13 | P36: -1 | Q36: -789 | R36: 126 | S36: -109 | T36: -9
B37: ⃤ RELATIVA | C37: 0.4 | D37: -0.24 | E37: -2.68 | F37: -6.94 | G37: 2.52 | H37: 1.5 | I37: -0.32 | J37: -0.78 | K37: 10.8 | L37: 36.11 | M37: 3.79 | N37: -2.63 | O37: -1.18 | P37: -0.06 | Q37: 2.82 | R37: 0.46 | S37: -5.19 | T37: -0.15
B38: MARÇO | C38: -45 | D38: -133 | E38: -14 | F38: -146 | G38: 61 | H38: -15 | I38: -33 | J38: -18 | K38: -358 | L38: -245 | M38: 623 | N38: 202 | O38: -31 | P38: -24 | Q38: -107 | R38: -141 | S38: -92 | T38: -79
B39: ⃤ ABSOLUTA | C39: 132 | D39: -56 | E39: -140 | F39: -51 | G39: -33 | H39: -25 | I39: -58 | J39: -2 | K39: 114 | L39: 89 | M39: 1190 | N39: -52 | O39: -7 | P39: -7 | Q39: 402 | R39: 7 | S39: 38 | T39: -11
B40: ⃤ RELATIVA | C40: -0.75 | D40: 0.73 | E40: -1.11 | F40: 0.54 | G40: -0.35 | H40: -2.5 | I40: -2.32 | J40: 0.13 | K40: -0.24 | L40: -0.27 | N40: -0.2 | O40: 0.29 | P40: 0.41 | Q40: -0.79 | R40: -0.05 | S40: -0.29 | T40: 0.16
B41: ABRIL | C41: -172 | D41: -130 | E41: -107 | F41: -140 | G41: 76 | H41: -5 | I41: 497 | J41: -40 | K41: -656 | L41: -135 | M41: 429 | N41: 332 | O41: -14 | P41: -10 | Q41: -156 | R41: -157 | S41: -4 | T41: 12
B42: ⃤ ABSOLUTA | C42: -127 | D42: 3 | E42: -93 | F42: 6 | G42: 15 | H42: 10 | I42: 530 | J42: -22 | K42: -298 | L42: 110 | M42: -194 | N42: 130 | O42: 17 | P42: 14 | Q42: -49 | R42: -16 | S42: 88 | T42: 91
B43: ⃤ RELATIVA | C43: 2.82 | D43: -0.02 | E43: 6.64 | F43: -0.04 | G43: 0.25 | H43: -0.67 | I43: -16.06 | J43: 1.22 | K43: 0.83 | L43: -0.45 | M43: -0.31 | N43: 0.64 | O43: -0.55 | P43: -0.58 | Q43: 0.46 | R43: 0.11 | S43: -0.96 | T43: -1.15
B44: MAIO | C44: -86 | E44: 88 | G44: -16 | I44: 9 | K44: -516 | M44: -208 | O44: -16 | Q44: -61 | S44: 21
B45: ⃤ ABSOLUTA | C45: 86 | D45: 130 | E45: 195 | F45: 140 | G45: -92 | H45: 5 | I45: -488 | J45: 40 | K45: 140 | L45: 135 | M45: -637 | N45: -332 | O45: -2 | P45: 10 | Q45: 95 | R45: 157 | S45: 25 | T45: -12
B46: ⃤ RELATIVA | C46: -0.5 | D46: -1 | E46: -1.82 | F46: -1 | G46: -1.21 | H46: -1 | I46: -0.98 | J46: -1 | K46: -0.21 | L46: -1 | M46: -1.48 | N46: -1 | O46: 0.14 | P46: -1 | Q46: -0.61 | R46: -1 | S46: -6.25 | T46: -1
B47: JUNHO | C47: -200 | D47: -57 | E47: -4 | F47: -85 | G47: -47 | H47: -42 | I47: 67 | J47: -12 | K47: -13 | L47: 87 | M47: 634 | N47: 89 | O47: -26 | P47: -3 | Q47: -310 | R47: -136 | T47: -105
B48: ⃤ ABSOLUTA | C48: =C47-C44 -> -114 | D48: =D47-D44 -> -57 | E48: =E47-E44 -> -92 | F48: =F47-F44 -> -85 | G48: =G47-G44 -> -31 | H48: =H47-H44 -> -42 | I48: =I47-I44 -> 58 | J48: =J47-J44 -> -12 | ... T48: =T47-T44 -> -105
B49: ⃤ RELATIVA | C49: =C48/C44 -> 1.3255814 | D49: =D48/D44 -> #DIV/0! | E49: =E48/E44 -> -1.0454545 | F49: =F48/F44 -> #DIV/0! | G49: =G48/G44 -> 1.9375 | H49: =H48/H44 -> #DIV/0! | I49: =I48/I44 -> 6.4444444 | J49: =J48/J44 -> #DIV/0! | ... T49: =T48/T44 -> #DIV/0!
B50: JULHO | C50: 157 | D50: -50 | E50: 88 | F50: 102 | G50: -58 | H50: 9 | I50: -87 | J50: -11 | K50: -1207 | L50: -13 | M50: 885 | N50: 879 | O50: -34 | P50: 6 | Q50: -157 | R50: 42 | S50: -25 | T50: =-541+642 -> 101
B51: ⃤ ABSOLUTA | C51: =C50-C47 -> 357 | D51: =D50-D47 -> 7 | E51: =E50-E47 -> 92 | F51: =F50-F47 -> 187 | G51: =G50-G47 -> -11 | H51: =H50-H47 -> 51 | I51: =I50-I47 -> -154 | J51: =J50-J47 -> 1 | ... T51: =T50-T47 -> 206
B52: ⃤ RELATIVA | C52: =C51/C47 -> -1.785 | D52: =D51/D47 -> -0.12280702 | E52: =E51/E47 -> -23 | F52: =F51/F47 -> -2.2 | G52: =G51/G47 -> 0.23404255 | H52: =H51/H47 -> -1.2142857 | I52: =I51/I47 -> -2.2985075 | J52: =J51/J47 -> -0.083333333 | ... T52: =T51/T47 -> -1.9619048
B53: AGOSTO
B54: ⃤ ABSOLUTA | C54: =C53-C50 -> -157 | D54: =D53-D50 -> 50 | E54: =E53-E50 -> -88 | F54: =F53-F50 -> -102 | G54: =G53-G50 -> 58 | H54: =H53-H50 -> -9 | I54: =I53-I50 -> 87 | J54: =J53-J50 -> 11 | ... T54: =T53-T50 -> -101
B55: ⃤ RELATIVA | C55: =C54/C50 -> -1 | D55: =D54/D50 -> -1 | E55: =E54/E50 -> -1 | F55: =F54/F50 -> -1 | G55: =G54/G50 -> -1 | H55: =H54/H50 -> -1 | I55: =I54/I50 -> -1 | J55: =J54/J50 -> -1 | ... T55: =T54/T50 -> -1
B56: SETEMBRO
B57: ⃤ ABSOLUTA | C57: =C56-C53 -> 0 | D57: =D56-D53 -> 0 | E57: =E56-E53 -> 0 | F57: =F56-F53 -> 0 | G57: =G56-G53 -> 0 | H57: =H56-H53 -> 0 | I57: =I56-I53 -> 0 | J57: =J56-J53 -> 0 | ... T57: =T56-T53 -> 0
B58: ⃤ RELATIVA | C58: =C57/C53 -> #DIV/0! | D58: =D57/D53 -> #DIV/0! | E58: =E57/E53 -> #DIV/0! | F58: =F57/F53 -> #DIV/0! | G58: =G57/G53 -> #DIV/0! | H58: =H57/H53 -> #DIV/0! | I58: =I57/I53 -> #DIV/0! | J58: =J57/J53 -> #DIV/0! | ... T58: =T57/T53 -> #DIV/0!
B59: OUTUBRO
B60: ⃤ ABSOLUTA | C60: =C59-C56 -> 0 | D60: =D59-D56 -> 0 | E60: =E59-E56 -> 0 | F60: =F59-F56 -> 0 | G60: =G59-G56 -> 0 | H60: =H59-H56 -> 0 | I60: =I59-I56 -> 0 | J60: =J59-J56 -> 0 | ... T60: =T59-T56 -> 0
B61: ⃤ RELATIVA | C61: =C60/C56 -> #DIV/0! | D61: =D60/D56 -> #DIV/0! | E61: =E60/E56 -> #DIV/0! | F61: =F60/F56 -> #DIV/0! | G61: =G60/G56 -> #DIV/0! | H61: =H60/H56 -> #DIV/0! | I61: =I60/I56 -> #DIV/0! | J61: =J60/J56 -> #DIV/0! | ... T61: =T60/T56 -> #DIV/0!
B62: NOVEMBRO
B63: ⃤ ABSOLUTA | C63: =C62-C59 -> 0 | D63: =D62-D59 -> 0 | E63: =E62-E59 -> 0 | F63: =F62-F59 -> 0 | G63: =G62-G59 -> 0 | H63: =H62-H59 -> 0 | I63: =I62-I59 -> 0 | J63: =J62-J59 -> 0 | ... T63: =T62-T59 -> 0
B64: ⃤ RELATIVA | C64: =C63/C59 -> #DIV/0! | D64: =D63/D59 -> #DIV/0! | E64: =E63/E59 -> #DIV/0! | F64: =F63/F59 -> #DIV/0! | G64: =G63/G59 -> #DIV/0! | H64: =H63/H59 -> #DIV/0! | I64: =I63/I59 -> #DIV/0! | J64: =J63/J59 -> #DIV/0! | ... T64: =T63/T59 -> #DIV/0!
B65: DEZEMBRO
B66: ⃤ ABSOLUTA | C66: =C65-C62 -> 0 | D66: =D65-D62 -> 0 | E66: =E65-E62 -> 0 | F66: =F65-F62 -> 0 | G66: =G65-G62 -> 0 | H66: =H65-H62 -> 0 | I66: =I65-I62 -> 0 | J66: =J65-J62 -> 0 | ... T66: =T65-T62 -> 0
B67: ⃤ RELATIVA | C67: =C66/C62 -> #DIV/0! | D67: =D66/D62 -> #DIV/0! | E67: =E66/E62 -> #DIV/0! | F67: =F66/F62 -> #DIV/0! | G67: =G66/G62 -> #DIV/0! | H67: =H66/H62 -> #DIV/0! | I67: =I66/I62 -> #DIV/0! | J67: =J66/J62 -> #DIV/0! | ... T67: =T66/T62 -> #DIV/0!
B68: Média | C68: =AVERAGE(C34:C35,C38,C44,C41,C47,C50,C53,C56,C59,C62,C65) -> -116.57143 | D68: =AVERAGE(D34:D35,D38,D44,D41,D47,D50,D53,D56,D59,D62,D65) -> -84.833333 | E68: =AVERAGE(E34:E35,E38,E44,E41,E47,E50,E53,E56,E59,E62,E65) -> 14.571429 | F68: =AVERAGE(F34:F35,F38,F44,F41,F47,F50,F53,F56,F59,F62,F65) -> -58 | G68: =AVERAGE(G34:G35,G38,G44,G41,G47,G50,G53,G56,G59,G62,G65) -> 6.8571429 | H68: =AVERAGE(H34:H35,H38,H44,H41,H47,H50,H53,H56,H59,H62,H65) -> -10.5 | I68: =AVERAGE(I34:I35,I38,I44,I41,I47,I50,I53,I56,I59,I62,I65) -> 71 | J68: =AVERAGE(J34:J35,J38,J44,J41,J47,J50,J53,J56,J59,J62,J65) -> -17.666667 | ... T68: =AVERAGE(T34:T35,T38,T44,T41,T47,T50,T53,T56,T59,T62,T65) -> -33
B69: 20 vs 32 | C69: =(C68-D68)/C68 -> 0.27226307 | E69: =(E68-F68)/E68 -> 4.9803922 | G69: =(G68-H68)/G68 -> 2.53125 | I69: =(I68-J68)/I68 -> 1.2488263 | K69: =(K68-L68)/K68 -> 0.76788269 | M69: =(M68-N68)/M68 -> -0.065699516 | O69: =(O68-P68)/O68 -> 0.52136752 | Q69: =(Q68-R68)/Q68 -> 0.068954248 | S69: =(S68-T68)/S68 -> 0.21115538
B71: RENDIMENTOS
C72: BATATA | E72: ALFACE L6 | G72: SOPAS | I72: COB CHOCOLATE | K72: COB CARAMELO | M72: COB MORANGO | O72: COB SNICKERS | Q72: COB MARS | S72: LEITE SUNDAE
C73: 20 | D73: 32 | E73: 20 | F73: 32 | G73: 20 | H73: 32 | I73: 20 | J73: 32 | K73: 20 | L73: 32 | M73: 20 | N73: 32 | O73: 20 | P73: 32 | Q73: 20 | R73: 32 | S73: 20 | T73: 32
B74: JANEIRO | C74: -30 | D74: -6.6 | E74: 57 | F74: 6.2 | I74: 5.5 | J74: 2 | K74: 6.9 | L74: 1.2 | M74: 0.24 | N74: -1.6 | O74: 4.7 | P74: 2.2 | Q74: -7.8 | R74: -7.3 | S74: 111 | T74: 25
B75: FEVEREIRO | C75: -136 | D75: -5 | E75: 27.136 | F75: 1.4 | G75: -50.5 | I75: 4.04 | J75: 0.6 | K75: 3.6 | L75: -1.3 | M75: -0.6 | N75: -3.6 | O75: 5.4 | P75: 2.8 | Q75: -9 | R75: -8 | S75: 90 | T75: 13
B76: ⃤ ABSOLUTA | C76: -106 | D76: 1.6 | E76: 39 | F76: -4.8 | G76: -50.5 | H76: 0 | I76: 3.4 | J76: -1.4 | K76: 2.7 | L76: -2.5 | M76: 2 | N76: -2 | O76: 1.9 | P76: 0.6 | Q76: -4.9 | R76: -0.7 | S76: 45 | T76: -12
B77: ⃤ RELATIVA | C77: -3.53 | D77: 0.24 | E77: 0.02 | F77: -0.77 | G77: #DIV/0! | H77: #DIV/0! | I77: -0.62 | J77: -0.7 | K77: 0.39 | L77: -2.08 | M77: -8.33 | N77: -1.25 | O77: -0.4 | P77: -0.27 | Q77: -0.63 | R77: -0.1 | S77: -0.41 | T77: 0.48
B78: MARÇO | C78: 27.66 | D78: -42 | E78: 56.603 | F78: 25 | G78: -19 | H78: -26.8 | I78: 5.4 | J78: 3.5 | K78: -6.3 | L78: 2 | M78: -1.24 | N78: -2.6 | P78: 2.1 | Q78: -10.724 | R78: -10.7 | S78: 67 | T78: 2.2
B79: ⃤ ABSOLUTA | C79: 163.66 | D79: -37 | E79: 29.467 | F79: 23.6 | G79: 31.5 | H79: -26.8 | I79: 1.36 | J79: 2.9 | K79: -9.9 | L79: 3.3 | M79: -0.64 | N79: 1 | O79: -5.4 | P79: -0.7 | Q79: -1.724 | R79: -2.7 | S79: -23 | T79: -10.8
B80: ⃤ RELATIVA | C80: -1.2 | D80: 7.4 | E80: 1.09 | F80: 16.86 | G80: -0.62 | H80: #DIV/0! | I80: 0.34 | J80: 4.83 | K80: -2.75 | L80: -2.54 | M80: 1.07 | N80: -0.28 | O80: -1 | P80: -0.25 | Q80: 0.19 | R80: 0.34 | S80: -0.26 | T80: -0.83
B81: ABRIL | C81: -89 | D81: -67 | E81: 20 | F81: 3.5 | G81: -53.89 | H81: -5.7 | I81: 6 | J81: 0.3 | K81: -7.7 | L81: 0.7 | M81: -6.9 | N81: -5 | O81: 5 | P81: 2 | Q81: -83 | R81: -10 | S81: 95.01 | T81: -16
B82: ⃤ ABSOLUTA | C82: -116.66 | D82: -25 | E82: -36.603 | F82: -21.5 | G82: -34.89 | H82: 21.1 | I82: 0.6 | J82: -3.2 | K82: -1.4 | L82: -1.3 | M82: -5.66 | N82: -2.4 | O82: 5 | P82: -0.1 | Q82: -72.276 | R82: 0.7 | S82: 28.01 | T82: -18.2
B83: ⃤ RELATIVA | C83: -4.22 | D83: 0.6 | E83: -0.65 | F83: -0.86 | G83: 1.84 | H83: -0.79 | I83: 0.11 | J83: -0.91 | K83: 0.22 | L83: -0.65 | M83: 4.56 | N83: 0.92 | O83: #DIV/0! | P83: -0.05 | Q83: 6.74 | R83: -0.07 | S83: 0.42 | T83: -8.27
B84: MAIO | C84: -7.9 | E84: 9.66 | G84: -22.93 | I84: 2.9 | K84: 3.28 | M84: 1.62 | O84: 4.51 | Q84: -8.14 | S84: 80.1
B85: ⃤ ABSOLUTA | C85: 81.1 | D85: 67 | E85: -10.34 | F85: -3.5 | G85: 30.96 | H85: 5.7 | I85: -3.1 | J85: -0.3 | K85: 10.98 | L85: -0.7 | M85: 8.52 | N85: 5 | O85: -0.49 | P85: -2 | Q85: 74.86 | R85: 10 | S85: -14.91 | T85: 16
B86: ⃤ RELATIVA | C86: -0.91 | D86: -1 | E86: -0.52 | F86: -1 | G86: -0.57 | H86: -1 | I86: -0.52 | J86: -1 | K86: -1.43 | L86: -1 | M86: -1.23 | N86: -1 | O86: -0.1 | P86: -1 | Q86: -0.9 | R86: -1 | S86: -0.16 | T86: -1
B87: JUNHO | C87: -25.4 | D87: 3 | E87: -38.92 | F87: -1.5 | G87: 41.5 | H87: -15.5 | I87: 4.7 | J87: -1.5 | K87: 11.58 | L87: -4.1 | M87: -5.1 | N87: -3.2 | O87: 3.4 | P87: 0.6 | Q87: -6 | R87: -7.5 | S87: 101.2 | T87: -37.9
B88: ⃤ ABSOLUTA | C88: =C87-C84 -> -17.5 | D88: =D87-D84 -> 3 | E88: =E87-E84 -> -48.58 | F88: =F87-F84 -> -1.5 | G88: =G87-G84 -> 64.43 | H88: =H87-H84 -> -15.5 | I88: =I87-I84 -> 1.8 | J88: =J87-J84 -> -1.5 | ... T88: =T87-T84 -> -37.9
B89: ⃤ RELATIVA | C89: =C88/C84 -> 2.2151899 | D89: =D88/D84 -> #DIV/0! | E89: =E88/E84 -> -5.0289855 | F89: =F88/F84 -> #DIV/0! | G89: =G88/G84 -> -2.8098561 | H89: =H88/H84 -> #DIV/0! | I89: =I88/I84 -> 0.62068966 | J89: =J88/J84 -> #DIV/0! | ... T89: =T88/T84 -> #DIV/0!
B90: JULHO | C90: 75 | D90: 60 | E90: -15 | F90: 15 | G90: -81 | H90: -20 | I90: 7 | J90: -1 | K90: 20 | L90: 6 | N90: -7 | O90: 5 | P90: 2 | Q90: -10 | R90: -14 | S90: 158 | T90: 70
B91: ⃤ ABSOLUTA | C91: =C90-C87 -> 100.4 | D91: =D90-D87 -> 57 | E91: =E90-E87 -> 23.92 | F91: =F90-F87 -> 16.5 | G91: =G90-G87 -> -122.5 | H91: =H90-H87 -> -4.5 | I91: =I90-I87 -> 2.3 | J91: =J90-J87 -> 0.5 | ... T91: =T90-T87 -> 107.9
B92: ⃤ RELATIVA | C92: =C91/C87 -> -3.9527559 | D92: =D91/D87 -> 19 | E92: =E91/E87 -> -0.61459404 | F92: =F91/F87 -> -11 | G92: =G91/G87 -> -2.9518072 | H92: =H91/H87 -> 0.29032258 | I92: =I91/I87 -> 0.4893617 | J92: =J91/J87 -> -0.33333333 | ... T92: =T91/T87 -> -2.8469657
B93: AGOSTO
B94: ⃤ ABSOLUTA | C94: =C93-C90 -> -75 | D94: =D93-D90 -> -60 | E94: =E93-E90 -> 15 | F94: =F93-F90 -> -15 | G94: =G93-G90 -> 81 | H94: =H93-H90 -> 20 | I94: =I93-I90 -> -7 | J94: =J93-J90 -> 1 | ... T94: =T93-T90 -> -70
B95: ⃤ RELATIVA | C95: =C94/C90 -> -1 | D95: =D94/D90 -> -1 | E95: =E94/E90 -> -1 | F95: =F94/F90 -> -1 | G95: =G94/G90 -> -1 | H95: =H94/H90 -> -1 | I95: =I94/I90 -> -1 | J95: =J94/J90 -> -1 | ... T95: =T94/T90 -> -1
B96: SETEMBRO
B97: ⃤ ABSOLUTA | C97: =C96-C93 -> 0 | D97: =D96-D93 -> 0 | E97: =E96-E93 -> 0 | F97: =F96-F93 -> 0 | G97: =G96-G93 -> 0 | H97: =H96-H93 -> 0 | I97: =I96-I93 -> 0 | J97: =J96-J93 -> 0 | ... T97: =T96-T93 -> 0
B98: ⃤ RELATIVA | C98: =C97/C93 -> #DIV/0! | D98: =D97/D93 -> #DIV/0! | E98: =E97/E93 -> #DIV/0! | F98: =F97/F93 -> #DIV/0! | G98: =G97/G93 -> #DIV/0! | H98: =H97/H93 -> #DIV/0! | I98: =I97/I93 -> #DIV/0! | J98: =J97/J93 -> #DIV/0! | ... T98: =T97/T93 -> #DIV/0!
B99: OUTUBRO
B100: ⃤ ABSOLUTA | C100: =C99-C96 -> 0 | D100: =D99-D96 -> 0 | E100: =E99-E96 -> 0 | F100: =F99-F96 -> 0 | G100: =G99-G96 -> 0 | H100: =H99-H96 -> 0 | I100: =I99-I96 -> 0 | J100: =J99-J96 -> 0 | ... T100: =T99-T96 -> 0
B101: ⃤ RELATIVA | C101: =C100/C96 -> #DIV/0! | D101: =D100/D96 -> #DIV/0! | E101: =E100/E96 -> #DIV/0! | F101: =F100/F96 -> #DIV/0! | G101: =G100/G96 -> #DIV/0! | H101: =H100/H96 -> #DIV/0! | I101: =I100/I96 -> #DIV/0! | J101: =J100/J96 -> #DIV/0! | ... T101: =T100/T96 -> #DIV/0!
B102: NOVEMBRO
B103: ⃤ ABSOLUTA | C103: =C102-C99 -> 0 | D103: =D102-D99 -> 0 | E103: =E102-E99 -> 0 | F103: =F102-F99 -> 0 | G103: =G102-G99 -> 0 | H103: =H102-H99 -> 0 | I103: =I102-I99 -> 0 | J103: =J102-J99 -> 0 | ... T103: =T102-T99 -> 0
B104: ⃤ RELATIVA | C104: =C103/C99 -> #DIV/0! | D104: =D103/D99 -> #DIV/0! | E104: =E103/E99 -> #DIV/0! | F104: =F103/F99 -> #DIV/0! | G104: =G103/G99 -> #DIV/0! | H104: =H103/H99 -> #DIV/0! | I104: =I103/I99 -> #DIV/0! | J104: =J103/J99 -> #DIV/0! | ... T104: =T103/T99 -> #DIV/0!
B105: DEZEMBRO
B106: ⃤ ABSOLUTA | C106: =C105-C102 -> 0 | D106: =D105-D102 -> 0 | E106: =E105-E102 -> 0 | F106: =F105-F102 -> 0 | G106: =G105-G102 -> 0 | H106: =H105-H102 -> 0 | I106: =I105-I102 -> 0 | J106: =J105-J102 -> 0 | ... T106: =T105-T102 -> 0
B107: ⃤ RELATIVA | C107: =C106/C102 -> #DIV/0! | D107: =D106/D102 -> #DIV/0! | E107: =E106/E102 -> #DIV/0! | F107: =F106/F102 -> #DIV/0! | G107: =G106/G102 -> #DIV/0! | H107: =H106/H102 -> #DIV/0! | I107: =I106/I102 -> #DIV/0! | J107: =J106/J102 -> #DIV/0! | ... T107: =T106/T102 -> #DIV/0!
B108: Média | C108: =AVERAGE(C74:C75,C78,C84,C81,C87,C90,C93,C96,C99,C102,C105) -> -26.52 | D108: =AVERAGE(D74:D75,D78,D84,D81,D87,D90,D93,D96,D99,D102,D105) -> -9.6 | E108: =AVERAGE(E74:E75,E78,E84,E81,E87,E90,E93,E96,E99,E102,E105) -> 16.639857 | F108: =AVERAGE(F74:F75,F78,F84,F81,F87,F90,F93,F96,F99,F102,F105) -> 8.2666667 | G108: =AVERAGE(G74:G75,G78,G84,G81,G87,G90,G93,G96,G99,G102,G105) -> -30.97 | H108: =AVERAGE(H74:H75,H78,H84,H81,H87,H90,H93,H96,H99,H102,H105) -> -17 | I108: =AVERAGE(I74:I75,I78,I84,I81,I87,I90,I93,I96,I99,I102,I105) -> 5.0771429 | J108: =AVERAGE(J74:J75,J78,J84,J81,J87,J90,J93,J96,J99,J102,J105) -> 0.65 | ... T108: =AVERAGE(T74:T75,T78,T84,T81,T87,T90,T93,T96,T99,T102,T105) -> 9.3833333
B109: 20 vs 32 | C109: =(C108-D108)/C108 -> 0.63800905 | E109: =(E108-F108)/E108 -> 0.50320086 | G109: =(G108-H108)/G108 -> 0.45108169 | I109: =(I108-J108)/I108 -> 0.87197524 | K109: =(K108-L108)/K108 -> 0.83258929 | M109: =(M108-N108)/M108 -> -0.91986644 | O109: =(O108-P108)/O108 -> 0.58229204 | Q109: =(Q108-R108)/Q108 -> 0.50184657 | S109: =(S108-T108)/S108 -> 0.9064753
B111: COMPARAÇÃO DE CUSTOS AMADORA | K111: COMPARAÇÃO DE CUSTOS QUELUZ
A112: OBJETIVO | C112: CUSTO INVENTÁRIO 20) | E112: CUSTO TEÓRICO (20) | G112: DESVIO (20) | I112: DESVIO RENDIMENTO (20) | K112: CUSTO INVENTÁRIO (32) | M112: CUSTO TEÓRICO (32) | O112: DESVIO (32) | Q112: DESVIO RENDIMENTO (32) | T112: CUSTO INVENTÁRIO (20) | U112: CUSTO TEÓRICO (20) | V112: DESVIO (20) | W112: DESVIO RENDIMENTO (20) | X112: CUSTO INVENTÁRIO (32) | Y112: CUSTO TEÓRICO (32) | Z112: DESVIO (32) | AA112: DESVIO RENDIMENTO (32)
A113: DESVIO | B113: JANEIRO | G113: =C113-E113 -> 0 | O113: =K113-M113 -> 0 | T113: =C113 -> 0 | U113: =E113 -> 0 | V113: =G113 -> 0 | W113: =I113 -> 0 | X113: =K113 -> 0 | Y113: =M113 -> 0 | Z113: =O113 -> 0 | AA113: =Q113 -> 0
A114: 0 | B114: FEVEREIRO | G114: =C114-E114 -> 0 | K114: 0.2671 | M114: 0.264 | O114: 0.0031 | Q114: 0.0008 | T114: =C114 -> 0 | U114: =E114 -> 0 | V114: =G114 -> 0 | W114: =I114 -> 0 | X114: =K114 -> 0.2671 | Y114: =M114 -> 0.264 | Z114: =O114 -> 0.0031 | AA114: =Q114 -> 0.0008
B115: ⃤ ABSOLUTA | C115: =C114-C113 -> 0 | E115: =E114-E113 -> 0 | G115: =G114-G113 -> 0 | I115: =I114-I113 -> 0 | K115: 0.2671 | M115: 0.264 | O115: 0.0031 | Q115: 0.0008 | T115: =C117 -> 0 | U115: =E117 -> 0 | V115: =G117 -> 0 | W115: =I117 -> 0 | X115: =K117 -> 0.2759 | Y115: =M117 -> 0.2699 | Z115: =O117 -> -0.006 | AA115: =Q117 -> -0.0029
B116: ⃤ RELATIVA | C116: =C115/C113 -> #DIV/0! | E116: =E115/E113 -> #DIV/0! | G116: =G115/G113 -> #DIV/0! | I116: =I115/I113 -> #DIV/0! | K116: #DIV/0! | M116: #DIV/0! | O116: #DIV/0! | Q116: #DIV/0! | T116: =C120 -> 0 | U116: =E120 -> 0 | V116: =G120 -> 0 | W116: =I120 -> 0 | X116: =K120 -> 0.2708 | Y116: =M120 -> 0.2654 | Z116: =O120 -> -0.0054 | AA116: =Q120 -> -0.0005
B117: MARÇO | G117: =C117-E117 -> 0 | K117: 0.2759 | M117: 0.2699 | O117: -0.006 | Q117: -0.0029 | T117: =E123 -> 0 | U117: =E123 -> 0 | V117: =G123 -> 0 | W117: =I123 -> 0 | X117: =K123 -> 0.2775 | Y117: =M123 -> 0.2754 | Z117: =O123 -> 0.0021 | AA117: =Q12 -> 0
B118: ⃤ ABSOLUTA | C118: =C117-C114 -> 0 | E118: =E117-E114 -> 0 | G118: =G117-G114 -> 0 | I118: =I117-I114 -> 0 | K118: 0.0088 | M118: 0.0059 | O118: -0.0091 | Q118: -0.0037 | T118: =C126 -> 0 | U118: =E126 -> 0 | V118: =G126 -> 0 | W118: =I126 -> 0 | X118: =K126 -> 0.2818 | Y118: =M126 -> 0.241 | Z118: =O126 -> 0.0408 | AA118: =Q126 -> -0.0055
...

Sheet Manutenção
D2: ANÁLISE DE CUSTOS
E3: JANEIRO | F3: FEVEREIRO | G3: MARÇO | H3: ABRIL | I3: MAIO | J3: JUNHO | K3: JULHO | L3: AGOSTO | M3: SETEMBRO | N3: OUTUBRO | O3: NOVEMBRO | P3: DEZEMBRO | Q3: ANO
D4: 20- VENDAS | E4: =Serviço!C70 -> 288945 | F4: =Serviço!D70 -> 254163 | G4: =Serviço!E70 -> 280532 | H4: =Serviço!F70 -> 247258 | I4: =Serviço!G70 -> 251597 | J4: =Serviço!H70 -> 252397 | K4: =Serviço!I70 -> 268928 | L4: =Serviço!J70 -> 286413 | ... P4: =Serviço!N70 -> 82979 | Q4: =SUM(E4:P4) -> 2932397
D5: 32- VENDAS | E5: =Serviço!C81 -> 157396 | F5: =Serviço!D81 -> 143160 | G5: =Serviço!E81 -> 153168 | H5: =Serviço!F81 -> 142879 | I5: =Serviço!G81 -> 161979 | J5: =Serviço!H81 -> 159094 | K5: =Serviço!I81 -> 165280 | L5: =Serviço!J81 -> 168534 | ... P5: =Serviço!N81 -> 57366 | Q5: =SUM(E5:P5) -> 1788785
D6: 20- GASTOS GERAIS | E6: 2584 | Q6: =SUM(E6:P6) -> 2584
D7: 20- OPS | E7: 2962 | Q7: =SUM(E7:P7) -> 2962
D8: 20- MAN&REP | E8: 2648 | Q8: =SUM(E8:P8) -> 2648
D9: 32- GASTOS GERAIS | E9: 1821 | Q9: =SUM(E9:P9) -> 1821
D10: 32- OPS | E10: 2132 | Q10: =SUM(E10:P10) -> 2132
D11: 32- MAN&REP | E11: 790 | Q11: =SUM(E11:P11) -> 790
D31: GASTOS GERAIS
E32: JANEIRO | F32: FEVEREIRO | G32: MARÇO | H32: ABRIL | I32: MAIO | J32: JUNHO | K32: JULHO | L32: AGOSTO | M32: SETEMBRO | N32: OUTUBRO | O32: NOVEMBRO | P32: DEZEMBRO | Q32: ANO
D33: 20-ÁGUA | E33: 118 | Q33: =SUM(E33:P33) -> 118
D34: 20-ELETRICIDADE | E34: 1478 | Q34: =SUM(E34:P34) -> 1478
D35: 32-ÁGUA | E35: 128 | Q35: =SUM(E35:P35) -> 128
D36: 32-ELETRICIDADE | E36: 1135 | Q36: =SUM(E36:P36) -> 1135
C37: OBJETIVO | D37: 20- KW 22 vs 23 | E37: =27283-27548 -> -265 | Q37: =SUM(E37:P37) -> -265
C38: = ou > a 2022 | D38: 32- KW 22 vs 23 | E38: =21033-20809 -> 224 | Q38: =SUM(E38:P38) -> 224
A56: OPS
C57: EASY WASH | E57: APC | G57: LIQUÍDO WC | I57: GRILL CLEANER | K57: MASCARAS | M57: GEL DA MÃOS | O57: SACOS DO LIXO | Q57: ESFREGÃO | S57: SOLID FLOORCARE
C58: ∆ ABSOLUTA | D58: ∆ RELATIVA | E58: ∆ ABSOLUTA | F58: ∆ RELATIVA | G58: ∆ ABSOLUTA | H58: ∆ RELATIVA | I58: ∆ ABSOLUTA | J58: ∆ RELATIVA | K58: ∆ ABSOLUTA | L58: ∆ RELATIVA | M58: ∆ ABSOLUTA | N58: ∆ RELATIVA | O58: ∆ ABSOLUTA | P58: ∆ RELATIVA | Q58: ∆ ABSOLUTA | R58: ∆ RELATIVA | S58: ∆ ABSOLUTA | T58: ∆ RELATIVA
A59: JANEIRO | B59: AMADORA | C59: -37 | E59: -1 | G59: 6 | I59: -35 | K59: -3 | M59: -3 | O59: -13 | Q59: -4 | S59: -2
B60: QUELUZ | C60: -57 | E60: -1 | G60: 0 | I60: -24 | K60: -1 | M60: -1 | O60: -351 | Q60: -5 | S60: -1
A61: FEVEREIRO | B61: AMADORA | C61: -51 | D61: =(C61-C59)/C59 -> 0.37837838 | E61: -1 | F61: =(E61-E59)/E59 -> 0 | G61: -1 | H61: =(G61-G59)/G59 -> -1.1666667 | I61: -45 | J61: =(I61-I59)/I59 -> 0.28571429 | K61: -3 | L61: =(K61-K59)/K59 -> 0 | M61: -3 | N61: =(M61-M59)/M59 -> 0 | O61: -260 | P61: =(O61-O59)/O59 -> 19 | Q61: -7 | R61: =(Q61-Q59)/Q59 -> 0.75 | S61: -3 | T61: =(S61-S59)/S59 -> 0.5
B62: QUELUZ | C62: -122 | D62: =(C62-C60)/C60 -> 1.1403509 | E62: -1 | F62: =(E62-E60)/E60 -> 0 | G62: 1 | H62: =(G62-G60)/G60 -> #DIV/0! | I62: 5 | J62: =(I62-I60)/I60 -> -1.2083333 | K62: 0 | L62: =(K62-K60)/K60 -> -1 | M62: 0 | N62: =(M62-M60)/M60 -> -1 | O62: 106 | P62: =(O62-O60)/O60 -> -1.3019943 | Q62: 1 | R62: =(Q62-Q60)/Q60 -> -1.2 | S62: 0 | T62: =(S62-S60)/S60 -> -1
A63: MARÇO | B63: AMADORA | D63: =(C63-C61)/C61 -> -1 | F63: =(E63-E61)/E61 -> -1 | H63: =(G63-G61)/G61 -> -1 | J63: =(I63-I61)/I61 -> -1 | L63: =(K63-K61)/K61 -> -1 | N63: =(M63-M61)/M61 -> -1 | P63: =(O63-O61)/O61 -> -1 | R63: =(Q63-Q61)/Q61 -> -1 | T63: =(S63-S61)/S61 -> -1
B64: QUELUZ | D64: =(C64-C62)/C62 -> -1 | F64: =(E64-E62)/E62 -> -1 | H64: =(G64-G62)/G62 -> -1 | J64: =(I64-I62)/I62 -> -1 | L64: =(K64-K62)/K62 -> #DIV/0! | N64: =(M64-M62)/M62 -> #DIV/0! | P64: =(O64-O62)/O62 -> -1 | R64: =(Q64-Q62)/Q62 -> -1 | T64: =(S64-S62)/S62 -> #DIV/0!
A65: ABRIL | B65: AMADORA | D65: =(C65-C63)/C63 -> #DIV/0! | F65: =(E65-E63)/E63 -> #DIV/0! | H65: =(G65-G63)/G63 -> #DIV/0! | J65: =(I65-I63)/I63 -> #DIV/0! | L65: =(K65-K63)/K63 -> #DIV/0! | N65: =(M65-M63)/M63 -> #DIV/0! | P65: =(O65-O63)/O63 -> #DIV/0! | R65: =(Q65-Q63)/Q63 -> #DIV/0! | T65: =(S65-S63)/S63 -> #DIV/0!
B66: QUELUZ | D66: =(C66-C64)/C64 -> #DIV/0! | F66: =(E66-E64)/E64 -> #DIV/0! | H66: =(G66-G64)/G64 -> #DIV/0! | J66: =(I66-I64)/I64 -> #DIV/0! | L66: =(K66-K64)/K64 -> #DIV/0! | N66: =(M66-M64)/M64 -> #DIV/0! | P66: =(O66-O64)/O64 -> #DIV/0! | R66: =(Q66-Q64)/Q64 -> #DIV/0! | T66: =(S66-S64)/S64 -> #DIV/0!
A67: MAIO | B67: AMADORA | D67: =(C67-C65)/C65 -> #DIV/0! | F67: =(E67-E65)/E65 -> #DIV/0! | H67: =(G67-G65)/G65 -> #DIV/0! | J67: =(I67-I65)/I65 -> #DIV/0! | L67: =(K67-K65)/K65 -> #DIV/0! | N67: =(M67-M65)/M65 -> #DIV/0! | P67: =(O67-O65)/O65 -> #DIV/0! | R67: =(Q67-Q65)/Q65 -> #DIV/0! | T67: =(S67-S65)/S65 -> #DIV/0!
B68: QUELUZ | D68: =(C68-C66)/C66 -> #DIV/0! | F68: =(E68-E66)/E66 -> #DIV/0! | H68: =(G68-G66)/G66 -> #DIV/0! | J68: =(I68-I66)/I66 -> #DIV/0! | L68: =(K68-K66)/K66 -> #DIV/0! | N68: =(M68-M66)/M66 -> #DIV/0! | P68: =(O68-O66)/O66 -> #DIV/0! | R68: =(Q68-Q66)/Q66 -> #DIV/0! | T68: =(S68-S66)/S66 -> #DIV/0!
A69: JUNHO | B69: AMADORA | D69: =(C69-C67)/C67 -> #DIV/0! | F69: =(E69-E67)/E67 -> #DIV/0! | H69: =(G69-G67)/G67 -> #DIV/0! | J69: =(I69-I67)/I67 -> #DIV/0! | L69: =(K69-K67)/K67 -> #DIV/0! | N69: =(M69-M67)/M67 -> #DIV/0! | P69: =(O69-O67)/O67 -> #DIV/0! | R69: =(Q69-Q67)/Q67 -> #DIV/0! | T69: =(S69-S67)/S67 -> #DIV/0!
B70: QUELUZ | D70: =(C70-C68)/C68 -> #DIV/0! | F70: =(E70-E68)/E68 -> #DIV/0! | H70: =(G70-G68)/G68 -> #DIV/0! | J70: =(I70-I68)/I68 -> #DIV/0! | L70: =(K70-K68)/K68 -> #DIV/0! | N70: =(M70-M68)/M68 -> #DIV/0! | P70: =(O70-O68)/O68 -> #DIV/0! | R70: =(Q70-Q68)/Q68 -> #DIV/0! | T70: =(S70-S68)/S68 -> #DIV/0!
A71: JULHO | B71: AMADORA | D71: =(C71-C69)/C69 -> #DIV/0! | F71: =(E71-E69)/E69 -> #DIV/0! | H71: =(G71-G69)/G69 -> #DIV/0! | J71: =(I71-I69)/I69 -> #DIV/0! | L71: =(K71-K69)/K69 -> #DIV/0! | N71: =(M71-M69)/M69 -> #DIV/0! | P71: =(O71-O69)/O69 -> #DIV/0! | R71: =(Q71-Q69)/Q69 -> #DIV/0! | T71: =(S71-S69)/S69 -> #DIV/0!
B72: QUELUZ | D72: =(C72-C70)/C70 -> #DIV/0! | F72: =(E72-E70)/E70 -> #DIV/0! | H72: =(G72-G70)/G70 -> #DIV/0! | J72: =(I72-I70)/I70 -> #DIV/0! | L72: =(K72-K70)/K70 -> #DIV/0! | N72: =(M72-M70)/M70 -> #DIV/0! | P72: =(O72-O70)/O70 -> #DIV/0! | R72: =(Q72-Q70)/Q70 -> #DIV/0! | T72: =(S72-S70)/S70 -> #DIV/0!
A73: AGOSTO | B73: AMADORA | D73: =(C73-C71)/C71 -> #DIV/0! | F73: =(E73-E71)/E71 -> #DIV/0! | H73: =(G73-G71)/G71 -> #DIV/0! | J73: =(I73-I71)/I71 -> #DIV/0! | L73: =(K73-K71)/K71 -> #DIV/0! | N73: =(M73-M71)/M71 -> #DIV/0! | P73: =(O73-O71)/O71 -> #DIV/0! | R73: =(Q73-Q71)/Q71 -> #DIV/0! | T73: =(S73-S71)/S71 -> #DIV/0!
B74: QUELUZ | D74: =(C74-C72)/C72 -> #DIV/0! | F74: =(E74-E72)/E72 -> #DIV/0! | H74: =(G74-G72)/G72 -> #DIV/0! | J74: =(I74-I72)/I72 -> #DIV/0! | L74: =(K74-K72)/K72 -> #DIV/0! | N74: =(M74-M72)/M72 -> #DIV/0! | P74: =(O74-O72)/O72 -> #DIV/0! | R74: =(Q74-Q72)/Q72 -> #DIV/0! | T74: =(S74-S72)/S72 -> #DIV/0!
A75: SETEMBRO | B75: AMADORA | D75: =(C75-C73)/C73 -> #DIV/0! | F75: =(E75-E73)/E73 -> #DIV/0! | H75: =(G75-G73)/G73 -> #DIV/0! | J75: =(I75-I73)/I73 -> #DIV/0! | L75: =(K75-K73)/K73 -> #DIV/0! | N75: =(M75-M73)/M73 -> #DIV/0! | P75: =(O75-O73)/O73 -> #DIV/0! | R75: =(Q75-Q73)/Q73 -> #DIV/0! | T75: =(S75-S73)/S73 -> #DIV/0!
B76: QUELUZ | D76: =(C76-C74)/C74 -> #DIV/0! | F76: =(E76-E74)/E74 -> #DIV/0! | H76: =(G76-G74)/G74 -> #DIV/0! | J76: =(I76-I74)/I74 -> #DIV/0! | L76: =(K76-K74)/K74 -> #DIV/0! | N76: =(M76-M74)/M74 -> #DIV/0! | P76: =(O76-O74)/O74 -> #DIV/0! | R76: =(Q76-Q74)/Q74 -> #DIV/0! | T76: =(S76-S74)/S74 -> #DIV/0!
A77: OUTUBRO | B77: AMADORA | D77: =(C77-C75)/C75 -> #DIV/0! | F77: =(E77-E75)/E75 -> #DIV/0! | H77: =(G77-G75)/G75 -> #DIV/0! | J77: =(I77-I75)/I75 -> #DIV/0! | L77: =(K77-K75)/K75 -> #DIV/0! | N77: =(M77-M75)/M75 -> #DIV/0! | P77: =(O77-O75)/O75 -> #DIV/0! | R77: =(Q77-Q75)/Q75 -> #DIV/0! | T77: =(S77-S75)/S75 -> #DIV/0!
B78: QUELUZ | D78: =(C78-C76)/C76 -> #DIV/0! | F78: =(E78-E76)/E76 -> #DIV/0! | H78: =(G78-G76)/G76 -> #DIV/0! | J78: =(I78-I76)/I76 -> #DIV/0! | L78: =(K78-K76)/K76 -> #DIV/0! | N78: =(M78-M76)/M76 -> #DIV/0! | P78: =(O78-O76)/O76 -> #DIV/0! | R78: =(Q78-Q76)/Q76 -> #DIV/0! | T78: =(S78-S76)/S76 -> #DIV/0!
A79: NOVEMBRO | B79: AMADORA | D79: =(C79-C77)/C77 -> #DIV/0! | F79: =(E79-E77)/E77 -> #DIV/0! | H79: =(G79-G77)/G77 -> #DIV/0! | J79: =(I79-I77)/I77 -> #DIV/0! | L79: =(K79-K77)/K77 -> #DIV/0! | N79: =(M79-M77)/M77 -> #DIV/0! | P79: =(O79-O77)/O77 -> #DIV/0! | R79: =(Q79-Q77)/Q77 -> #DIV/0! | T79: =(S79-S77)/S77 -> #DIV/0!
B80: QUELUZ | D80: =(C80-C78)/C78 -> #DIV/0! | F80: =(E80-E78)/E78 -> #DIV/0! | H80: =(G80-G78)/G78 -> #DIV/0! | J80: =(I80-I78)/I78 -> #DIV/0! | L80: =(K80-K78)/K78 -> #DIV/0! | N80: =(M80-M78)/M78 -> #DIV/0! | P80: =(O80-O78)/O78 -> #DIV/0! | R80: =(Q80-Q78)/Q78 -> #DIV/0! | T80: =(S80-S78)/S78 -> #DIV/0!
A81: DEZEMBRO | B81: AMADORA | D81: =(C81-C79)/C79 -> #DIV/0! | F81: =(E81-E79)/E79 -> #DIV/0! | H81: =(G81-G79)/G79 -> #DIV/0! | J81: =(I81-I79)/I79 -> #DIV/0! | L81: =(K81-K79)/K79 -> #DIV/0! | N81: =(M81-M79)/M79 -> #DIV/0! | P81: =(O81-O79)/O79 -> #DIV/0! | R81: =(Q81-Q79)/Q79 -> #DIV/0! | T81: =(S81-S79)/S79 -> #DIV/0!
B82: QUELUZ | D82: =(C82-C80)/C80 -> #DIV/0! | F82: =(E82-E80)/E80 -> #DIV/0! | H82: =(G82-G80)/G80 -> #DIV/0! | J82: =(I82-I80)/I80 -> #DIV/0! | L82: =(K82-K80)/K80 -> #DIV/0! | N82: =(M82-M80)/M80 -> #DIV/0! | P82: =(O82-O80)/O80 -> #DIV/0! | R82: =(Q82-Q80)/Q80 -> #DIV/0! | T82: =(S82-S80)/S80 -> #DIV/0!
B113: AVARIAS AMADORA | K113: AVARIAS QUELUZ
B114: EQUIPAMENTO | C114: CAUSA | H114: DATA | I114: PEÇAS | J114: CUSTO | K114: EQUIPAMENTO | L114: CAUSA | Q114: DATA | R114: PEÇAS | S114: CUSTO
B115: SONDA SOPA1 | C115: NOVA, ANTIGA NAO TINHA REPARACAO | H115: 45303 | I115: 1 | J115: 472.32 | K115: Testo 270 | L115: Avaria, sem Reparaçao | Q115: 45299 | R115: Novo | S115: 513
B116: router das sondas | C116: cabo do router das sondas | H116: 45307 | I116: 1 | J116: 69.19 | K116: Sonda Bop | L116: Avaria, sem Reparaçao | Q116: 45294 | R116: Novo | S116: 259.5
B117: impressora balcão | C117: problemas tecnicos | H117: 45322 | I117: 1 | J117: 398 | K117: Placa Interface | L117: Avaria, sem Reparaçao | R117: Novo
B118: impressora zebra | C118: problemas tecnicos | I118: 1 | J118: 81 | K118: Cilindor Gril | L118: Avaria, sem Reparaçao | R118: Novo
B119: estufa UHC | C119: nova | H119: 45316 | I119: 1 | J119: 5 131,01€ | K119: Estrado Negativa | L119: Partidos | R119: Novo
B120: evaporizador | C120: novo | H120: 45316 | I120: 1 | J120: 1 355,39€ | K120: Recolha de Gas AC | L120: abate do equipamento | S120: 500
B121: impressora sok30 | C121: talão não sai com tinta | H121: 45341 | I121: 1 | J121: 398 | K121: Cuba Gelo | L121: Tampa Partida | Q121: 45301 | R121: Novo | S121: 24.7
B122: borrachas das arcas | C122: encontram se rasgadas | H122: 45324 | I122: 8 | J122: 94.29 | K122: Panela Sopa | L122: Sem tampa e sem pega | Q122: 44941 | R122: Nova | S122: 28.31
B123: fundo de cx | C123: substituição do fundo de cx | H123: 45327 | I123: 1 | J123: 50 | K123: Micro chip Fritad | L123: Avaria Total | R123: Novo
B124: POS 4 | C124: novo POS 4 | H124: 45341 | I124: 1 | J124: 1 869,90€
D165: DESEMPENHO AMADORA
C166: OBJETIVO | E166: JANEIRO | F166: FEVEREIRO | G166: MARÇO | H166: ABRIL | I166: MAIO | J166: JUNHO | K166: JULHO | L166: AGOSTO | M166: SETEMBRO | N166: OUTUBRO | O166: NOVEMBRO | P166: DEZEMBRO | Q166: ANO
C167: 0.96 | D167: CMP | Q167: =AVERAGE(E167:P167) -> #DIV/0!
C168: 0.97 | D168: PL | Q168: =AVERAGE(E168:P168) -> #DIV/0!
C169: 0.7 | D169: AVALIAÇÕES | Q169: =AVERAGE(E169:P169) -> #DIV/0!
D176: DESEMPENHO QUELUZ
C177: OBJETIVO | E177: JANEIRO | F177: FEVEREIRO | G177: MARÇO | H177: ABRIL | I177: MAIO | J177: JUNHO | K177: JULHO | L177: AGOSTO | M177: SETEMBRO | N177: OUTUBRO | O177: NOVEMBRO | P177: DEZEMBRO | Q177: ANO
C178: 0.96 | D178: CMP | E178: 1 | Q178: =AVERAGE(E178:P178) -> 1
C179: 0.97 | D179: PL | E179: 0.9686 | Q179: =AVERAGE(E179:P179) -> 0.9686
C180: 0.7 | D180: AVALIAÇÕES | Q180: =AVERAGE(E180:P180) -> #DIV/0!
C183: JANEIRO | D183: FEVEREIRO | E183: MARÇO | F183: ABRIL | G183: MAIO | H183: JUNHO | I183: JULHO | J183: AGOSTO | K183: SETEMBRO | L183: OUTUBRO | M183: NOVEMBRO | N183: DEZEMBRO | O183: ANO
B184: 20-CMP | C184: =E167 -> 0 | D184: =F167 -> 0 | E184: =G167 -> 0 | F184: =H167 -> 0 | G184: =I167 -> 0 | H184: =J167 -> 0 | I184: =K167 -> 0 | J184: =L167 -> 0 | ... O184: =Q167 -> #DIV/0!
B185: 20- PL | C185: =E168 -> 0 | D185: =F168 -> 0 | E185: =G168 -> 0 | F185: =H168 -> 0 | G185: =I168 -> 0 | H185: =J168 -> 0 | I185: =K168 -> 0 | J185: =L168 -> 0 | ... O185: =Q168 -> #DIV/0!
B186: 20-AVALIAÇÕES | C186: =E169 -> 0 | D186: =F169 -> 0 | E186: =G169 -> 0 | F186: =H169 -> 0 | G186: =I169 -> 0 | H186: =J169 -> 0 | I186: =K169 -> 0 | J186: =L169 -> 0 | ... O186: =Q169 -> #DIV/0!
B187: 32-CMP | C187: =E178 -> 1 | D187: =F178 -> 0 | E187: =G178 -> 0 | F187: =H178 -> 0 | G187: =I178 -> 0 | H187: =J178 -> 0 | I187: =K178 -> 0 | J187: =L178 -> 0 | ... O187: =Q178 -> 1
B188: 32- PL | C188: =E179 -> 0.9686 | D188: =F179 -> 0 | E188: =G179 -> 0 | F188: =H179 -> 0 | G188: =I179 -> 0 | H188: =J179 -> 0 | I188: =K179 -> 0 | J188: =L179 -> 0 | ... O188: =Q179 -> 0.9686
B189: 32-AVALIAÇÕES | C189: =E180 -> 0 | D189: =F180 -> 0 | E189: =G180 -> 0 | F189: =H180 -> 0 | G189: =I180 -> 0 | H189: =J180 -> 0 | I189: =K180 -> 0 | J189: =L180 -> 0 | ... O189: =Q180 -> #DIV/0!
C197: AVALIAÇÃO DE LIMPEZA AMADORA | K197: AVALIAÇÃO DE LIMPEZA QUELUZ
C198: ÁREA | E198: ERRO | G198: CAUSA | I198: AÇÃO CORRETIVA | K198: ÁREA | M198: ERRO | O198: CAUSA | Q198: AÇÃO CORRETIVA
C243: 20/32 | D243: JANEIRO | E243: FEVEREIRO | F243: MARÇO | G243: ABRIL | H243: MAIO | I243: JUNHO | J243: JULHO | K243: AGOSTO | L243: SETEMBRO | M243: OUTUBRO | N243: NOVEMBRO | O243: DEZEMBRO | P243: ANO
C245: Gastos Gerais | D245: =IF(E37<0,"OK","NOK") -> OK | E245: =IF(F37<0,"OK","NOK") -> NOK | F245: =IF(G37<0,"OK","NOK") -> NOK | G245: =IF(H37<0,"OK","NOK") -> NOK | H245: =IF(I37<0,"OK","NOK") -> NOK | I245: =IF(J37<0,"OK","NOK") -> NOK | J245: =IF(K37<0,"OK","NOK") -> NOK | K245: =IF(L37<0,"OK","NOK") -> NOK | ... O245: =IF(P37<0,"OK","NOK") -> NOK | P245: =+COUNTIF(D245:O245,"OK") -> 1
C246: Desvio | D246: =IF(H168<=$A169,"OK","NOK") -> OK | E246: =IF(H169<=$A169,"OK","NOK") -> OK | F246: =IF(H172<=$A169,"OK","NOK") -> OK | G246: =IF(H175<=$A169,"OK","NOK") -> OK | H246: =IF(H178<=$A169,"OK","NOK") -> OK | I246: =IF(H181<=$A169,"OK","NOK") -> OK | J246: =IF(H184<=$A169,"OK","NOK") -> OK | K246: =IF(H187<=$A169,"OK","NOK") -> OK | L246: =IF(H168<=$A169,"OK","NOK") -> OK | M246: =IF(H190<=$A169,"OK","NOK") -> OK | N246: =IF(H196<=$A169,"OK","NOK") -> OK | O246: =IF(H199<=$A169,"OK","NOK") -> OK | P246: =+COUNTIF(D246:O246,"OK") -> 12
C247: CMP | D247: =IF(E167>$C167,"OK","NOK") -> NOK | E247: =IF(F167>$C167,"OK","NOK") -> NOK | F247: =IF(G167>$C167,"OK","NOK") -> NOK | G247: =IF(H167>$C167,"OK","NOK") -> NOK | H247: =IF(I167>$C167,"OK","NOK") -> NOK | I247: =IF(J167>$C167,"OK","NOK") -> NOK | J247: =IF(K167>$C167,"OK","NOK") -> NOK | K247: =IF(L167>$C167,"OK","NOK") -> NOK | ... O247: =IF(P167>$C167,"OK","NOK") -> NOK | P247: =+COUNTIF(D247:O247,"OK") -> 0
C248: Plano de limpezas | D248: =IF(E168>$C168,"OK","NOK") -> NOK | E248: =IF(F168>$C168,"OK","NOK") -> NOK | F248: =IF(G168>$C168,"OK","NOK") -> NOK | G248: =IF(H168>$C168,"OK","NOK") -> NOK | H248: =IF(I168>$C168,"OK","NOK") -> NOK | I248: =IF(J168>$C168,"OK","NOK") -> NOK | J248: =IF(K168>$C168,"OK","NOK") -> NOK | K248: =IF(L168>$C168,"OK","NOK") -> NOK | ... O248: =IF(P168>$C168,"OK","NOK") -> NOK | P248: =+COUNTIF(D248:O248,"OK") -> 0
C249: Avaliação | D249: =IF(E169>$C169,"OK","NOK") -> NOK | E249: =IF(F169>$C169,"OK","NOK") -> NOK | F249: =IF(G169>$C169,"OK","NOK") -> NOK | G249: =IF(H169>$C169,"OK","NOK") -> NOK | H249: =IF(I169>$C169,"OK","NOK") -> NOK | I249: =IF(J169>$C169,"OK","NOK") -> NOK | J249: =IF(K169>$C169,"OK","NOK") -> NOK | K249: =IF(L169>$C169,"OK","NOK") -> NOK | ... O249: =IF(P169>$C169,"OK","NOK") -> NOK | P249: =+COUNTIF(D249:O249,"OK") -> 0
C250: Refeições | D250: =IF(D61<$A61,"OK","NOK") -> OK | E250: =IF(E61<$A61,"OK","NOK") -> OK | F250: =IF(F61<$A61,"OK","NOK") -> OK | G250: =IF(G61<$A61,"OK","NOK") -> OK | H250: =IF(H61<$A61,"OK","NOK") -> OK | I250: =IF(I61<$A61,"OK","NOK") -> OK | J250: =IF(J61<$A61,"OK","NOK") -> OK | K250: =IF(K61<$A61,"OK","NOK") -> OK | ... O250: =IF(O61<$A61,"OK","NOK") -> OK
C251: Perdas | D251: =IF(D62<$A62,"OK","NOK") -> NOK | E251: =IF(E62<$A62,"OK","NOK") -> OK | F251: =IF(F62<$A62,"OK","NOK") -> NOK | G251: =IF(G62<$A62,"OK","NOK") -> NOK | H251: =IF(H62<$A62,"OK","NOK") -> #DIV/0! | I251: =IF(I62<$A62,"OK","NOK") -> NOK | J251: =IF(J62<$A62,"OK","NOK") -> OK | K251: =IF(K62<$A62,"OK","NOK") -> NOK | ... O251: =IF(O62<$A62,"OK","NOK") -> NOK
D252: =IF(D63=$A63,"OK","NOK") -> NOK | E252: =IF(E63=$A63,"OK","NOK") -> NOK | F252: =IF(F63=$A63,"OK","NOK") -> NOK | G252: =IF(G63=$A63,"OK","NOK") -> NOK | H252: =IF(H63=$A63,"OK","NOK") -> NOK | I252: =IF(I63=$A63,"OK","NOK") -> NOK | J252: =IF(J63=$A63,"OK","NOK") -> NOK | K252: =IF(K63=$A63,"OK","NOK") -> NOK | ... O252: =IF(O63=$A63,"OK","NOK") -> NOK
C253: Total | D253: =COUNTIF(D244:D252,"OK") -> 3 | E253: =COUNTIF(E244:E252,"OK") -> 3 | F253: =COUNTIF(F244:F252,"OK") -> 2 | G253: =COUNTIF(G244:G252,"OK") -> 2 | H253: =COUNTIF(H244:H252,"OK") -> 2 | I253: =COUNTIF(I244:I252,"OK") -> 2 | J253: =COUNTIF(J244:J252,"OK") -> 3 | K253: =COUNTIF(K244:K252,"OK") -> 2 | ... O253: =COUNTIF(O244:O252,"OK") -> 2 | P253: =SUM(P244:P252) -> 13
C254: Tx Concretização | D254: =D253/9 -> 0.33333333 | E254: =E253/9 -> 0.33333333 | F254: =F253/9 -> 0.22222222 | G254: =G253/9 -> 0.22222222 | H254: =H253/9 -> 0.22222222 | I254: =I253/9 -> 0.22222222 | J254: =J253/9 -> 0.33333333 | K254: =K253/9 -> 0.22222222 | ... O254: =O253/9 -> 0.22222222 | P254: =P253/108 -> 0.12037037
C256: Gastos Gerais | D256: =IF(E38<0,"OK","NOK") -> NOK | E256: =IF(F38<0,"OK","NOK") -> NOK | F256: =IF(G38<0,"OK","NOK") -> NOK | G256: =IF(H38<0,"OK","NOK") -> NOK | H256: =IF(I38<0,"OK","NOK") -> NOK | I256: =IF(J38<0,"OK","NOK") -> NOK | J256: =IF(K38<0,"OK","NOK") -> NOK | K256: =IF(L38<0,"OK","NOK") -> NOK | ... O256: =IF(P38<0,"OK","NOK") -> NOK | P256: =+COUNTIF(D256:O256,"OK") -> 0
C257: Desvio | D257: =IF(P168<=$A169,"OK","NOK") -> OK | E257: =IF(P169<=$A169,"OK","NOK") -> OK | F257: =IF(P172<=$A169,"OK","NOK") -> OK | G257: =IF(P175<=$A169,"OK","NOK") -> OK | H257: =IF(P178<=$A169,"OK","NOK") -> OK | I257: =IF(P181<=$A169,"OK","NOK") -> OK | J257: =IF(P184<=$A169,"OK","NOK") -> OK | K257: =IF(P187<=$A169,"OK","NOK") -> OK | L257: =IF(P190<=$A169,"OK","NOK") -> OK | M257: =IF(P193<=$A169,"OK","NOK") -> OK | N257: =IF(P196<=$A169,"OK","NOK") -> OK | O257: =IF(P199<=$A169,"OK","NOK") -> OK | P257: =+COUNTIF(D257:O257,"OK") -> 12
C258: CMP | D258: =IF(E178>$C178,"OK","NOK") -> OK | E258: =IF(F178>$C178,"OK","NOK") -> NOK | F258: =IF(G178>$C178,"OK","NOK") -> NOK | G258: =IF(H178>$C178,"OK","NOK") -> NOK | H258: =IF(I178>$C178,"OK","NOK") -> NOK | I258: =IF(J178>$C178,"OK","NOK") -> NOK | J258: =IF(K178>$C178,"OK","NOK") -> NOK | K258: =IF(L178>$C178,"OK","NOK") -> NOK | ... O258: =IF(P178>$C178,"OK","NOK") -> NOK | P258: =+COUNTIF(D258:O258,"OK") -> 1
C259: Plano de limpezas | D259: =IF(E179>$C179,"OK","NOK") -> NOK | E259: =IF(F179>$C179,"OK","NOK") -> NOK | F259: =IF(G179>$C179,"OK","NOK") -> NOK | G259: =IF(H179>$C179,"OK","NOK") -> NOK | H259: =IF(I179>$C179,"OK","NOK") -> NOK | I259: =IF(J179>$C179,"OK","NOK") -> NOK | J259: =IF(K179>$C179,"OK","NOK") -> NOK | K259: =IF(L179>$C179,"OK","NOK") -> NOK | ... O259: =IF(P179>$C179,"OK","NOK") -> NOK | P259: =+COUNTIF(D259:O259,"OK") -> 0
C260: Avaliação | D260: =IF(E180>$C180,"OK","NOK") -> NOK | E260: =IF(F180>$C180,"OK","NOK") -> NOK | F260: =IF(G180>$C180,"OK","NOK") -> NOK | G260: =IF(H180>$C180,"OK","NOK") -> NOK | H260: =IF(I180>$C180,"OK","NOK") -> NOK | I260: =IF(J180>$C180,"OK","NOK") -> NOK | J260: =IF(K180>$C180,"OK","NOK") -> NOK | K260: =IF(L180>$C180,"OK","NOK") -> NOK | ... O260: =IF(P180>$C180,"OK","NOK") -> NOK | P260: =+COUNTIF(D260:O260,"OK") -> 0
C261: Refeições | D261: =IF(D67<$A67,"OK","NOK") -> #DIV/0! | E261: =IF(E67<$A67,"OK","NOK") -> OK | F261: =IF(F67<$A67,"OK","NOK") -> #DIV/0! | G261: =IF(G67<$A67,"OK","NOK") -> OK | H261: =IF(H67<$A67,"OK","NOK") -> #DIV/0! | I261: =IF(I67<$A67,"OK","NOK") -> OK | J261: =IF(J67<$A67,"OK","NOK") -> #DIV/0! | K261: =IF(K67<$A67,"OK","NOK") -> OK | ... O261: =IF(O67<$A67,"OK","NOK") -> OK
C262: Perdas | D262: =IF(D68<$A68,"OK","NOK") -> #DIV/0! | E262: =IF(E68<$A68,"OK","NOK") -> NOK | F262: =IF(F68<$A68,"OK","NOK") -> #DIV/0! | G262: =IF(G68<$A68,"OK","NOK") -> NOK | H262: =IF(H68<$A68,"OK","NOK") -> #DIV/0! | I262: =IF(I68<$A68,"OK","NOK") -> NOK | J262: =IF(J68<$A68,"OK","NOK") -> #DIV/0! | K262: =IF(K68<$A68,"OK","NOK") -> NOK | ... O262: =IF(O68<$A68,"OK","NOK") -> NOK
C264: Total | D264: =COUNTIF(D255:D263,"OK") -> 2 | E264: =COUNTIF(E255:E263,"OK") -> 2 | F264: =COUNTIF(F255:F263,"OK") -> 1 | G264: =COUNTIF(G255:G263,"OK") -> 2 | H264: =COUNTIF(H255:H263,"OK") -> 1 | I264: =COUNTIF(I255:I263,"OK") -> 2 | J264: =COUNTIF(J255:J263,"OK") -> 1 | K264: =COUNTIF(K255:K263,"OK") -> 2 | ... P264: =COUNTIF(P255:P263,"OK") -> 0
C265: Tx Concretização | D265: =D264/9 -> 0.22222222 | E265: =E264/9 -> 0.22222222 | F265: =F264/9 -> 0.11111111 | G265: =G264/9 -> 0.22222222 | H265: =H264/9 -> 0.11111111 | I265: =I264/9 -> 0.22222222 | J265: =J264/9 -> 0.11111111 | K265: =K264/9 -> 0.22222222 | ... O265: =O264/9 -> 0.22222222 | P265: =P264/108 -> 0

Sheet BSV
B1: Desempenho de Gerentes
B2: Dados | F2: Secções de avaliação
B3: Data | D3: Loja | E3: Gerente | F3: =[1]Original!$A$2 -> Limpeza e Higienização | G3: =[1]Original!$A$3 -> Prevenção e Contaminação | H3: =[1]Original!$A$4 -> Armazenamento | I3: =[1]Original!$A$5 -> Confeção | J3: =[1]Original!$A$6 -> Geral | K3: Máquinas de Gelado e BIC | L3: Lista de Controlo Diário | M3: Controlos de Gestão | N3: Nota final
A4: Janeiro | B4: 22-jan. | C4: 0 | D4: 20 | E4: Uilson | F4: 1 | G4: 0.8 | H4: 0.7368 | I4: 1 | J4: 1 | K4: 0.895 | N4: 0.895 | O4: Bruna | P4: =AVERAGEIFS(N$4:N$28,E$4:E$28,"Bruna") -> #DIV/0!
B5: 31-jan. | C5: 0 | D5: 32 | E5: Marília | F5: 1 | G5: 0.7 | H5: 0.7368 | I5: 1 | J5: 1 | K5: 0.867 | N5: 0.867 | O5: Claudia | P5: =AVERAGEIFS(N$4:N$28,E$4:E$28,"Claudia") -> #DIV/0!
A6: Fevereiro | B6: 2-fev. | C6: 0 | D6: 20 | E6: Uilson | F6: 0.7619 | G6: 0.6 | H6: 0.7368 | I6: 1 | J6: 0.8333 | K6: 0.743 | N6: 0.743 | O6: Hugo | P6: =AVERAGEIFS(N$4:N$28,E$4:E$28,"Hugo") -> #DIV/0!
B7: 16-fev. | C7: 0 | D7: 20 | E7: Isabel | F7: 1 | G7: 0.74 | H7: 0.5 | I7: 1 | J7: 1 | K7: 0.821 | N7: 0.821 | O7: Isaac | P7: =AVERAGEIFS(N$4:N$28,E$4:E$28,"Isaac") -> #DIV/0!
B8: 22-fev. | C8: 1 | D8: 32 | E8: Vitor | F8: 0.86 | G8: 1 | H8: 0.74 | I8: 1 | J8: 1 | N8: 0.924
A9: Março | B9: 15-mar. | C9: 0 | D9: 20 | E9: Isabel | F9: 0.85714286 | G9: 0.7 | H9: 0.57894737 | I9: 1 | J9: 1 | N9: 0.75 | O9: Isabel | P9: =AVERAGEIFS(N$4:N$28,E$4:E$28,"Isabel") -> 0.7855
B10: 20-mar. | C10: 0 | D10: 32 | E10: Vitor | F10: 0.76190476 | G10: 0.7 | H10: 0.84210526 | I10: 1 | J10: 1 | N10: 0.75 | O10: Janice | P10: =AVERAGEIFS(N$4:N$28,E$4:E$28,"Janice") -> #DIV/0!
A11: Abril | C11: =IF(E11=B$30,1,0) -> 1 | O11: Luis | P11: =AVERAGEIFS(N$4:N$28,E$4:E$28,"Luis") -> #DIV/0!
C12: =IF(E12=B$30,1,0) -> 1 | O12: Marília | P12: =AVERAGEIFS(N$4:N$28,E$4:E$28,"Marília") -> 0.867
A13: Maio | C13: =IF(E13=B$30,1,0) -> 1 | O13: Uilson | P13: =AVERAGEIFS(N$4:N$28,E$4:E$28,"Uilson") -> 0.819
C14: =IF(E14=B$30,1,0) -> 1 | O14: Vitor | P14: =AVERAGEIFS(N$4:N$28,E$4:E$28,"Vitor") -> 0.837
A15: Junho | C15: =IF(E15=B$30,1,0) -> 1 | O15: William | P15: =AVERAGEIFS(N$4:N$28,E$4:E$28,"William") -> #DIV/0!
C16: =IF(E16=B$30,1,0) -> 1 | O16: Média | P16: =AVERAGE(P4:P15) -> #DIV/0!
A17: Julho | C17: =IF(E17=B$30,1,0) -> 1
C18: =IF(E18=B$30,1,0) -> 1
A19: Agosto | C19: =IF(E19=B$30,1,0) -> 1
C20: =IF(E20=B$30,1,0) -> 1
A21: Setembro | C21: =IF(E21=B$30,1,0) -> 1
C22: =IF(E22=B$30,1,0) -> 1
A23: Outubro | C23: =IF(E23=B$30,1,0) -> 1
C24: =IF(E24=B$30,1,0) -> 1
A25: Novembro | C25: =IF(E25=B$30,1,0) -> 1
C26: =IF(E26=B$30,1,0) -> 1
A27: Dezembro | C27: =IF(E27=B$30,1,0) -> 1
C28: =IF(E28=B$30,1,0) -> 1
A29: Média por área | F29: =AVERAGE(F4:F28) -> 0.89156395 | G29: =AVERAGE(G4:G28) -> 0.74857143 | H29: =AVERAGE(H4:H28) -> 0.6959218 | I29: =AVERAGE(I4:I28) -> 1 | J29: =AVERAGE(J4:J28) -> 0.97618571 | K29: =AVERAGE(K4:K28) -> 0.8315 | L29: =AVERAGE(L4:L28) -> #DIV/0! | M29: =AVERAGE(M4:M28) -> #DIV/0! | N29: =AVERAGE(N4:N28) -> 0.82142857
A30: Gerente | F30: =F34/F33 -> 0.045263158 | G30: =G34/G33 -> 0.052631579 | H30: =H34/H33 -> 0.038947368 | I30: =I34/I33 -> 0.052631579 | J30: =J34/J33 -> 0.052631579 | K30: =K34/K33 -> 0 | L30: =L34/L33 -> 0 | M30: =M34/M33 -> 0 | N30: =N34/N33 -> 0.048631579
F31: =COUNTIF($D4:$D28,$B35) -> 0 | G31: =COUNTIF($D4:$D28,$B35) -> 0 | H31: =COUNTIF($D4:$D28,$B35) -> 0 | I31: =COUNTIF($D4:$D28,$B35) -> 0 | J31: =COUNTIF($D4:$D28,$B35) -> 0 | K31: =COUNTIF($D4:$D28,$B35) -> 0 | L31: =COUNTIF($D4:$D28,$B35) -> 0 | M31: =COUNTIF($D4:$D28,$B35) -> 0 | N31: =COUNTIF($D4:$D28,$B35) -> 0
F32: =SUMIF(D4:D28,B35,F4:F28) -> 0 | G32: =SUMIF($D4:$D28,$B35,G4:G28) -> 0 | H32: =SUMIF($D4:$D28,$B35,H4:H28) -> 0 | I32: =SUMIF($D4:$D28,$B35,I4:I28) -> 0 | J32: =SUMIF($D4:$D28,$B35,J4:J28) -> 0 | K32: =SUMIF($D4:$D28,$B35,K4:K28) -> 0 | L32: =SUMIF($D4:$D28,$B35,L4:L28) -> 0 | M32: =SUMIF($D4:$D28,$B35,M4:M28) -> 0 | N32: =SUMIF($D4:$D28,$B35,N4:N28) -> 0
F33: =COUNTIF($C4:$C28,1) -> 19 | G33: =COUNTIF($C4:$C28,1) -> 19 | H33: =COUNTIF($C4:$C28,1) -> 19 | I33: =COUNTIF($C4:$C28,1) -> 19 | J33: =COUNTIF($C4:$C28,1) -> 19 | K33: =COUNTIF($C4:$C28,1) -> 19 | L33: =COUNTIF($C4:$C28,1) -> 19 | M33: =COUNTIF($C4:$C28,1) -> 19 | N33: =COUNTIF($C4:$C28,1) -> 19
F34: =SUMIF($C4:$C28,1,F4:F28) -> 0.86 | G34: =SUMIF($C4:$C28,1,G4:G28) -> 1 | H34: =SUMIF($C4:$C28,1,H4:H28) -> 0.74 | I34: =SUMIF($C4:$C28,1,I4:I28) -> 1 | J34: =SUMIF($C4:$C28,1,J4:J28) -> 1 | K34: =SUMIF($C4:$C28,1,K4:K28) -> 0 | L34: =SUMIF($C4:$C28,1,L4:L28) -> 0 | M34: =SUMIF($C4:$C28,1,M4:M28) -> 0 | N34: =SUMIF($C4:$C28,1,N4:N28) -> 0.924
A35: Loja | F35: =F32/F31 -> #DIV/0! | G35: =G32/G31 -> #DIV/0! | H35: =H32/H31 -> #DIV/0! | I35: =I32/I31 -> #DIV/0! | J35: =J32/J31 -> #DIV/0! | K35: =K32/K31 -> #DIV/0! | L35: =L32/L31 -> #DIV/0! | M35: =M32/M31 -> #DIV/0! | N35: =N32/N31 -> #DIV/0!
B36: Nota por dep. | F36: =AVERAGE(F4:H28) -> 0.77868573 | I36: =AVERAGE(I4:J28) -> 0.98809286 | L36: =AVERAGE(L4:N28) -> 0.82142857

Sheet VSC
B1: Desempenho de Gerentes
B2: Dados | F2: Secções de avaliação
B3: Data | C3: =IF(E3=B$29,1,0) -> 0 | D3: Loja | E3: Gerente | F3: =[1]Original!$A$2 -> Limpeza e Higienização | G3: =[1]Original!$A$3 -> Prevenção e Contaminação | H3: =[1]Original!$A$4 -> Armazenamento | I3: =[1]Original!$A$5 -> Confeção | J3: =[1]Original!$A$6 -> Geral | K3: Máquinas de Gelado e BIC | L3: Lista de Controlo Diário | M3: Controlos de Gestão | N3: Nota final
A4: Janeiro | B4: 45299 | C4: 1 | D4: 20 | E4: Bruna | F4: 1 | G4: 0.61 | H4: 0.5 | I4: 1 | J4: 1 | N4: 0.76 | O4: Bruna | P4: =AVERAGEIFS(N$4:N$27,E$4:E$27,"Bruna") -> 0.76
B5: 45313 | C5: 0 | D5: 32 | E5: Vitor | F5: 1 | G5: 0.61 | H5: 0.5 | I5: 1 | J5: 0.46 | N5: 0.68 | O5: Claudia | P5: =AVERAGEIFS(N$4:N$27,E$4:E$27,"Claudia") -> #DIV/0!
A6: Fevereiro | B6: 45324 | C6: 0 | D6: 32 | E6: Marilia | F6: 1 | G6: 0.5 | H6: 0.52 | I6: 0.81 | J6: 1 | N6: 0.68 | O6: Hugo | P6: =AVERAGEIFS(N$4:N$27,E$4:E$27,"Hugo") -> #DIV/0!
B7: 45338 | C7: 0 | D7: 20 | E7: Isabel | F7: 1 | G7: 0.74 | H7: 0.5 | I7: 1 | J7: 1 | K7: 0.5 | L7: 1 | M7: 1 | N7: 0.821 | O7: Isaac | P7: =AVERAGEIFS(N$4:N$27,E$4:E$27,"Isaac") -> #DIV/0!
A8: Março | C8: =IF(E8=B$29,1,0) -> 0 | O8: Isabel | P8: =AVERAGEIFS(N$4:N$27,E$4:E$27,"Isabel") -> 0.821
C9: =IF(E9=B$29,1,0) -> 0 | O9: Janice | P9: =AVERAGEIFS(N$4:N$27,E$4:E$27,"Janice") -> #DIV/0!
A10: Abril | C10: =IF(E10=B$29,1,0) -> 0 | O10: Luis | P10: =AVERAGEIFS(N$4:N$27,E$4:E$27,"Luis") -> #DIV/0!
C11: =IF(E11=B$29,1,0) -> 0 | O11: Marília | P11: =AVERAGEIFS(N$4:N$27,E$4:E$27,"Marília") -> #DIV/0!
A12: Maio | C12: =IF(E12=B$29,1,0) -> 0 | O12: Uilson | P12: =AVERAGEIFS(N$4:N$27,E$4:E$27,"Uilson") -> #DIV/0!
C13: =IF(E13=B$29,1,0) -> 0 | O13: Vitor | P13: =AVERAGEIFS(N$4:N$27,E$4:E$27,"Vitor") -> 0.68
A14: Junho | C14: =IF(E14=B$29,1,0) -> 0 | O14: William | P14: =AVERAGEIFS(N$4:N$27,E$4:E$27,"William") -> #DIV/0!
C15: =IF(E15=B$29,1,0) -> 0 | O15: Média | P15: =AVERAGE(P4:P14) -> #DIV/0!
A16: Julho | C16: =IF(E16=B$29,1,0) -> 0
C17: =IF(E17=B$29,1,0) -> 0
A18: Agosto | C18: =IF(E18=B$29,1,0) -> 0
C19: =IF(E19=B$29,1,0) -> 0
A20: Setembro | C20: =IF(E20=B$29,1,0) -> 0
C21: =IF(E21=B$29,1,0) -> 0
A22: Outubro | C22: =IF(E22=B$29,1,0) -> 0
C23: =IF(E23=B$29,1,0) -> 0
A24: Novembro | C24: =IF(E24=B$29,1,0) -> 0
C25: =IF(E25=B$29,1,0) -> 0
A26: Dezembro | C26: =IF(E26=B$29,1,0) -> 0
C27: =IF(E27=B$29,1,0) -> 0
A28: Média por área | F28: =AVERAGE(F4:F27) -> 1 | G28: =AVERAGE(G4:G27) -> 0.615 | H28: =AVERAGE(H4:H27) -> 0.505 | I28: =AVERAGE(I4:I27) -> 0.9525 | J28: =AVERAGE(J4:J27) -> 0.865 | K28: =AVERAGE(K4:K27) -> 0.5 | L28: =AVERAGE(L4:L27) -> 1 | M28: =AVERAGE(M4:M27) -> 1 | N28: =AVERAGE(N4:N27) -> 0.73525
A29: Gerente | B29: Vitor | F29: =F33/F32 -> 1 | G29: =G33/G32 -> 0.61 | H29: =H33/H32 -> 0.5 | I29: =I33/I32 -> 1 | J29: =J33/J32 -> 1 | K29: =K33/K32 -> 0 | L29: =L33/L32 -> 0 | M29: =M33/M32 -> 0 | N29: =N33/N32 -> 0.76
F30: =COUNTIF($D4:$D27,$B34) -> 0 | G30: =COUNTIF($D4:$D27,$B34) -> 0 | H30: =COUNTIF($D4:$D27,$B34) -> 0 | I30: =COUNTIF($D4:$D27,$B34) -> 0 | J30: =COUNTIF($D4:$D27,$B34) -> 0 | K30: =COUNTIF($D4:$D27,$B34) -> 0 | L30: =COUNTIF($D4:$D27,$B34) -> 0 | M30: =COUNTIF($D4:$D27,$B34) -> 0 | N30: =COUNTIF($D4:$D27,$B34) -> 0
F31: =SUMIF(D4:D27,B34,F4:F27) -> 0 | G31: =SUMIF($D4:$D27,$B34,G4:G27) -> 0 | H31: =SUMIF($D4:$D27,$B34,H4:H27) -> 0 | I31: =SUMIF($D4:$D27,$B34,I4:I27) -> 0 | J31: =SUMIF($D4:$D27,$B34,J4:J27) -> 0 | K31: =SUMIF($D4:$D27,$B34,K4:K27) -> 0 | L31: =SUMIF($D4:$D27,$B34,L4:L27) -> 0 | M31: =SUMIF($D4:$D27,$B34,M4:M27) -> 0 | N31: =SUMIF($D4:$D27,$B34,N4:N27) -> 0
F32: =COUNTIF($C4:$C27,1) -> 1 | G32: =COUNTIF($C4:$C27,1) -> 1 | H32: =COUNTIF($C4:$C27,1) -> 1 | I32: =COUNTIF($C4:$C27,1) -> 1 | J32: =COUNTIF($C4:$C27,1) -> 1 | K32: =COUNTIF($C4:$C27,1) -> 1 | L32: =COUNTIF($C4:$C27,1) -> 1 | M32: =COUNTIF($C4:$C27,1) -> 1 | N32: =COUNTIF($C4:$C27,1) -> 1
F33: =SUMIF($C4:$C27,1,F4:F27) -> 1 | G33: =SUMIF($C4:$C27,1,G4:G27) -> 0.61 | H33: =SUMIF($C4:$C27,1,H4:H27) -> 0.5 | I33: =SUMIF($C4:$C27,1,I4:I27) -> 1 | J33: =SUMIF($C4:$C27,1,J4:J27) -> 1 | K33: =SUMIF($C4:$C27,1,K4:K27) -> 0 | L33: =SUMIF($C4:$C27,1,L4:L27) -> 0 | M33: =SUMIF($C4:$C27,1,M4:M27) -> 0 | N33: =SUMIF($C4:$C27,1,N4:N27) -> 0.76
A34: Loja | F34: =F31/F30 -> #DIV/0! | G34: =G31/G30 -> #DIV/0! | H34: =H31/H30 -> #DIV/0! | I34: =I31/I30 -> #DIV/0! | J34: =J31/J30 -> #DIV/0! | K34: =K31/K30 -> #DIV/0! | L34: =L31/L30 -> #DIV/0! | M34: =M31/M30 -> #DIV/0! | N34: =N31/N30 -> #DIV/0!
B35: Nota por dep. | F35: =AVERAGE(F4:H27) -> 0.70666667 | I35: =AVERAGE(I4:J27) -> 0.90875 | L35: =AVERAGE(L4:N27) -> 0.8235

Sheet Gestão de Turno
A2: Bruna | J2: Isaac | S2: Isabel
B4: Real | C4: Planificado | D4: Diferença | F4: Real | G4: Planificado | H4: Diferença | K4: Real | L4: Planificado | M4: Diferença | O4: Real | P4: Planificado | Q4: Diferença | T4: Real | U4: Planificado | V4: Diferença | X4: Real | Y4: Planificado | Z4: Diferença
A5: Vendas (16h) | E5: Vendas (16h) | J5: Vendas (16h) | N5: Vendas (16h) | S5: Vendas (16h) | W5: Vendas (16h)
A6: GC's | E6: GC's | J6: GC's | N6: GC's | S6: GC's | W6: GC's
A7: BM | E7: BM | J7: BM | N7: BM | S7: BM | W7: BM
A8: Horas | E8: Horas | J8: Horas | N8: Horas | S8: Horas | W8: Horas
A9: MO | E9: MO | J9: MO | N9: MO | S9: MO | W9: MO
A10: Perdas | E10: Perdas | J10: Perdas | N10: Perdas | S10: Perdas | W10: Perdas
A11: Refeições | E11: Refeições | J11: Refeições | N11: Refeições | S11: Refeições | W11: Refeições
A12: TET | D12: Objetivo 150" | E12: TET | H12: Objetivo 150" | J12: TET | M12: Objetivo 150" | N12: TET | Q12: Objetivo 150" | S12: TET | V12: Objetivo 150" | W12: TET | Z12: Objetivo 150"
A13: Tempo serviço | D13: Objetivo 90" | E13: Tempo serviço | H13: Objetivo 90" | J13: Tempo serviço | M13: Objetivo 90" | N13: Tempo serviço | Q13: Objetivo 90" | S13: Tempo serviço | V13: Objetivo 90" | W13: Tempo serviço | Z13: Objetivo 90"
A14: CMP % | E14: CMP % | J14: CMP % | N14: CMP % | O14: =(((SUMIF([2]Jan!O192,">0")+SUMIF([2]Fev!O192,">0")+SUMIF([2]Mar!O192,">0")+SUMIF([2]Abr!O192,">0")+SUMIF([2]Mai!O192,">0")+SUMIF([2]Jun!O192,">0")+SUMIF([2]Jul!O192,">0")+SUMIF([2]Ago!O192,">0")+SUMIF([2]Set!O192,">0")+SUMIF([2]Out!O192,">0")+SUMIF([2]Nov!O192,">0")+SUMIF([2]Dez!O192,">0"))/((COUNTIF([2]Jan!O192,">0")+COUNTIF([2]Fev!O192,">0")+COUNTIF([2]Mar!O192,">0")+COUNTIF([2]Abr!O192,">0")+COUNTIF([2]Mai!O192,">0")+COUNTIF([2]Jun!O192,">0")+COUNTIF([2]Jul!O192,">0")+COUNTIF([2]Ago!O192,">0")+COUNTIF([2]Set!O192,">0")+COUNTIF([2]Out!O192,">0")+COUNTIF([2]Nov!O192,">0")+COUNTIF([2]Dez!O192,">0"))))*100)/N18 -> #VALUE! | S14: CMP % | W14: CMP %
A15: P. Limpezas % | E15: P. Limpezas % | J15: P. Limpezas % | N15: P. Limpezas % | O15: =(((SUMIF([2]Jan!O193,">0")+SUMIF([2]Fev!O193,">0")+SUMIF([2]Mar!O193,">0")+SUMIF([2]Abr!O193,">0")+SUMIF([2]Mai!O193,">0")+SUMIF([2]Jun!O193,">0")+SUMIF([2]Jul!O193,">0")+SUMIF([2]Ago!O193,">0")+SUMIF([2]Set!O193,">0")+SUMIF([2]Out!O193,">0")+SUMIF([2]Nov!O193,">0")+SUMIF([2]Dez!O193,">0"))/(COUNTIF([2]Jan!O193,">0")+COUNTIF([2]Fev!O193,">0")+COUNTIF([2]Mar!O193,">0")+COUNTIF([2]Abr!O193,">0")+COUNTIF([2]Mai!O193,">0")+COUNTIF([2]Jun!O193,">0")+COUNTIF([2]Jul!O193,">0")+COUNTIF([2]Ago!O193,">0")+COUNTIF([2]Set!O193,">0")+COUNTIF([2]Out!O193,">0")+COUNTIF([2]Nov!O193,">0")+COUNTIF([2]Dez!O193,">0"))*100)/N18) -> #VALUE! | S15: P. Limpezas % | W15: P. Limpezas %
A16: Reembolsos | B16: Quantidade | C16: Valor | D16: Média | E16: Reembolsos | F16: Quantidade | G16: Valor | H16: Média | J16: Reembolsos | K16: Quantidade | L16: Valor | M16: Média | N16: Reembolsos | O16: Quantidade | P16: Valor | Q16: Média | S16: Reembolsos | T16: Quantidade | U16: Valor | V16: Média | W16: Reembolsos | X16: Quantidade | Y16: Valor | Z16: Média
Q17: =P17/O17 -> #DIV/0!
A19: Janice | B19: , | J19: Luis | S19: Uilson
B21: Real | C21: Planificado | D21: Diferença | F21: Real | G21: Planificado | H21: Diferença | K21: Real | L21: Planificado | M21: Diferença | O21: Real | P21: Planificado | Q21: Diferença | T21: Real | U21: Planificado | V21: Diferença | X21: Real | Y21: Planificado | Z21: Diferença
A22: Vendas (16h) | E22: Vendas (16h) | J22: Vendas (16h) | N22: Vendas (16h) | S22: Vendas (16h) | W22: Vendas (16h)
A23: GC's | E23: GC's | J23: GC's | N23: GC's | S23: GC's | W23: GC's
A24: BM | E24: BM | J24: BM | N24: BM | S24: BM | W24: BM
A25: Horas | E25: Horas | J25: Horas | N25: Horas | S25: Horas | W25: Horas
A26: MO | E26: MO | J26: MO | N26: MO | S26: MO | W26: MO
A27: Perdas | E27: Perdas | J27: Perdas | N27: Perdas | S27: Perdas | W27: Perdas
A28: Refeições | E28: Refeições | J28: Refeições | N28: Refeições | S28: Refeições | W28: Refeições
A29: TET | D29: Objetivo 150" | E29: TET | H29: Objetivo 150" | J29: TET | M29: Objetivo 150" | N29: TET | Q29: Objetivo 150" | S29: TET | V29: Objetivo 150" | W29: TET | Z29: Objetivo 150"
A30: Tempo serviço | D30: Objetivo 90" | E30: Tempo serviço | H30: Objetivo 90" | J30: Tempo serviço | M30: Objetivo 90" | N30: Tempo serviço | Q30: Objetivo 90" | S30: Tempo serviço | V30: Objetivo 90" | W30: Tempo serviço | Z30: Objetivo 90"
A31: CMP % | E31: CMP % | F31: =(((SUMIF([2]Jan!F209,">0")+SUMIF([2]Fev!F209,">0")+SUMIF([2]Mar!F209,">0")+SUMIF([2]Abr!F209,">0")+SUMIF([2]Mai!F209,">0")+SUMIF([2]Jun!F209,">0")+SUMIF([2]Jul!F209,">0")+SUMIF([2]Ago!F209,">0")+SUMIF([2]Set!F209,">0")+SUMIF([2]Out!F209,">0")+SUMIF([2]Nov!F209,">0")+SUMIF([2]Dez!F209,">0"))/((COUNTIF([2]Jan!F209,">0")+COUNTIF([2]Fev!F209,">0")+COUNTIF([2]Mar!F209,">0")+COUNTIF([2]Abr!F209,">0")+COUNTIF([2]Mai!F209,">0")+COUNTIF([2]Jun!F209,">0")+COUNTIF([2]Jul!F209,">0")+COUNTIF([2]Ago!F209,">0")+COUNTIF([2]Set!F209,">0")+COUNTIF([2]Out!F209,">0")+COUNTIF([2]Nov!F209,">0")+COUNTIF([2]Dez!F209,">0"))))*100)/E35 -> #VALUE! | J31: CMP % | N31: CMP % | S31: CMP % | W31: CMP %
A32: P. Limpezas % | E32: P. Limpezas % | F32: =(((SUMIF([2]Jan!F210,">0")+SUMIF([2]Fev!F210,">0")+SUMIF([2]Mar!F210,">0")+SUMIF([2]Abr!F210,">0")+SUMIF([2]Mai!F210,">0")+SUMIF([2]Jun!F210,">0")+SUMIF([2]Jul!F210,">0")+SUMIF([2]Ago!F210,">0")+SUMIF([2]Set!F210,">0")+SUMIF([2]Out!F210,">0")+SUMIF([2]Nov!F210,">0")+SUMIF([2]Dez!F210,">0"))/(COUNTIF([2]Jan!F210,">0")+COUNTIF([2]Fev!F210,">0")+COUNTIF([2]Mar!F210,">0")+COUNTIF([2]Abr!F210,">0")+COUNTIF([2]Mai!F210,">0")+COUNTIF([2]Jun!F210,">0")+COUNTIF([2]Jul!F210,">0")+COUNTIF([2]Ago!F210,">0")+COUNTIF([2]Set!F210,">0")+COUNTIF([2]Out!F210,">0")+COUNTIF([2]Nov!F210,">0")+COUNTIF([2]Dez!F210,">0"))*100)/E35) -> #VALUE! | J32: P. Limpezas % | N32: P. Limpezas % | S32: P. Limpezas % | W32: P. Limpezas %
A33: Reembolsos | B33: Quantidade | C33: Valor | D33: Média | E33: Reembolsos | F33: Quantidade | G33: Valor | H33: Média | J33: Reembolsos | K33: Quantidade | L33: Valor | M33: Média | N33: Reembolsos | O33: Quantidade | P33: Valor | Q33: Média | S33: Reembolsos | T33: Quantidade | U33: Valor | V33: Média | W33: Reembolsos | X33: Quantidade | Y33: Valor | Z33: Média
A36: Claudia | J36: Hugo | S36: Marília
B38: Real | C38: Planificado | D38: Diferença | F38: Real | G38: Planificado | H38: Diferença | K38: Real | L38: Planificado | M38: Diferença | O38: Real | P38: Planificado | Q38: Diferença
A39: Vendas (16h) | E39: Vendas (16h) | J39: Vendas (16h) | N39: Vendas (16h) | Q39: =O39-P39 -> 0 | S39: Vendas (16h) | W39: Vendas (16h)
A40: GC's | E40: GC's | J40: GC's | N40: GC's | Q40: =O40-P40 -> 0 | S40: GC's | W40: GC's
A41: BM | E41: BM | J41: BM | N41: BM | Q41: =O41-P41 -> 0 | S41: BM | W41: BM
A42: Horas | E42: Horas | J42: Horas | N42: Horas | Q42: =O42-P42 -> 0 | S42: Horas | W42: Horas
A43: MO | E43: MO | J43: MO | N43: MO | Q43: =O43-P43 -> 0 | S43: MO | W43: MO
A44: Perdas | E44: Perdas | J44: Perdas | N44: Perdas | Q44: =O44-P44 -> 0 | S44: Perdas | W44: Perdas
A45: Refeições | E45: Refeições | J45: Refeições | N45: Refeições | Q45: =O45-P45 -> 0 | S45: Refeições | W45: Refeições
A46: TET | D46: Objetivo 150" | E46: TET | H46: Objetivo 150" | J46: TET | M46: Objetivo 150" | N46: TET | Q46: Objetivo 150" | S46: TET | V46: Objetivo 150" | W46: TET | Z46: Objetivo 150"
A47: Tempo serviço | D47: Objetivo 90" | E47: Tempo serviço | H47: Objetivo 90" | J47: Tempo serviço | M47: Objetivo 90" | N47: Tempo serviço | Q47: Objetivo 90" | S47: Tempo serviço | V47: Objetivo 90" | W47: Tempo serviço | Z47: Objetivo 90"
A48: CMP % | E48: CMP % | J48: CMP % | N48: CMP % | S48: CMP % | W48: CMP %
A49: P. Limpezas % | E49: P. Limpezas % | J49: P. Limpezas % | N49: P. Limpezas % | S49: P. Limpezas % | W49: P. Limpezas %
A50: Reembolsos | B50: Quantidade | C50: Valor | D50: Média | E50: Reembolsos | F50: Quantidade | G50: Valor | H50: Média | J50: Reembolsos | K50: Quantidade | L50: Valor | M50: Média | N50: Reembolsos | O50: Quantidade | P50: Valor | Q50: Média | S50: Reembolsos | T50: Quantidade | U50: Valor | V50: Média | W50: Reembolsos | X50: Quantidade | Y50: Valor | Z50: Média
A53: Vitor | J53: William
A56: Vendas (16h) | E56: Vendas (16h) | J56: Vendas (16h) | N56: Vendas (16h)
A57: GC's | E57: GC's | J57: GC's | N57: GC's
A58: BM | E58: BM | J58: BM | N58: BM
A59: Horas | E59: Horas | J59: Horas | N59: Horas
A60: MO | E60: MO | J60: MO | N60: MO
A61: Perdas | E61: Perdas | J61: Perdas | N61: Perdas
A62: Refeições | E62: Refeições | J62: Refeições | N62: Refeições
A63: TET | D63: Objetivo 150" | E63: TET | H63: Objetivo 150" | J63: TET | M63: Objetivo 150" | N63: TET | Q63: Objetivo 150"
A64: Tempo serviço | D64: Objetivo 90" | E64: Tempo serviço | H64: Objetivo 90" | J64: Tempo serviço | M64: Objetivo 90" | N64: Tempo serviço | Q64: Objetivo 90"
A65: CMP % | E65: CMP % | F65: =(((SUMIF([2]Jan!F243,">0")+SUMIF([2]Fev!F243,">0")+SUMIF([2]Mar!F243,">0")+SUMIF([2]Abr!F243,">0")+SUMIF([2]Mai!F243,">0")+SUMIF([2]Jun!F243,">0")+SUMIF([2]Jul!F243,">0")+SUMIF([2]Ago!F243,">0")+SUMIF([2]Set!F243,">0")+SUMIF([2]Out!F243,">0")+SUMIF([2]Nov!F243,">0")+SUMIF([2]Dez!F243,">0"))/((COUNTIF([2]Jan!F243,">0")+COUNTIF([2]Fev!F243,">0")+COUNTIF([2]Mar!F243,">0")+COUNTIF([2]Abr!F243,">0")+COUNTIF([2]Mai!F243,">0")+COUNTIF([2]Jun!F243,">0")+COUNTIF([2]Jul!F243,">0")+COUNTIF([2]Ago!F243,">0")+COUNTIF([2]Set!F243,">0")+COUNTIF([2]Out!F243,">0")+COUNTIF([2]Nov!F243,">0")+COUNTIF([2]Dez!F243,">0"))))*100)/E69 -> #VALUE! | J65: CMP % | N65: CMP %
A66: P. Limpezas % | E66: P. Limpezas % | F66: =(((SUMIF([2]Jan!F244,">0")+SUMIF([2]Fev!F244,">0")+SUMIF([2]Mar!F244,">0")+SUMIF([2]Abr!F244,">0")+SUMIF([2]Mai!F244,">0")+SUMIF([2]Jun!F244,">0")+SUMIF([2]Jul!F244,">0")+SUMIF([2]Ago!F244,">0")+SUMIF([2]Set!F244,">0")+SUMIF([2]Out!F244,">0")+SUMIF([2]Nov!F244,">0")+SUMIF([2]Dez!F244,">0"))/(COUNTIF([2]Jan!F244,">0")+COUNTIF([2]Fev!F244,">0")+COUNTIF([2]Mar!F244,">0")+COUNTIF([2]Abr!F244,">0")+COUNTIF([2]Mai!F244,">0")+COUNTIF([2]Jun!F244,">0")+COUNTIF([2]Jul!F244,">0")+COUNTIF([2]Ago!F244,">0")+COUNTIF([2]Set!F244,">0")+COUNTIF([2]Out!F244,">0")+COUNTIF([2]Nov!F244,">0")+COUNTIF([2]Dez!F244,">0"))*100)/E69) -> #VALUE! | J66: P. Limpezas % | N66: P. Limpezas %
A67: Reembolsos | B67: Quantidade | C67: Valor | D67: Média | E67: Reembolsos | F67: Quantidade | G67: Valor | H67: Média | J67: Reembolsos | K67: Quantidade | L67: Valor | M67: Média | N67: Reembolsos | O67: Quantidade | P67: Valor | Q67: Média

Sheet Gerentes
C2: BSV | D2: VSC | E2: Vendas | F2: ∆Vendas | G2: Horas | H2: Produtividade | I2: Mão obra | J2: Perdas | K2: TET | L2: R2P | M2: Reembolsos | N2: µ Reembolsos
B3: Bruna | C3: =BSV!P4 -> #DIV/0! | D3: =VSC!$D$36 -> 0 | E3: ='Gestão de Turno'!B5+'Gestão de Turno'!F5 -> 0 | F3: ='Gestão de Turno'!D5+'Gestão de Turno'!H5 -> 0 | G3: ='Gestão de Turno'!B8+'Gestão de Turno'!F8 -> 0 | H3: =E3/G3 -> #DIV/0! | I3: =(G3*6.7)/E3 -> #DIV/0! | J3: =('Gestão de Turno'!B10+'Gestão de Turno'!F10)/E3 -> #DIV/0! | K3: =R3 -> 0 | L3: =T3 -> 0 | M3: ='Gestão de Turno'!B17 -> 0 | N3: =('Gestão de Turno'!C17+'Gestão de Turno'!G17)/('Gestão de Turno'!B17+'Gestão de Turno'!F17) -> #DIV/0! | R3: {=('Gestão de Turno'!B12:C12+'Gestão de Turno'!F12:G12)/2} -> 0 | S3: 0 | T3: {=('Gestão de Turno'!B13:C13+'Gestão de Turno'!F13:G13)/2} -> 0 | U3: 0
B4: Isaac | C4: =BSV!P5 -> #DIV/0! | D4: =VSC!$D$36 -> 0 | E4: ='Gestão de Turno'!K5+'Gestão de Turno'!O5 -> 0 | F4: ='Gestão de Turno'!M5+'Gestão de Turno'!Q5 -> 0 | G4: ='Gestão de Turno'!K8+'Gestão de Turno'!O8 -> 0 | H4: =E4/G4 -> #DIV/0! | I4: =(G4*6.7)/E4 -> #DIV/0! | J4: =('Gestão de Turno'!K10+'Gestão de Turno'!O10)/E4 -> #DIV/0! | K4: =R4 -> 0 | L4: =T4 -> 0 | M4: ='Gestão de Turno'!K17 -> 0 | N4: =('Gestão de Turno'!L17+'Gestão de Turno'!O17)/('Gestão de Turno'!K17+'Gestão de Turno'!O17) -> #DIV/0! | R4: {=('Gestão de Turno'!K12:L12+'Gestão de Turno'!O12:P12)/2} -> 0 | S4: 0 | T4: {=('Gestão de Turno'!K13:L13+'Gestão de Turno'!O13:P13)/2} -> 0 | U4: 0
B5: Isabel | C5: =BSV!P6 -> #DIV/0! | D5: =VSC!$D$36 -> 0 | E5: ='Gestão de Turno'!T5+'Gestão de Turno'!X5 -> 0 | F5: ='Gestão de Turno'!V5+'Gestão de Turno'!Z5 -> 0 | G5: ='Gestão de Turno'!T8+'Gestão de Turno'!X8 -> 0 | H5: =E5/G5 -> #DIV/0! | I5: =(G5*6.7)/E5 -> #DIV/0! | J5: =('Gestão de Turno'!T10+'Gestão de Turno'!X10)/E5 -> #DIV/0! | K5: =R5 -> 0 | L5: =T5 -> 0 | M5: ='Gestão de Turno'!T17+'Gestão de Turno'!X17 -> 0 | N5: =('Gestão de Turno'!U17+'Gestão de Turno'!Y17)/('Gestão de Turno'!T17+'Gestão de Turno'!X17) -> #DIV/0! | R5: {=('Gestão de Turno'!T12:U12+'Gestão de Turno'!X12:Y12)/2} -> 0 | S5: 0 | T5: {=('Gestão de Turno'!T13:U13+'Gestão de Turno'!X13:Y13)/2} -> 0 | U5: 0
B6: Janice | C6: =BSV!P7 -> #DIV/0! | D6: =VSC!$D$36 -> 0 | E6: ='Gestão de Turno'!B22+'Gestão de Turno'!F22 -> 0 | F6: ='Gestão de Turno'!D22+'Gestão de Turno'!H22 -> 0 | G6: ='Gestão de Turno'!B25+'Gestão de Turno'!F25 -> 0 | H6: =E6/G6 -> #DIV/0! | I6: =(G6*6.7)/E6 -> #DIV/0! | J6: =('Gestão de Turno'!B27+'Gestão de Turno'!F27)/E6 -> #DIV/0! | K6: =R6 -> 0 | L6: =T6 -> 0 | M6: ='Gestão de Turno'!B34+'Gestão de Turno'!F34 -> 0 | N6: =('Gestão de Turno'!C34+'Gestão de Turno'!G34)/('Gestão de Turno'!F34+'Gestão de Turno'!B34) -> #DIV/0! | R6: {=('Gestão de Turno'!B29:C29+'Gestão de Turno'!F29:G29)/2} -> 0 | S6: 0 | T6: {=('Gestão de Turno'!B30:C30+'Gestão de Turno'!F30:G30)/2} -> 0 | U6: 0
C7: =BSV!P9 -> 0.7855 | D7: =VSC!$D$36 -> 0 | E7: ='Gestão de Turno'!K22+'Gestão de Turno'!O22 -> 0 | F7: ='Gestão de Turno'!M22+'Gestão de Turno'!Q22 -> 0 | G7: ='Gestão de Turno'!K25+'Gestão de Turno'!O25 -> 0 | H7: =E7/G7 -> #DIV/0! | I7: =(G7*6.7)/E7 -> #DIV/0! | J7: =('Gestão de Turno'!K27+'Gestão de Turno'!O27)/E7 -> #DIV/0! | K7: =R7 -> 0 | L7: =T7 -> 0 | M7: ='Gestão de Turno'!K34+'Gestão de Turno'!O34 -> 0 | N7: =('Gestão de Turno'!L34+'Gestão de Turno'!P34)/('Gestão de Turno'!K34+'Gestão de Turno'!O34) -> #DIV/0! | R7: {=('Gestão de Turno'!K29:L29+'Gestão de Turno'!O29:P29)/2} -> 0 | S7: 0 | T7: {=('Gestão de Turno'!K30:L30+'Gestão de Turno'!O30:P30)/2} -> 0 | U7: 0
B8: Uilson | C8: =BSV!P10 -> #DIV/0! | D8: =VSC!$D$36 -> 0 | E8: ='Gestão de Turno'!T22+'Gestão de Turno'!X22 -> 0 | F8: ='Gestão de Turno'!V22+'Gestão de Turno'!Z22 -> 0 | G8: ='Gestão de Turno'!T25+'Gestão de Turno'!X25 -> 0 | H8: =E8/G8 -> #DIV/0! | I8: =(G8*6.7)/E8 -> #DIV/0! | J8: =('Gestão de Turno'!T27+'Gestão de Turno'!X27)/E8 -> #DIV/0! | K8: =R8 -> 0 | L8: =T8 -> 0 | M8: ='Gestão de Turno'!T34+'Gestão de Turno'!X34 -> 0 | N8: =('Gestão de Turno'!U34+'Gestão de Turno'!Y34)/Gerentes!M8 -> #DIV/0! | R8: {=('Gestão de Turno'!T29:U29+'Gestão de Turno'!X29:Y29)/2} -> 0 | S8: 0 | T8: {=('Gestão de Turno'!T30:U30+'Gestão de Turno'!X30:Y30)/2} -> 0 | U8: 0
B9: Claudia | C9: =BSV!P11 -> #DIV/0! | D9: =VSC!$D$36 -> 0 | E9: ='Gestão de Turno'!B39+'Gestão de Turno'!F39 -> 0 | F9: =+'Gestão de Turno'!D39+'Gestão de Turno'!H39 -> 0 | G9: =+'Gestão de Turno'!B42+'Gestão de Turno'!F42 -> 0 | H9: =E9/G9 -> #DIV/0! | I9: =(G9*6.7)/E9 -> #DIV/0! | J9: =('Gestão de Turno'!B44+'Gestão de Turno'!F44)/E9 -> #DIV/0! | K9: =R9 -> 0 | L9: =T9 -> 0 | M9: ='Gestão de Turno'!B51+'Gestão de Turno'!F51 -> 0 | N9: =('Gestão de Turno'!C51+'Gestão de Turno'!G51)/Gerentes!M9 -> #DIV/0! | R9: {=('Gestão de Turno'!B46:C46+'Gestão de Turno'!F46:G46)/2} -> 0 | S9: 0 | T9: {=('Gestão de Turno'!B47:C47+'Gestão de Turno'!F47:G47)/2} -> 0 | U9: 0
B10: Hugo | C10: =BSV!P12 -> 0.867 | D10: =VSC!$D$36 -> 0 | E10: =+'Gestão de Turno'!K39+'Gestão de Turno'!O39 -> 0 | F10: =+'Gestão de Turno'!M39+'Gestão de Turno'!Q39 -> 0 | G10: =+'Gestão de Turno'!K42+'Gestão de Turno'!O42 -> 0 | H10: =E10/G10 -> #DIV/0! | I10: =(G10*6.7)/E10 -> #DIV/0! | J10: =('Gestão de Turno'!K44+'Gestão de Turno'!O44)/E10 -> #DIV/0! | K10: =R10 -> 0 | L10: =T10 -> 0 | M10: ='Gestão de Turno'!K51+'Gestão de Turno'!O51 -> 0 | N10: =('Gestão de Turno'!L51+'Gestão de Turno'!P51)/Gerentes!M10 -> #DIV/0! | R10: {=+('Gestão de Turno'!B46:C46+'Gestão de Turno'!K46:L46)/2} -> 0 | S10: 0 | T10: {=+('Gestão de Turno'!B47:B47+'Gestão de Turno'!K47:L47)/2} -> 0 | U10: 0
B11: Marília | C11: =BSV!P13 -> 0.819 | D11: =VSC!$D$36 -> 0 | E11: ='Gestão de Turno'!T39+'Gestão de Turno'!X39 -> 0 | F11: ='Gestão de Turno'!V39+'Gestão de Turno'!Z39 -> 0 | G11: ='Gestão de Turno'!X42+'Gestão de Turno'!T42 -> 0 | H11: =E11/G11 -> #DIV/0! | I11: =(G11*6.7)/E11 -> #DIV/0! | J11: =('Gestão de Turno'!T44+'Gestão de Turno'!X44)/E11 -> #DIV/0! | K11: =R11 -> 0 | L11: =T11 -> 0 | M11: ='Gestão de Turno'!T51+'Gestão de Turno'!X51 -> 0 | N11: =('Gestão de Turno'!U51+'Gestão de Turno'!Y51)/Gerentes!M11 -> #DIV/0! | R11: {=('Gestão de Turno'!T46:U46+'Gestão de Turno'!X46:Y46)/2} -> 0 | S11: 0 | T11: {=('Gestão de Turno'!T47:U47+'Gestão de Turno'!X47:Y47)/2} -> 0 | U11: 0
B12: Vitor | C12: =BSV!P14 -> 0.837 | D12: =VSC!$D$36 -> 0 | E12: ='Gestão de Turno'!B56+'Gestão de Turno'!C56 -> 0 | F12: ='Gestão de Turno'!D56+'Gestão de Turno'!H56 -> 0 | G12: =+'Gestão de Turno'!B59+'Gestão de Turno'!F59 -> 0 | H12: =E12/G12 -> #DIV/0! | I12: =(G12*6.7)/E12 -> #DIV/0! | J12: =('Gestão de Turno'!B19+'Gestão de Turno'!F19)/E12 -> #VALUE! | K12: =R12 -> 0 | L12: =T12 -> 0 | M12: ='Gestão de Turno'!B68+'Gestão de Turno'!F68 -> 0 | N12: =('Gestão de Turno'!C68+'Gestão de Turno'!G68)/Gerentes!M12 -> #DIV/0! | R12: {=('Gestão de Turno'!B63:C63+'Gestão de Turno'!F63:G63)/2} -> 0 | S12: 0 | T12: {=('Gestão de Turno'!B64:C64+'Gestão de Turno'!F64:G64)/2} -> 0 | U12: 0
B13: William | C13: =BSV!P15 -> #DIV/0! | D13: =VSC!$D$36 -> 0 | E13: ='Gestão de Turno'!K56+'Gestão de Turno'!O56 -> 0 | F13: ='Gestão de Turno'!M56+'Gestão de Turno'!Q56 -> 0 | G13: ='Gestão de Turno'!K59+'Gestão de Turno'!O59 -> 0 | H13: =E13/G13 -> #DIV/0! | I13: =(G13*6.7)/E13 -> #DIV/0! | J13: =('Gestão de Turno'!B20+'Gestão de Turno'!F20)/E13 -> #DIV/0! | K13: =R13 -> 0 | L13: =T13 -> 0 | M13: ='Gestão de Turno'!K68+'Gestão de Turno'!O68 -> 0 | N13: =('Gestão de Turno'!L68+'Gestão de Turno'!P68)/Gerentes!M13 -> #DIV/0! | R13: {=('Gestão de Turno'!K63:L63+'Gestão de Turno'!O63:P63)/2} -> 0 | S13: 0 | T13: {=+('Gestão de Turno'!K64:L64+'Gestão de Turno'!O64:P64)/2} -> 0 | U13: 0
B14: Média | C14: =AVERAGE(C3:C13) -> #DIV/0! | D14: =AVERAGE(D3:D13) -> 0 | E14: =AVERAGE(E3:E13) -> 0 | F14: =AVERAGE(F3:F13) -> 0 | G14: =AVERAGE(G3:G13) -> 0 | H14: =AVERAGE(H3:H13) -> #DIV/0! | I14: =AVERAGE(I3:I13) -> #DIV/0! | J14: =AVERAGE(J3:J13) -> #DIV/0! | ... N14: =AVERAGE(N3:N13) -> #DIV/0!

Sheet Folha1
B1: Pós Venda Nova
B2: Relativo
B3: Amadora | C3: Pborges | D3: Nacional | E3: Região | F3: Tipologia | I3: Amadora | J3: Peso
A4: Vendas Totais | B4: -0.123 | D4: 0.066 | E4: 0.02 | F4: -0.003 | H4: Vendas Totais | I4: 79182 | J4: 1
A5: Vendas Delivery | B5: -0.2051 | D5: -0.02 | E5: -0.0324 | F5: -0.0629 | H5: Vendas Delivery | I5: 39178 | J5: =I5/I4 -> 0.49478417
A6: Vendas In Store | B6: -0.077 | H6: Vendas In Store | I6: =I4-I5 -> 40004 | J6: =I6/I4 -> 0.50521583
H7: Média diária | I7: =I4/10 -> 7918.2 | J7: =(I15-I7)/I15 -> 0.102604
B9: Pré Venda Nova
B10: Relativo | I10: Absoluto
B11: Amadora | C11: Pborges | D11: Nacional | E11: Região | F11: Tipologia | I11: Amadora | J11: Pborges | K11: Nacional | L11: Região | M11: Tipologia
A12: Vendas Totais | B12: 0.1796 | H12: Vendas Totais | I12: 150000
A13: Vendas Delivery | B13: 0.2531 | H13: Vendas Delivery | I13: 81911
A14: Vendas In Store | B14: 0.052 | H14: Vendas In Store | I14: =I12-I13 -> 68089
H15: Média diária | I15: =I12/17 -> 8823.5294
B16: Pós Venda Nova
B17: Relativo | I17: Absoluto
B18: Amadora | C18: Pborges | D18: Nacional | E18: Região | F18: Tipologia | I18: Amadora | J18: Pborges | K18: Nacional | L18: Região | M18: Tipologia
A19: Almoço | B19: -0.165 | D19: 0.008 | H19: Almoço
A20: Tarde | B20: -0.061 | D20: 0.05 | H20: Tarde
A21: Jantar | B21: -0.17 | D21: -0.005 | H21: Jantar
A22: Pós Jantar | B22: 0.121 | D22: 0.006 | H22: Pós Jantar
B24: Pré Venda Nova
B25: Relativo | I25: Absoluto
B26: Amadora | C26: Pborges | D26: Nacional | E26: Região | F26: Tipologia | I26: Amadora | J26: Pborges | K26: Nacional | L26: Região | M26: Tipologia
A27: GC's Totais | B27: -0.123 | D27: -0.01 | E27: -0.025 | F27: -0.066 | H27: GC's Totais
A28: GC's Delivery | E28: -0.0559 | F28: -0.0973 | H28: GC's Delivery
A29: GC's In Store | H29: GC's In Store
